Workbook
Name dFrom: Dashboard!$B$6
Name dHost: Dashboard!$AE$4
Name dTo: Dashboard!$D$6
Name HostRoster: 'Cleaned Data'!$Z$9:$Z$13

Sheet README
B1: LIVE COMMERCE SALES PERFORMANCE ANALYSIS
A2: Excel-Based GMV Tracking, Host Performance Reporting, and Sales Analytics
B3: Prepared by John Paulo Lumagbas | Self-directed portfolio project | Entry-level Data Analyst portfolio
B6: ⚠ Portfolio project using synthetic data. Figures, hosts, and business information are fictional and do not represent any actual company's performance.
B8: PROJECT PURPOSE & BUSINESS SCENARIO
B9: Purpose: demonstrate practical, entry-level data analysis in Excel — organising business data, validating it, building accurate formulas, summarising results, and communicating insights through a dashboard. The project is inspired by my experience recording livestream sales and GMV in spreadsheets as a Livestream Assistant; it is a self-directed portfolio piece, not work product from a data analyst role.
B10: Scenario: “Sample Live Commerce Store” (fictional) runs livestream shopping sessions with five fictional hosts. Management wants to know how much GMV the sessions generate, how performance changes week to week, which hosts contribute and which are most efficient, and when sessions perform best. The dataset covers 374 synthetic sessions across 13 full weeks (Mon 02 Jun 2025 – Sun 31 Aug 2025).
B11: Tools & techniques: Microsoft Excel — Excel Tables and structured references, SUMIFS / COUNTIFS / INDEX-MATCH / RANK / CORREL / SLOPE, date and time functions, named ranges, data validation, conditional formatting, formula-driven dashboard filters, native charts. No macros, no dynamic-array functions and no add-ins are required (works in Excel 2010 or later).
B12: WORKBOOK GUIDE (click a sheet name)
B13: Raw Data | C13: Source layer: 374 synthetic session records in Excel Table tblRaw. Values only; no calculations.
B14: Cleaned Data | C14: Formula layer tblClean: standardises each raw row, derives duration, GMV per hour, week, month, slot; runs live data-quality checks and sets an Include flag.
B15: Daily Sales | C15: 91-day report: sessions, hours, GMV, items, GMV per hour, 7-day average, reconciliation to raw data, chart.
B16: Weekly Summary | C16: 13 weekly rows with week-over-week change and %, reconciliation, weekly GMV chart.
B17: Host Performance | C17: Host scorecard, documented ranking rule, host × time-slot efficiency table, weekly GMV heat-map by host.
B18: Dashboard | C18: Executive view: six KPI cards, five charts, date-range and host filters (yellow cells).
B19: Insights | C19: Eight calculated findings with why-it-matters and next steps, plus supporting tables.
B20: Flow: Raw Data → Cleaned Data (tblClean) → Daily / Weekly / Host summaries → Dashboard → Insights. Every summary reads from tblClean and counts only rows with Include = 1; each summary sheet reconciles back to Raw Data.
B21: HOW TO USE THE DASHBOARD
B22: Change the yellow cells on the Dashboard: From Date, To Date (dates between 02-Jun-2025 and 31-Aug-2025) and Host (dropdown). KPI cards, the daily trend and the weekly trend recalculate for the selected dates and host. The three host-comparison charts respond to the date range only, so all hosts stay visible for comparison. Limitation: this uses formula-driven filters rather than PivotTable slicers, so it works in any desktop Excel version without setup; weeks at the edge of a custom date range show partial totals, and charts skip days/weeks outside the range (helper cells use NA() placeholders by design).
B23: METRIC DEFINITIONS
B24: GMV | C24: Gross Merchandise Value: total value of goods sold through livestream sessions (here, “Attributed GMV”, in Philippine pesos). GMV is NOT net revenue, profit or cash received; returns, cancellations, discounts, fees and costs are not modelled.
B25: Items Sold | C25: Total units sold in a session (sum of item quantities).
B26: Livestream Duration | C26: Hours on air = (End Time − Start Time) × 24, using MOD(…,1) so sessions that cross midnight are handled.
B27: GMV per Hour | C27: Total GMV ÷ total livestream hours. Overall and per-host rates are weighted (sum ÷ sum), never an average of session-level rates, because session lengths differ.
B28: Views | C28: Number of livestream views recorded for a session.
B29: GMV per 1K Views | C29: Total GMV ÷ total views × 1,000. A sales-yield measure per 1,000 views; it is not a conversion rate.
B30: Average Order Value | C30: NOT calculated: the dataset has no order count, so AOV cannot be derived honestly.
B31: Conversion Rate | C31: NOT calculated: the dataset has no clicks, visitors or orders to use as a denominator.
B32: Weekly GMV | C32: GMV summed over a Monday–Sunday reporting week (Week Start = date − WEEKDAY(date,2) + 1).
B33: WoW Change / % | C33: Current-week GMV − previous-week GMV; % = change ÷ previous week. Shown as n/a for week 1 or when the prior week is zero/missing.
B34: Host Performance | C34: Host results measured together: total GMV (contribution), GMV per hour (efficiency), average GMV and items per session, share of GMV, and Efficiency Index (share of GMV ÷ share of hours).
B35: Time Slot | C35: Based on session start time: Morning 06–12h, Afternoon 12–16h, Early Evening 16–19h, Prime Time 19–22h, Late Night 22–06h.
B36: DATA QUALITY & DESIGN DECISIONS
B37: • Single dataset: all months live in one table instead of separate monthly tabs, so every report reads the same source.
B38: • Typed-in inputs only on Raw Data; all totals, rates and rankings are formulas (no hardcoded totals). Reports reconcile to Raw Data and show ✔ Reconciled / PASS checks.
B39: • Cleaning layer handles issues common in manual trackers: text-formatted numbers, times typed as text, inconsistent host spelling/spacing, duplicate IDs, negative or missing values, impossible durations. The synthetic sample is clean, so all checks currently read PASS; the checks are live and would flag problems in newly pasted data.
B40: • Excel functions only (no Google-Sheets-only formulas, no spill arrays). Data validation on Raw Data restricts GMV/items/views/followers to non-negative values and hosts to the roster.
B41: • Power Query alternative: Data → From Table/Range on tblRaw → Transform: trim/capitalise Host Name; set Date, Time and number types; add custom columns Duration = Duration.TotalHours(End − Start) with +1 day when End < Start, Week Start = Date.StartOfWeek(Date, Day.Monday); remove duplicates on Session ID; filter negatives → Close & Load to a table. The formula version above is used so the workbook works without any setup.
B42: DATA DICTIONARY
B43: Sheet | C43: Field | D43: Type | E43: Description | F43: How it is derived
B44: Raw Data | C44: Session ID | D44: Text | E44: Unique identifier of a livestream session (LS-0001…). | F44: Input
B45: Raw Data | C45: Date | D45: Date | E45: Calendar date the session started. | F45: Input
B46: Raw Data | C46: Host Name | D46: Text | E46: Fictional host who ran the session (five hosts). | F46: Input (dropdown validated against roster)
B47: Raw Data | C47: Start Time | D47: Time | E47: Time the session went live. | F47: Input
B48: Raw Data | C48: End Time | D48: Time | E48: Time the session ended; may be after midnight. | F48: Input
B49: Raw Data | C49: Attributed GMV PHP | D49: Currency (PHP) | E49: GMV attributed to the session, in pesos. | F49: Input (≥ 0)
B50: Raw Data | C50: Items Sold | D50: Whole number | E50: Units sold in the session. | F50: Input (≥ 0)
B51: Raw Data | C51: Livestream Views | D51: Whole number | E51: Views recorded for the session. | F51: Input (≥ 0)
B52: Raw Data | C52: New Followers | D52: Whole number | E52: Followers gained during the session. | F52: Input (≥ 0)
B53: Cleaned Data | C53: Session ID … New Followers (A–I) | D53: As raw | E53: Standardised copies of the nine raw fields. | F53: Linked to Raw Data row; TRIM/PROPER for text, INT/MOD for dates and times, VALUE for numbers stored as text
B54: Cleaned Data | C54: Duration Hours | D54: Number | E54: Hours on air. | F54: ROUND(MOD(End − Start, 1) × 24, 2)
... B71: Host Performance | C71: All columns | D71: Mixed | E71: Host totals, averages, shares, Efficiency Index, ranks, profile label. | F71: SUMIFS / COUNTIFS by Host Name; RANK
B73: Color key: blue text = typed input (host roster, dashboard filters); black = formula. Yellow cells on the Dashboard are filters.

Sheet Raw Data
A1: RAW DATA | Synthetic Livestream Session Log
A2: Source layer: values as recorded, one row per livestream session. All figures are fictional (synthetic). Add new sessions directly beneath the last row; the table expands automatically.
A4: Session ID | B4: Date | C4: Host Name | D4: Start Time | E4: End Time | F4: Attributed GMV PHP | G4: Items Sold | H4: Livestream Views | I4: New Followers
A5: LS-0001 | B5: 45810 | C5: Carlo Mendoza | D5: 0.54166667 | E5: 0.625 | F5: 32102 | G5: 85 | H5: 125767 | I5: 748
A6: LS-0002 | B6: 45810 | C6: Bianca Reyes | D6: 0.66666667 | E6: 0.79166667 | F6: 14260 | G6: 44 | H6: 53670 | I6: 396
A7: LS-0003 | B7: 45810 | C7: Aira Valdez | D7: 0.79166667 | E7: 0.89583333 | F7: 39064 | G7: 105 | H7: 121105 | I7: 1392
A8: LS-0004 | B8: 45811 | C8: Carlo Mendoza | D8: 0.41666667 | E8: 0.5 | F8: 11178 | G8: 27 | H8: 44877 | I8: 381
A9: LS-0005 | B9: 45811 | C9: Bianca Reyes | D9: 0.54166667 | E9: 0.64583333 | F9: 19147 | G9: 56 | H9: 64713 | I9: 629
A10: LS-0006 | B10: 45811 | C10: Carlo Mendoza | D10: 0.66666667 | E10: 0.77083333 | F10: 24963 | G10: 78 | H10: 77927 | I10: 344
A11: LS-0007 | B11: 45811 | C11: Aira Valdez | D11: 0.79166667 | E11: 0.89583333 | F11: 82257 | G11: 243 | H11: 216966 | I11: 1728
A12: LS-0008 | B12: 45811 | C12: Aira Valdez | D12: 0.91666667 | E12: 0.020833333 | F12: 39674 | G12: 119 | H12: 102019 | I12: 825
A13: LS-0009 | B13: 45812 | C13: Carlo Mendoza | D13: 0.66666667 | E13: 0.79166667 | F13: 25112 | G13: 73 | H13: 77728 | I13: 552
A14: LS-0010 | B14: 45812 | C14: Bianca Reyes | D14: 0.79166667 | E14: 0.89583333 | F14: 8207 | G14: 22 | H14: 27621 | I14: 298
A15: LS-0011 | B15: 45812 | C15: Dani Villanueva | D15: 0.91666667 | E15: 0.041666667 | F15: 26243 | G15: 77 | H15: 58338 | I15: 332
A16: LS-0012 | B16: 45813 | C16: Bianca Reyes | D16: 0.54166667 | E16: 0.625 | F16: 6069 | G16: 17 | H16: 20285 | I16: 262
... A378: LS-0374 | B378: 45900 | C378: Carlo Mendoza | D378: 0.91666667 | E378: 0.020833333 | F378: 51021 | G378: 139 | H378: 216876 | I378: 1414

Sheet Cleaned Data
A1: CLEANED DATA & CALCULATIONS | Formula-Driven Transformation Layer
A2: Each row links to the same row on 'Raw Data' and standardizes, derives and validates it. Every summary sheet reads from this table (tblClean), counting only rows where Include = 1.
A3: DATA QUALITY CHECKS (live formulas — all should read PASS)
A4: Raw rows vs cleaned rows | B4: Missing or non-numeric values | C4: Duplicate Session IDs | D4: Negative GMV / items / views / followers | E4: Invalid durations (≤0h or >12h) | F4: Host names not on roster | G4: Rows included in analysis | H4: GMV: raw minus included (PHP) | I4: Items: raw minus included
A5: =ROWS(tblRaw[Session ID]) -> 374 | B5: =SUM(tblClean[Missing Flag]) -> 0 | C5: =SUM(tblClean[Duplicate Flag]) -> 0 | D5: =SUM(tblClean[Negative Flag]) -> 0 | E5: =SUM(tblClean[Duration Flag]) -> 0 | F5: =SUM(tblClean[Host Flag]) -> 0 | G5: =SUM(tblClean[Include]) -> 374 | H5: =SUM(tblRaw[Attributed GMV PHP])-SUMIFS(tblClean[Attributed GMV PHP],tblClean[Include],1) -> 0 | I5: =SUM(tblRaw[Items Sold])-SUMIFS(tblClean[Items Sold],tblClean[Include],1) -> 0
A6: =IF(A5=ROWS(tblClean[Session ID]),"PASS","REVIEW") -> PASS | B6: =IF(B5=0,"PASS","REVIEW") -> PASS | C6: =IF(C5=0,"PASS","REVIEW") -> PASS | D6: =IF(D5=0,"PASS","REVIEW") -> PASS | E6: =IF(E5=0,"PASS","REVIEW") -> PASS | F6: =IF(F5=0,"PASS","REVIEW") -> PASS | G6: =IF(G5=ROWS(tblRaw[Session ID]),"PASS","REVIEW") -> PASS | H6: =IF(ROUND(H5,2)=0,"PASS","REVIEW") -> PASS | I6: =IF(I5=0,"PASS","REVIEW") -> PASS
A7: Rule: a row counts toward analysis only if none of the five flag columns (S–W) equals 1. If duplicate IDs exist, every row sharing the ID is held out for review.
A8: Session ID | B8: Date | C8: Host Name | D8: Start Time | E8: End Time | F8: Attributed GMV PHP | G8: Items Sold | H8: Livestream Views | I8: New Followers | J8: Duration Hours | K8: GMV per Hour | L8: Month | M8: Week Start | N8: Week Number | O8: Day of Week | P8: Day Type | Q8: Time Slot | R8: Duration Band | S8: Missing Flag | T8: Duplicate Flag | U8: Negative Flag | V8: Duration Flag | W8: Host Flag | X8: Include | Z8: Host Roster
A9: =TRIM('Raw Data'!A5) -> LS-0001 | B9: =IF(ISNUMBER('Raw Data'!B5),INT('Raw Data'!B5),IFERROR(DATEVALUE('Raw Data'!B5),"")) -> 45810 | C9: =PROPER(TRIM('Raw Data'!C5)) -> Carlo Mendoza | D9: =IF(ISNUMBER('Raw Data'!D5),MOD('Raw Data'!D5,1),IFERROR(TIMEVALUE('Raw Data'!D5),"")) -> 0.54166667 | E9: =IF(ISNUMBER('Raw Data'!E5),MOD('Raw Data'!E5,1),IFERROR(TIMEVALUE('Raw Data'!E5),"")) -> 0.625 | F9: =IF(ISNUMBER('Raw Data'!F5),'Raw Data'!F5,IFERROR(VALUE(SUBSTITUTE('Raw Data'!F5,",","")),"")) -> 32102 | G9: =IF(ISNUMBER('Raw Data'!G5),'Raw Data'!G5,IFERROR(VALUE(SUBSTITUTE('Raw Data'!G5,",","")),"")) -> 85 | H9: =IF(ISNUMBER('Raw Data'!H5),'Raw Data'!H5,IFERROR(VALUE(SUBSTITUTE('Raw Data'!H5,",","")),"")) -> 125767 | I9: =IF(ISNUMBER('Raw Data'!I5),'Raw Data'!I5,IFERROR(VALUE(SUBSTITUTE('Raw Data'!I5,",","")),"")) -> 748 | J9: =IF(AND(ISNUMBER(tblClean[[#This Row],[Start Time]]),ISNUMBER(tblClean[[#This Row],[End Time]])),ROUND(MOD(tblClean[[#This Row],[End Time]]-tblClean[[#This Row],[Start Time]],1)*24,2),"") -> 2 | K9: =IF(AND(ISNUMBER(tblClean[[#This Row],[Duration Hours]]),ISNUMBER(tblClean[[#This Row],[Attributed GMV PHP]])),IF(tblClean[[#This Row],[Duration Hours]]>0,tblClean[[#This Row],[Attributed GMV PHP]]/tblClean[[#This Row],[Duration Hours]],""),"") -> 16051 | L9: =IF(ISNUMBER(tblClean[[#This Row],[Date]]),DATE(YEAR(tblClean[[#This Row],[Date]]),MONTH(tblClean[[#This Row],[Date]]),1),"") -> 45809 | M9: =IF(ISNUMBER(tblClean[[#This Row],[Date]]),tblClean[[#This Row],[Date]]-WEEKDAY(tblClean[[#This Row],[Date]],2)+1,"") -> 45810 | N9: =IF(ISNUMBER(tblClean[[#This Row],[Week Start]]),(tblClean[[#This Row],[Week Start]]-MIN(tblClean[Week Start]))/7+1,"") -> 1 | O9: =IF(ISNUMBER(tblClean[[#This Row],[Date]]),CHOOSE(WEEKDAY(tblClean[[#This Row],[Date]],2),"Mon","Tue","Wed","Thu","Fri","Sat","Sun"),"") -> Mon | P9: =IF(ISNUMBER(tblClean[[#This Row],[Date]]),IF(WEEKDAY(tblClean[[#This Row],[Date]],2)>=6,"Weekend","Weekday"),"") -> Weekday | Q9: =IF(ISNUMBER(tblClean[[#This Row],[Start Time]]),IF(tblClean[[#This Row],[Start Time]]<TIME(6,0,0),"Late Night",IF(tblClean[[#This Row],[Start Time]]<TIME(12,0,0),"Morning",IF(tblClean[[#This Row],[Start Time]]<TIME(16,0,0),"Afternoon",IF(tblClean[[#This Row],[Start Time]]<TIME(19,0,0),"Early Evening",IF(tblClean[[#This Row],[Start Time]]<TIME(22,0,0),"Prime Time","Late Night"))))),"") -> Afternoon | R9: =IF(ISNUMBER(tblClean[[#This Row],[Duration Hours]]),IF(tblClean[[#This Row],[Duration Hours]]<2,"Short (under 2h)",IF(tblClean[[#This Row],[Duration Hours]]<3,"Standard (2h to under 3h)","Long (3h or more)")),"") -> Standard (2h to under 3h) | S9: =IF(OR(NOT(ISNUMBER(tblClean[[#This Row],[Date]])),NOT(ISNUMBER(tblClean[[#This Row],[Start Time]])),NOT(ISNUMBER(tblClean[[#This Row],[End Time]])),NOT(ISNUMBER(tblClean[[#This Row],[Attributed GMV PHP]])),NOT(ISNUMBER(tblClean[[#This Row],[Items Sold]])),NOT(ISNUMBER(tblClean[[#This Row],[Livestream Views]])),NOT(ISNUMBER(tblClean[[#This Row],[New Followers]])),tblClean[[#This Row],[Host Name]]="",tblClean[[#This Row],[Session ID]]=""),1,0) -> 0 | T9: =IF(COUNTIF(tblClean[Session ID],tblClean[[#This Row],[Session ID]])>1,1,0) -> 0 | U9: =IF(OR(N(tblClean[[#This Row],[Attributed GMV PHP]])<0,N(tblClean[[#This Row],[Items Sold]])<0,N(tblClean[[#This Row],[Livestream Views]])<0,N(tblClean[[#This Row],[New Followers]])<0),1,0) -> 0 | V9: =IF(ISNUMBER(tblClean[[#This Row],[Duration Hours]]),IF(OR(tblClean[[#This Row],[Duration Hours]]<=0,tblClean[[#This Row],[Duration Hours]]>12),1,0),1) -> 0 | W9: =IF(COUNTIF(HostRoster,tblClean[[#This Row],[Host Name]])=0,1,0) -> 0 | X9: =IF(tblClean[[#This Row],[Missing Flag]]+tblClean[[#This Row],[Duplicate Flag]]+tblClean[[#This Row],[Negative Flag]]+tblClean[[#This Row],[Duration Flag]]+tblClean[[#This Row],[Host Flag]]=0,1,0) -> 1 | Z9: Aira Valdez
A10: =TRIM('Raw Data'!A6) -> LS-0002 | B10: =IF(ISNUMBER('Raw Data'!B6),INT('Raw Data'!B6),IFERROR(DATEVALUE('Raw Data'!B6),"")) -> 45810 | C10: =PROPER(TRIM('Raw Data'!C6)) -> Bianca Reyes | D10: =IF(ISNUMBER('Raw Data'!D6),MOD('Raw Data'!D6,1),IFERROR(TIMEVALUE('Raw Data'!D6),"")) -> 0.66666667 | E10: =IF(ISNUMBER('Raw Data'!E6),MOD('Raw Data'!E6,1),IFERROR(TIMEVALUE('Raw Data'!E6),"")) -> 0.79166667 | F10: =IF(ISNUMBER('Raw Data'!F6),'Raw Data'!F6,IFERROR(VALUE(SUBSTITUTE('Raw Data'!F6,",","")),"")) -> 14260 | G10: =IF(ISNUMBER('Raw Data'!G6),'Raw Data'!G6,IFERROR(VALUE(SUBSTITUTE('Raw Data'!G6,",","")),"")) -> 44 | H10: =IF(ISNUMBER('Raw Data'!H6),'Raw Data'!H6,IFERROR(VALUE(SUBSTITUTE('Raw Data'!H6,",","")),"")) -> 53670 | I10: =IF(ISNUMBER('Raw Data'!I6),'Raw Data'!I6,IFERROR(VALUE(SUBSTITUTE('Raw Data'!I6,",","")),"")) -> 396 | J10: =IF(AND(ISNUMBER(tblClean[[#This Row],[Start Time]]),ISNUMBER(tblClean[[#This Row],[End Time]])),ROUND(MOD(tblClean[[#This Row],[End Time]]-tblClean[[#This Row],[Start Time]],1)*24,2),"") -> 3 | K10: =IF(AND(ISNUMBER(tblClean[[#This Row],[Duration Hours]]),ISNUMBER(tblClean[[#This Row],[Attributed GMV PHP]])),IF(tblClean[[#This Row],[Duration Hours]]>0,tblClean[[#This Row],[Attributed GMV PHP]]/tblClean[[#This Row],[Duration Hours]],""),"") -> 4753.3333 | L10: =IF(ISNUMBER(tblClean[[#This Row],[Date]]),DATE(YEAR(tblClean[[#This Row],[Date]]),MONTH(tblClean[[#This Row],[Date]]),1),"") -> 45809 | M10: =IF(ISNUMBER(tblClean[[#This Row],[Date]]),tblClean[[#This Row],[Date]]-WEEKDAY(tblClean[[#This Row],[Date]],2)+1,"") -> 45810 | N10: =IF(ISNUMBER(tblClean[[#This Row],[Week Start]]),(tblClean[[#This Row],[Week Start]]-MIN(tblClean[Week Start]))/7+1,"") -> 1 | O10: =IF(ISNUMBER(tblClean[[#This Row],[Date]]),CHOOSE(WEEKDAY(tblClean[[#This Row],[Date]],2),"Mon","Tue","Wed","Thu","Fri","Sat","Sun"),"") -> Mon | P10: =IF(ISNUMBER(tblClean[[#This Row],[Date]]),IF(WEEKDAY(tblClean[[#This Row],[Date]],2)>=6,"Weekend","Weekday"),"") -> Weekday | Q10: =IF(ISNUMBER(tblClean[[#This Row],[Start Time]]),IF(tblClean[[#This Row],[Start Time]]<TIME(6,0,0),"Late Night",IF(tblClean[[#This Row],[Start Time]]<TIME(12,0,0),"Morning",IF(tblClean[[#This Row],[Start Time]]<TIME(16,0,0),"Afternoon",IF(tblClean[[#This Row],[Start Time]]<TIME(19,0,0),"Early Evening",IF(tblClean[[#This Row],[Start Time]]<TIME(22,0,0),"Prime Time","Late Night"))))),"") -> Early Evening | R10: =IF(ISNUMBER(tblClean[[#This Row],[Duration Hours]]),IF(tblClean[[#This Row],[Duration Hours]]<2,"Short (under 2h)",IF(tblClean[[#This Row],[Duration Hours]]<3,"Standard (2h to under 3h)","Long (3h or more)")),"") -> Long (3h or more) | S10: =IF(OR(NOT(ISNUMBER(tblClean[[#This Row],[Date]])),NOT(ISNUMBER(tblClean[[#This Row],[Start Time]])),NOT(ISNUMBER(tblClean[[#This Row],[End Time]])),NOT(ISNUMBER(tblClean[[#This Row],[Attributed GMV PHP]])),NOT(ISNUMBER(tblClean[[#This Row],[Items Sold]])),NOT(ISNUMBER(tblClean[[#This Row],[Livestream Views]])),NOT(ISNUMBER(tblClean[[#This Row],[New Followers]])),tblClean[[#This Row],[Host Name]]="",tblClean[[#This Row],[Session ID]]=""),1,0) -> 0 | T10: =IF(COUNTIF(tblClean[Session ID],tblClean[[#This Row],[Session ID]])>1,1,0) -> 0 | U10: =IF(OR(N(tblClean[[#This Row],[Attributed GMV PHP]])<0,N(tblClean[[#This Row],[Items Sold]])<0,N(tblClean[[#This Row],[Livestream Views]])<0,N(tblClean[[#This Row],[New Followers]])<0),1,0) -> 0 | V10: =IF(ISNUMBER(tblClean[[#This Row],[Duration Hours]]),IF(OR(tblClean[[#This Row],[Duration Hours]]<=0,tblClean[[#This Row],[Duration Hours]]>12),1,0),1) -> 0 | W10: =IF(COUNTIF(HostRoster,tblClean[[#This Row],[Host Name]])=0,1,0) -> 0 | X10: =IF(tblClean[[#This Row],[Missing Flag]]+tblClean[[#This Row],[Duplicate Flag]]+tblClean[[#This Row],[Negative Flag]]+tblClean[[#This Row],[Duration Flag]]+tblClean[[#This Row],[Host Flag]]=0,1,0) -> 1 | Z10: Bianca Reyes
A11: =TRIM('Raw Data'!A7) -> LS-0003 | B11: =IF(ISNUMBER('Raw Data'!B7),INT('Raw Data'!B7),IFERROR(DATEVALUE('Raw Data'!B7),"")) -> 45810 | C11: =PROPER(TRIM('Raw Data'!C7)) -> Aira Valdez | D11: =IF(ISNUMBER('Raw Data'!D7),MOD('Raw Data'!D7,1),IFERROR(TIMEVALUE('Raw Data'!D7),"")) -> 0.79166667 | E11: =IF(ISNUMBER('Raw Data'!E7),MOD('Raw Data'!E7,1),IFERROR(TIMEVALUE('Raw Data'!E7),"")) -> 0.89583333 | F11: =IF(ISNUMBER('Raw Data'!F7),'Raw Data'!F7,IFERROR(VALUE(SUBSTITUTE('Raw Data'!F7,",","")),"")) -> 39064 | G11: =IF(ISNUMBER('Raw Data'!G7),'Raw Data'!G7,IFERROR(VALUE(SUBSTITUTE('Raw Data'!G7,",","")),"")) -> 105 | H11: =IF(ISNUMBER('Raw Data'!H7),'Raw Data'!H7,IFERROR(VALUE(SUBSTITUTE('Raw Data'!H7,",","")),"")) -> 121105 | I11: =IF(ISNUMBER('Raw Data'!I7),'Raw Data'!I7,IFERROR(VALUE(SUBSTITUTE('Raw Data'!I7,",","")),"")) -> 1392 | J11: =IF(AND(ISNUMBER(tblClean[[#This Row],[Start Time]]),ISNUMBER(tblClean[[#This Row],[End Time]])),ROUND(MOD(tblClean[[#This Row],[End Time]]-tblClean[[#This Row],[Start Time]],1)*24,2),"") -> 2.5 | K11: =IF(AND(ISNUMBER(tblClean[[#This Row],[Duration Hours]]),ISNUMBER(tblClean[[#This Row],[Attributed GMV PHP]])),IF(tblClean[[#This Row],[Duration Hours]]>0,tblClean[[#This Row],[Attributed GMV PHP]]/tblClean[[#This Row],[Duration Hours]],""),"") -> 15625.6 | L11: =IF(ISNUMBER(tblClean[[#This Row],[Date]]),DATE(YEAR(tblClean[[#This Row],[Date]]),MONTH(tblClean[[#This Row],[Date]]),1),"") -> 45809 | M11: =IF(ISNUMBER(tblClean[[#This Row],[Date]]),tblClean[[#This Row],[Date]]-WEEKDAY(tblClean[[#This Row],[Date]],2)+1,"") -> 45810 | N11: =IF(ISNUMBER(tblClean[[#This Row],[Week Start]]),(tblClean[[#This Row],[Week Start]]-MIN(tblClean[Week Start]))/7+1,"") -> 1 | O11: =IF(ISNUMBER(tblClean[[#This Row],[Date]]),CHOOSE(WEEKDAY(tblClean[[#This Row],[Date]],2),"Mon","Tue","Wed","Thu","Fri","Sat","Sun"),"") -> Mon | P11: =IF(ISNUMBER(tblClean[[#This Row],[Date]]),IF(WEEKDAY(tblClean[[#This Row],[Date]],2)>=6,"Weekend","Weekday"),"") -> Weekday | Q11: =IF(ISNUMBER(tblClean[[#This Row],[Start Time]]),IF(tblClean[[#This Row],[Start Time]]<TIME(6,0,0),"Late Night",IF(tblClean[[#This Row],[Start Time]]<TIME(12,0,0),"Morning",IF(tblClean[[#This Row],[Start Time]]<TIME(16,0,0),"Afternoon",IF(tblClean[[#This Row],[Start Time]]<TIME(19,0,0),"Early Evening",IF(tblClean[[#This Row],[Start Time]]<TIME(22,0,0),"Prime Time","Late Night"))))),"") -> Prime Time | R11: =IF(ISNUMBER(tblClean[[#This Row],[Duration Hours]]),IF(tblClean[[#This Row],[Duration Hours]]<2,"Short (under 2h)",IF(tblClean[[#This Row],[Duration Hours]]<3,"Standard (2h to under 3h)","Long (3h or more)")),"") -> Standard (2h to under 3h) | S11: =IF(OR(NOT(ISNUMBER(tblClean[[#This Row],[Date]])),NOT(ISNUMBER(tblClean[[#This Row],[Start Time]])),NOT(ISNUMBER(tblClean[[#This Row],[End Time]])),NOT(ISNUMBER(tblClean[[#This Row],[Attributed GMV PHP]])),NOT(ISNUMBER(tblClean[[#This Row],[Items Sold]])),NOT(ISNUMBER(tblClean[[#This Row],[Livestream Views]])),NOT(ISNUMBER(tblClean[[#This Row],[New Followers]])),tblClean[[#This Row],[Host Name]]="",tblClean[[#This Row],[Session ID]]=""),1,0) -> 0 | T11: =IF(COUNTIF(tblClean[Session ID],tblClean[[#This Row],[Session ID]])>1,1,0) -> 0 | U11: =IF(OR(N(tblClean[[#This Row],[Attributed GMV PHP]])<0,N(tblClean[[#This Row],[Items Sold]])<0,N(tblClean[[#This Row],[Livestream Views]])<0,N(tblClean[[#This Row],[New Followers]])<0),1,0) -> 0 | V11: =IF(ISNUMBER(tblClean[[#This Row],[Duration Hours]]),IF(OR(tblClean[[#This Row],[Duration Hours]]<=0,tblClean[[#This Row],[Duration Hours]]>12),1,0),1) -> 0 | W11: =IF(COUNTIF(HostRoster,tblClean[[#This Row],[Host Name]])=0,1,0) -> 0 | X11: =IF(tblClean[[#This Row],[Missing Flag]]+tblClean[[#This Row],[Duplicate Flag]]+tblClean[[#This Row],[Negative Flag]]+tblClean[[#This Row],[Duration Flag]]+tblClean[[#This Row],[Host Flag]]=0,1,0) -> 1 | Z11: Carlo Mendoza
A12: =TRIM('Raw Data'!A8) -> LS-0004 | B12: =IF(ISNUMBER('Raw Data'!B8),INT('Raw Data'!B8),IFERROR(DATEVALUE('Raw Data'!B8),"")) -> 45811 | C12: =PROPER(TRIM('Raw Data'!C8)) -> Carlo Mendoza | D12: =IF(ISNUMBER('Raw Data'!D8),MOD('Raw Data'!D8,1),IFERROR(TIMEVALUE('Raw Data'!D8),"")) -> 0.41666667 | E12: =IF(ISNUMBER('Raw Data'!E8),MOD('Raw Data'!E8,1),IFERROR(TIMEVALUE('Raw Data'!E8),"")) -> 0.5 | F12: =IF(ISNUMBER('Raw Data'!F8),'Raw Data'!F8,IFERROR(VALUE(SUBSTITUTE('Raw Data'!F8,",","")),"")) -> 11178 | G12: =IF(ISNUMBER('Raw Data'!G8),'Raw Data'!G8,IFERROR(VALUE(SUBSTITUTE('Raw Data'!G8,",","")),"")) -> 27 | H12: =IF(ISNUMBER('Raw Data'!H8),'Raw Data'!H8,IFERROR(VALUE(SUBSTITUTE('Raw Data'!H8,",","")),"")) -> 44877 | I12: =IF(ISNUMBER('Raw Data'!I8),'Raw Data'!I8,IFERROR(VALUE(SUBSTITUTE('Raw Data'!I8,",","")),"")) -> 381 | J12: =IF(AND(ISNUMBER(tblClean[[#This Row],[Start Time]]),ISNUMBER(tblClean[[#This Row],[End Time]])),ROUND(MOD(tblClean[[#This Row],[End Time]]-tblClean[[#This Row],[Start Time]],1)*24,2),"") -> 2 | K12: =IF(AND(ISNUMBER(tblClean[[#This Row],[Duration Hours]]),ISNUMBER(tblClean[[#This Row],[Attributed GMV PHP]])),IF(tblClean[[#This Row],[Duration Hours]]>0,tblClean[[#This Row],[Attributed GMV PHP]]/tblClean[[#This Row],[Duration Hours]],""),"") -> 5589 | L12: =IF(ISNUMBER(tblClean[[#This Row],[Date]]),DATE(YEAR(tblClean[[#This Row],[Date]]),MONTH(tblClean[[#This Row],[Date]]),1),"") -> 45809 | M12: =IF(ISNUMBER(tblClean[[#This Row],[Date]]),tblClean[[#This Row],[Date]]-WEEKDAY(tblClean[[#This Row],[Date]],2)+1,"") -> 45810 | N12: =IF(ISNUMBER(tblClean[[#This Row],[Week Start]]),(tblClean[[#This Row],[Week Start]]-MIN(tblClean[Week Start]))/7+1,"") -> 1 | O12: =IF(ISNUMBER(tblClean[[#This Row],[Date]]),CHOOSE(WEEKDAY(tblClean[[#This Row],[Date]],2),"Mon","Tue","Wed","Thu","Fri","Sat","Sun"),"") -> Tue | P12: =IF(ISNUMBER(tblClean[[#This Row],[Date]]),IF(WEEKDAY(tblClean[[#This Row],[Date]],2)>=6,"Weekend","Weekday"),"") -> Weekday | Q12: =IF(ISNUMBER(tblClean[[#This Row],[Start Time]]),IF(tblClean[[#This Row],[Start Time]]<TIME(6,0,0),"Late Night",IF(tblClean[[#This Row],[Start Time]]<TIME(12,0,0),"Morning",IF(tblClean[[#This Row],[Start Time]]<TIME(16,0,0),"Afternoon",IF(tblClean[[#This Row],[Start Time]]<TIME(19,0,0),"Early Evening",IF(tblClean[[#This Row],[Start Time]]<TIME(22,0,0),"Prime Time","Late Night"))))),"") -> Morning | R12: =IF(ISNUMBER(tblClean[[#This Row],[Duration Hours]]),IF(tblClean[[#This Row],[Duration Hours]]<2,"Short (under 2h)",IF(tblClean[[#This Row],[Duration Hours]]<3,"Standard (2h to under 3h)","Long (3h or more)")),"") -> Standard (2h to under 3h) | S12: =IF(OR(NOT(ISNUMBER(tblClean[[#This Row],[Date]])),NOT(ISNUMBER(tblClean[[#This Row],[Start Time]])),NOT(ISNUMBER(tblClean[[#This Row],[End Time]])),NOT(ISNUMBER(tblClean[[#This Row],[Attributed GMV PHP]])),NOT(ISNUMBER(tblClean[[#This Row],[Items Sold]])),NOT(ISNUMBER(tblClean[[#This Row],[Livestream Views]])),NOT(ISNUMBER(tblClean[[#This Row],[New Followers]])),tblClean[[#This Row],[Host Name]]="",tblClean[[#This Row],[Session ID]]=""),1,0) -> 0 | T12: =IF(COUNTIF(tblClean[Session ID],tblClean[[#This Row],[Session ID]])>1,1,0) -> 0 | U12: =IF(OR(N(tblClean[[#This Row],[Attributed GMV PHP]])<0,N(tblClean[[#This Row],[Items Sold]])<0,N(tblClean[[#This Row],[Livestream Views]])<0,N(tblClean[[#This Row],[New Followers]])<0),1,0) -> 0 | V12: =IF(ISNUMBER(tblClean[[#This Row],[Duration Hours]]),IF(OR(tblClean[[#This Row],[Duration Hours]]<=0,tblClean[[#This Row],[Duration Hours]]>12),1,0),1) -> 0 | W12: =IF(COUNTIF(HostRoster,tblClean[[#This Row],[Host Name]])=0,1,0) -> 0 | X12: =IF(tblClean[[#This Row],[Missing Flag]]+tblClean[[#This Row],[Duplicate Flag]]+tblClean[[#This Row],[Negative Flag]]+tblClean[[#This Row],[Duration Flag]]+tblClean[[#This Row],[Host Flag]]=0,1,0) -> 1 | Z12: Dani Villanueva
A13: =TRIM('Raw Data'!A9) -> LS-0005 | B13: =IF(ISNUMBER('Raw Data'!B9),INT('Raw Data'!B9),IFERROR(DATEVALUE('Raw Data'!B9),"")) -> 45811 | C13: =PROPER(TRIM('Raw Data'!C9)) -> Bianca Reyes | D13: =IF(ISNUMBER('Raw Data'!D9),MOD('Raw Data'!D9,1),IFERROR(TIMEVALUE('Raw Data'!D9),"")) -> 0.54166667 | E13: =IF(ISNUMBER('Raw Data'!E9),MOD('Raw Data'!E9,1),IFERROR(TIMEVALUE('Raw Data'!E9),"")) -> 0.64583333 | F13: =IF(ISNUMBER('Raw Data'!F9),'Raw Data'!F9,IFERROR(VALUE(SUBSTITUTE('Raw Data'!F9,",","")),"")) -> 19147 | G13: =IF(ISNUMBER('Raw Data'!G9),'Raw Data'!G9,IFERROR(VALUE(SUBSTITUTE('Raw Data'!G9,",","")),"")) -> 56 | H13: =IF(ISNUMBER('Raw Data'!H9),'Raw Data'!H9,IFERROR(VALUE(SUBSTITUTE('Raw Data'!H9,",","")),"")) -> 64713 | I13: =IF(ISNUMBER('Raw Data'!I9),'Raw Data'!I9,IFERROR(VALUE(SUBSTITUTE('Raw Data'!I9,",","")),"")) -> 629 | J13: =IF(AND(ISNUMBER(tblClean[[#This Row],[Start Time]]),ISNUMBER(tblClean[[#This Row],[End Time]])),ROUND(MOD(tblClean[[#This Row],[End Time]]-tblClean[[#This Row],[Start Time]],1)*24,2),"") -> 2.5 | K13: =IF(AND(ISNUMBER(tblClean[[#This Row],[Duration Hours]]),ISNUMBER(tblClean[[#This Row],[Attributed GMV PHP]])),IF(tblClean[[#This Row],[Duration Hours]]>0,tblClean[[#This Row],[Attributed GMV PHP]]/tblClean[[#This Row],[Duration Hours]],""),"") -> 7658.8 | L13: =IF(ISNUMBER(tblClean[[#This Row],[Date]]),DATE(YEAR(tblClean[[#This Row],[Date]]),MONTH(tblClean[[#This Row],[Date]]),1),"") -> 45809 | M13: =IF(ISNUMBER(tblClean[[#This Row],[Date]]),tblClean[[#This Row],[Date]]-WEEKDAY(tblClean[[#This Row],[Date]],2)+1,"") -> 45810 | N13: =IF(ISNUMBER(tblClean[[#This Row],[Week Start]]),(tblClean[[#This Row],[Week Start]]-MIN(tblClean[Week Start]))/7+1,"") -> 1 | O13: =IF(ISNUMBER(tblClean[[#This Row],[Date]]),CHOOSE(WEEKDAY(tblClean[[#This Row],[Date]],2),"Mon","Tue","Wed","Thu","Fri","Sat","Sun"),"") -> Tue | P13: =IF(ISNUMBER(tblClean[[#This Row],[Date]]),IF(WEEKDAY(tblClean[[#This Row],[Date]],2)>=6,"Weekend","Weekday"),"") -> Weekday | Q13: =IF(ISNUMBER(tblClean[[#This Row],[Start Time]]),IF(tblClean[[#This Row],[Start Time]]<TIME(6,0,0),"Late Night",IF(tblClean[[#This Row],[Start Time]]<TIME(12,0,0),"Morning",IF(tblClean[[#This Row],[Start Time]]<TIME(16,0,0),"Afternoon",IF(tblClean[[#This Row],[Start Time]]<TIME(19,0,0),"Early Evening",IF(tblClean[[#This Row],[Start Time]]<TIME(22,0,0),"Prime Time","Late Night"))))),"") -> Afternoon | R13: =IF(ISNUMBER(tblClean[[#This Row],[Duration Hours]]),IF(tblClean[[#This Row],[Duration Hours]]<2,"Short (under 2h)",IF(tblClean[[#This Row],[Duration Hours]]<3,"Standard (2h to under 3h)","Long (3h or more)")),"") -> Standard (2h to under 3h) | S13: =IF(OR(NOT(ISNUMBER(tblClean[[#This Row],[Date]])),NOT(ISNUMBER(tblClean[[#This Row],[Start Time]])),NOT(ISNUMBER(tblClean[[#This Row],[End Time]])),NOT(ISNUMBER(tblClean[[#This Row],[Attributed GMV PHP]])),NOT(ISNUMBER(tblClean[[#This Row],[Items Sold]])),NOT(ISNUMBER(tblClean[[#This Row],[Livestream Views]])),NOT(ISNUMBER(tblClean[[#This Row],[New Followers]])),tblClean[[#This Row],[Host Name]]="",tblClean[[#This Row],[Session ID]]=""),1,0) -> 0 | T13: =IF(COUNTIF(tblClean[Session ID],tblClean[[#This Row],[Session ID]])>1,1,0) -> 0 | U13: =IF(OR(N(tblClean[[#This Row],[Attributed GMV PHP]])<0,N(tblClean[[#This Row],[Items Sold]])<0,N(tblClean[[#This Row],[Livestream Views]])<0,N(tblClean[[#This Row],[New Followers]])<0),1,0) -> 0 | V13: =IF(ISNUMBER(tblClean[[#This Row],[Duration Hours]]),IF(OR(tblClean[[#This Row],[Duration Hours]]<=0,tblClean[[#This Row],[Duration Hours]]>12),1,0),1) -> 0 | W13: =IF(COUNTIF(HostRoster,tblClean[[#This Row],[Host Name]])=0,1,0) -> 0 | X13: =IF(tblClean[[#This Row],[Missing Flag]]+tblClean[[#This Row],[Duplicate Flag]]+tblClean[[#This Row],[Negative Flag]]+tblClean[[#This Row],[Duration Flag]]+tblClean[[#This Row],[Host Flag]]=0,1,0) -> 1 | Z13: Elise Navarro
A14: =TRIM('Raw Data'!A10) -> LS-0006 | B14: =IF(ISNUMBER('Raw Data'!B10),INT('Raw Data'!B10),IFERROR(DATEVALUE('Raw Data'!B10),"")) -> 45811 | C14: =PROPER(TRIM('Raw Data'!C10)) -> Carlo Mendoza | D14: =IF(ISNUMBER('Raw Data'!D10),MOD('Raw Data'!D10,1),IFERROR(TIMEVALUE('Raw Data'!D10),"")) -> 0.66666667 | E14: =IF(ISNUMBER('Raw Data'!E10),MOD('Raw Data'!E10,1),IFERROR(TIMEVALUE('Raw Data'!E10),"")) -> 0.77083333 | F14: =IF(ISNUMBER('Raw Data'!F10),'Raw Data'!F10,IFERROR(VALUE(SUBSTITUTE('Raw Data'!F10,",","")),"")) -> 24963 | G14: =IF(ISNUMBER('Raw Data'!G10),'Raw Data'!G10,IFERROR(VALUE(SUBSTITUTE('Raw Data'!G10,",","")),"")) -> 78 | H14: =IF(ISNUMBER('Raw Data'!H10),'Raw Data'!H10,IFERROR(VALUE(SUBSTITUTE('Raw Data'!H10,",","")),"")) -> 77927 | I14: =IF(ISNUMBER('Raw Data'!I10),'Raw Data'!I10,IFERROR(VALUE(SUBSTITUTE('Raw Data'!I10,",","")),"")) -> 344 | J14: =IF(AND(ISNUMBER(tblClean[[#This Row],[Start Time]]),ISNUMBER(tblClean[[#This Row],[End Time]])),ROUND(MOD(tblClean[[#This Row],[End Time]]-tblClean[[#This Row],[Start Time]],1)*24,2),"") -> 2.5 | K14: =IF(AND(ISNUMBER(tblClean[[#This Row],[Duration Hours]]),ISNUMBER(tblClean[[#This Row],[Attributed GMV PHP]])),IF(tblClean[[#This Row],[Duration Hours]]>0,tblClean[[#This Row],[Attributed GMV PHP]]/tblClean[[#This Row],[Duration Hours]],""),"") -> 9985.2 | L14: =IF(ISNUMBER(tblClean[[#This Row],[Date]]),DATE(YEAR(tblClean[[#This Row],[Date]]),MONTH(tblClean[[#This Row],[Date]]),1),"") -> 45809 | M14: =IF(ISNUMBER(tblClean[[#This Row],[Date]]),tblClean[[#This Row],[Date]]-WEEKDAY(tblClean[[#This Row],[Date]],2)+1,"") -> 45810 | N14: =IF(ISNUMBER(tblClean[[#This Row],[Week Start]]),(tblClean[[#This Row],[Week Start]]-MIN(tblClean[Week Start]))/7+1,"") -> 1 | O14: =IF(ISNUMBER(tblClean[[#This Row],[Date]]),CHOOSE(WEEKDAY(tblClean[[#This Row],[Date]],2),"Mon","Tue","Wed","Thu","Fri","Sat","Sun"),"") -> Tue | P14: =IF(ISNUMBER(tblClean[[#This Row],[Date]]),IF(WEEKDAY(tblClean[[#This Row],[Date]],2)>=6,"Weekend","Weekday"),"") -> Weekday | Q14: =IF(ISNUMBER(tblClean[[#This Row],[Start Time]]),IF(tblClean[[#This Row],[Start Time]]<TIME(6,0,0),"Late Night",IF(tblClean[[#This Row],[Start Time]]<TIME(12,0,0),"Morning",IF(tblClean[[#This Row],[Start Time]]<TIME(16,0,0),"Afternoon",IF(tblClean[[#This Row],[Start Time]]<TIME(19,0,0),"Early Evening",IF(tblClean[[#This Row],[Start Time]]<TIME(22,0,0),"Prime Time","Late Night"))))),"") -> Early Evening | R14: =IF(ISNUMBER(tblClean[[#This Row],[Duration Hours]]),IF(tblClean[[#This Row],[Duration Hours]]<2,"Short (under 2h)",IF(tblClean[[#This Row],[Duration Hours]]<3,"Standard (2h to under 3h)","Long (3h or more)")),"") -> Standard (2h to under 3h) | S14: =IF(OR(NOT(ISNUMBER(tblClean[[#This Row],[Date]])),NOT(ISNUMBER(tblClean[[#This Row],[Start Time]])),NOT(ISNUMBER(tblClean[[#This Row],[End Time]])),NOT(ISNUMBER(tblClean[[#This Row],[Attributed GMV PHP]])),NOT(ISNUMBER(tblClean[[#This Row],[Items Sold]])),NOT(ISNUMBER(tblClean[[#This Row],[Livestream Views]])),NOT(ISNUMBER(tblClean[[#This Row],[New Followers]])),tblClean[[#This Row],[Host Name]]="",tblClean[[#This Row],[Session ID]]=""),1,0) -> 0 | T14: =IF(COUNTIF(tblClean[Session ID],tblClean[[#This Row],[Session ID]])>1,1,0) -> 0 | U14: =IF(OR(N(tblClean[[#This Row],[Attributed GMV PHP]])<0,N(tblClean[[#This Row],[Items Sold]])<0,N(tblClean[[#This Row],[Livestream Views]])<0,N(tblClean[[#This Row],[New Followers]])<0),1,0) -> 0 | V14: =IF(ISNUMBER(tblClean[[#This Row],[Duration Hours]]),IF(OR(tblClean[[#This Row],[Duration Hours]]<=0,tblClean[[#This Row],[Duration Hours]]>12),1,0),1) -> 0 | W14: =IF(COUNTIF(HostRoster,tblClean[[#This Row],[Host Name]])=0,1,0) -> 0 | X14: =IF(tblClean[[#This Row],[Missing Flag]]+tblClean[[#This Row],[Duplicate Flag]]+tblClean[[#This Row],[Negative Flag]]+tblClean[[#This Row],[Duration Flag]]+tblClean[[#This Row],[Host Flag]]=0,1,0) -> 1 | Z14: Master list (input). Named range: HostRoster
A15: =TRIM('Raw Data'!A11) -> LS-0007 | B15: =IF(ISNUMBER('Raw Data'!B11),INT('Raw Data'!B11),IFERROR(DATEVALUE('Raw Data'!B11),"")) -> 45811 | C15: =PROPER(TRIM('Raw Data'!C11)) -> Aira Valdez | D15: =IF(ISNUMBER('Raw Data'!D11),MOD('Raw Data'!D11,1),IFERROR(TIMEVALUE('Raw Data'!D11),"")) -> 0.79166667 | E15: =IF(ISNUMBER('Raw Data'!E11),MOD('Raw Data'!E11,1),IFERROR(TIMEVALUE('Raw Data'!E11),"")) -> 0.89583333 | F15: =IF(ISNUMBER('Raw Data'!F11),'Raw Data'!F11,IFERROR(VALUE(SUBSTITUTE('Raw Data'!F11,",","")),"")) -> 82257 | G15: =IF(ISNUMBER('Raw Data'!G11),'Raw Data'!G11,IFERROR(VALUE(SUBSTITUTE('Raw Data'!G11,",","")),"")) -> 243 | H15: =IF(ISNUMBER('Raw Data'!H11),'Raw Data'!H11,IFERROR(VALUE(SUBSTITUTE('Raw Data'!H11,",","")),"")) -> 216966 | I15: =IF(ISNUMBER('Raw Data'!I11),'Raw Data'!I11,IFERROR(VALUE(SUBSTITUTE('Raw Data'!I11,",","")),"")) -> 1728 | J15: =IF(AND(ISNUMBER(tblClean[[#This Row],[Start Time]]),ISNUMBER(tblClean[[#This Row],[End Time]])),ROUND(MOD(tblClean[[#This Row],[End Time]]-tblClean[[#This Row],[Start Time]],1)*24,2),"") -> 2.5 | K15: =IF(AND(ISNUMBER(tblClean[[#This Row],[Duration Hours]]),ISNUMBER(tblClean[[#This Row],[Attributed GMV PHP]])),IF(tblClean[[#This Row],[Duration Hours]]>0,tblClean[[#This Row],[Attributed GMV PHP]]/tblClean[[#This Row],[Duration Hours]],""),"") -> 32902.8 | L15: =IF(ISNUMBER(tblClean[[#This Row],[Date]]),DATE(YEAR(tblClean[[#This Row],[Date]]),MONTH(tblClean[[#This Row],[Date]]),1),"") -> 45809 | M15: =IF(ISNUMBER(tblClean[[#This Row],[Date]]),tblClean[[#This Row],[Date]]-WEEKDAY(tblClean[[#This Row],[Date]],2)+1,"") -> 45810 | N15: =IF(ISNUMBER(tblClean[[#This Row],[Week Start]]),(tblClean[[#This Row],[Week Start]]-MIN(tblClean[Week Start]))/7+1,"") -> 1 | O15: =IF(ISNUMBER(tblClean[[#This Row],[Date]]),CHOOSE(WEEKDAY(tblClean[[#This Row],[Date]],2),"Mon","Tue","Wed","Thu","Fri","Sat","Sun"),"") -> Tue | P15: =IF(ISNUMBER(tblClean[[#This Row],[Date]]),IF(WEEKDAY(tblClean[[#This Row],[Date]],2)>=6,"Weekend","Weekday"),"") -> Weekday | Q15: =IF(ISNUMBER(tblClean[[#This Row],[Start Time]]),IF(tblClean[[#This Row],[Start Time]]<TIME(6,0,0),"Late Night",IF(tblClean[[#This Row],[Start Time]]<TIME(12,0,0),"Morning",IF(tblClean[[#This Row],[Start Time]]<TIME(16,0,0),"Afternoon",IF(tblClean[[#This Row],[Start Time]]<TIME(19,0,0),"Early Evening",IF(tblClean[[#This Row],[Start Time]]<TIME(22,0,0),"Prime Time","Late Night"))))),"") -> Prime Time | R15: =IF(ISNUMBER(tblClean[[#This Row],[Duration Hours]]),IF(tblClean[[#This Row],[Duration Hours]]<2,"Short (under 2h)",IF(tblClean[[#This Row],[Duration Hours]]<3,"Standard (2h to under 3h)","Long (3h or more)")),"") -> Standard (2h to under 3h) | S15: =IF(OR(NOT(ISNUMBER(tblClean[[#This Row],[Date]])),NOT(ISNUMBER(tblClean[[#This Row],[Start Time]])),NOT(ISNUMBER(tblClean[[#This Row],[End Time]])),NOT(ISNUMBER(tblClean[[#This Row],[Attributed GMV PHP]])),NOT(ISNUMBER(tblClean[[#This Row],[Items Sold]])),NOT(ISNUMBER(tblClean[[#This Row],[Livestream Views]])),NOT(ISNUMBER(tblClean[[#This Row],[New Followers]])),tblClean[[#This Row],[Host Name]]="",tblClean[[#This Row],[Session ID]]=""),1,0) -> 0 | T15: =IF(COUNTIF(tblClean[Session ID],tblClean[[#This Row],[Session ID]])>1,1,0) -> 0 | U15: =IF(OR(N(tblClean[[#This Row],[Attributed GMV PHP]])<0,N(tblClean[[#This Row],[Items Sold]])<0,N(tblClean[[#This Row],[Livestream Views]])<0,N(tblClean[[#This Row],[New Followers]])<0),1,0) -> 0 | V15: =IF(ISNUMBER(tblClean[[#This Row],[Duration Hours]]),IF(OR(tblClean[[#This Row],[Duration Hours]]<=0,tblClean[[#This Row],[Duration Hours]]>12),1,0),1) -> 0 | W15: =IF(COUNTIF(HostRoster,tblClean[[#This Row],[Host Name]])=0,1,0) -> 0 | X15: =IF(tblClean[[#This Row],[Missing Flag]]+tblClean[[#This Row],[Duplicate Flag]]+tblClean[[#This Row],[Negative Flag]]+tblClean[[#This Row],[Duration Flag]]+tblClean[[#This Row],[Host Flag]]=0,1,0) -> 1
A16: =TRIM('Raw Data'!A12) -> LS-0008 | B16: =IF(ISNUMBER('Raw Data'!B12),INT('Raw Data'!B12),IFERROR(DATEVALUE('Raw Data'!B12),"")) -> 45811 | C16: =PROPER(TRIM('Raw Data'!C12)) -> Aira Valdez | D16: =IF(ISNUMBER('Raw Data'!D12),MOD('Raw Data'!D12,1),IFERROR(TIMEVALUE('Raw Data'!D12),"")) -> 0.91666667 | E16: =IF(ISNUMBER('Raw Data'!E12),MOD('Raw Data'!E12,1),IFERROR(TIMEVALUE('Raw Data'!E12),"")) -> 0.020833333 | F16: =IF(ISNUMBER('Raw Data'!F12),'Raw Data'!F12,IFERROR(VALUE(SUBSTITUTE('Raw Data'!F12,",","")),"")) -> 39674 | G16: =IF(ISNUMBER('Raw Data'!G12),'Raw Data'!G12,IFERROR(VALUE(SUBSTITUTE('Raw Data'!G12,",","")),"")) -> 119 | H16: =IF(ISNUMBER('Raw Data'!H12),'Raw Data'!H12,IFERROR(VALUE(SUBSTITUTE('Raw Data'!H12,",","")),"")) -> 102019 | I16: =IF(ISNUMBER('Raw Data'!I12),'Raw Data'!I12,IFERROR(VALUE(SUBSTITUTE('Raw Data'!I12,",","")),"")) -> 825 | J16: =IF(AND(ISNUMBER(tblClean[[#This Row],[Start Time]]),ISNUMBER(tblClean[[#This Row],[End Time]])),ROUND(MOD(tblClean[[#This Row],[End Time]]-tblClean[[#This Row],[Start Time]],1)*24,2),"") -> 2.5 | K16: =IF(AND(ISNUMBER(tblClean[[#This Row],[Duration Hours]]),ISNUMBER(tblClean[[#This Row],[Attributed GMV PHP]])),IF(tblClean[[#This Row],[Duration Hours]]>0,tblClean[[#This Row],[Attributed GMV PHP]]/tblClean[[#This Row],[Duration Hours]],""),"") -> 15869.6 | L16: =IF(ISNUMBER(tblClean[[#This Row],[Date]]),DATE(YEAR(tblClean[[#This Row],[Date]]),MONTH(tblClean[[#This Row],[Date]]),1),"") -> 45809 | M16: =IF(ISNUMBER(tblClean[[#This Row],[Date]]),tblClean[[#This Row],[Date]]-WEEKDAY(tblClean[[#This Row],[Date]],2)+1,"") -> 45810 | N16: =IF(ISNUMBER(tblClean[[#This Row],[Week Start]]),(tblClean[[#This Row],[Week Start]]-MIN(tblClean[Week Start]))/7+1,"") -> 1 | O16: =IF(ISNUMBER(tblClean[[#This Row],[Date]]),CHOOSE(WEEKDAY(tblClean[[#This Row],[Date]],2),"Mon","Tue","Wed","Thu","Fri","Sat","Sun"),"") -> Tue | P16: =IF(ISNUMBER(tblClean[[#This Row],[Date]]),IF(WEEKDAY(tblClean[[#This Row],[Date]],2)>=6,"Weekend","Weekday"),"") -> Weekday | Q16: =IF(ISNUMBER(tblClean[[#This Row],[Start Time]]),IF(tblClean[[#This Row],[Start Time]]<TIME(6,0,0),"Late Night",IF(tblClean[[#This Row],[Start Time]]<TIME(12,0,0),"Morning",IF(tblClean[[#This Row],[Start Time]]<TIME(16,0,0),"Afternoon",IF(tblClean[[#This Row],[Start Time]]<TIME(19,0,0),"Early Evening",IF(tblClean[[#This Row],[Start Time]]<TIME(22,0,0),"Prime Time","Late Night"))))),"") -> Late Night | R16: =IF(ISNUMBER(tblClean[[#This Row],[Duration Hours]]),IF(tblClean[[#This Row],[Duration Hours]]<2,"Short (under 2h)",IF(tblClean[[#This Row],[Duration Hours]]<3,"Standard (2h to under 3h)","Long (3h or more)")),"") -> Standard (2h to under 3h) | S16: =IF(OR(NOT(ISNUMBER(tblClean[[#This Row],[Date]])),NOT(ISNUMBER(tblClean[[#This Row],[Start Time]])),NOT(ISNUMBER(tblClean[[#This Row],[End Time]])),NOT(ISNUMBER(tblClean[[#This Row],[Attributed GMV PHP]])),NOT(ISNUMBER(tblClean[[#This Row],[Items Sold]])),NOT(ISNUMBER(tblClean[[#This Row],[Livestream Views]])),NOT(ISNUMBER(tblClean[[#This Row],[New Followers]])),tblClean[[#This Row],[Host Name]]="",tblClean[[#This Row],[Session ID]]=""),1,0) -> 0 | T16: =IF(COUNTIF(tblClean[Session ID],tblClean[[#This Row],[Session ID]])>1,1,0) -> 0 | U16: =IF(OR(N(tblClean[[#This Row],[Attributed GMV PHP]])<0,N(tblClean[[#This Row],[Items Sold]])<0,N(tblClean[[#This Row],[Livestream Views]])<0,N(tblClean[[#This Row],[New Followers]])<0),1,0) -> 0 | V16: =IF(ISNUMBER(tblClean[[#This Row],[Duration Hours]]),IF(OR(tblClean[[#This Row],[Duration Hours]]<=0,tblClean[[#This Row],[Duration Hours]]>12),1,0),1) -> 0 | W16: =IF(COUNTIF(HostRoster,tblClean[[#This Row],[Host Name]])=0,1,0) -> 0 | X16: =IF(tblClean[[#This Row],[Missing Flag]]+tblClean[[#This Row],[Duplicate Flag]]+tblClean[[#This Row],[Negative Flag]]+tblClean[[#This Row],[Duration Flag]]+tblClean[[#This Row],[Host Flag]]=0,1,0) -> 1
A17: =TRIM('Raw Data'!A13) -> LS-0009 | B17: =IF(ISNUMBER('Raw Data'!B13),INT('Raw Data'!B13),IFERROR(DATEVALUE('Raw Data'!B13),"")) -> 45812 | C17: =PROPER(TRIM('Raw Data'!C13)) -> Carlo Mendoza | D17: =IF(ISNUMBER('Raw Data'!D13),MOD('Raw Data'!D13,1),IFERROR(TIMEVALUE('Raw Data'!D13),"")) -> 0.66666667 | E17: =IF(ISNUMBER('Raw Data'!E13),MOD('Raw Data'!E13,1),IFERROR(TIMEVALUE('Raw Data'!E13),"")) -> 0.79166667 | F17: =IF(ISNUMBER('Raw Data'!F13),'Raw Data'!F13,IFERROR(VALUE(SUBSTITUTE('Raw Data'!F13,",","")),"")) -> 25112 | G17: =IF(ISNUMBER('Raw Data'!G13),'Raw Data'!G13,IFERROR(VALUE(SUBSTITUTE('Raw Data'!G13,",","")),"")) -> 73 | H17: =IF(ISNUMBER('Raw Data'!H13),'Raw Data'!H13,IFERROR(VALUE(SUBSTITUTE('Raw Data'!H13,",","")),"")) -> 77728 | I17: =IF(ISNUMBER('Raw Data'!I13),'Raw Data'!I13,IFERROR(VALUE(SUBSTITUTE('Raw Data'!I13,",","")),"")) -> 552 | J17: =IF(AND(ISNUMBER(tblClean[[#This Row],[Start Time]]),ISNUMBER(tblClean[[#This Row],[End Time]])),ROUND(MOD(tblClean[[#This Row],[End Time]]-tblClean[[#This Row],[Start Time]],1)*24,2),"") -> 3 | K17: =IF(AND(ISNUMBER(tblClean[[#This Row],[Duration Hours]]),ISNUMBER(tblClean[[#This Row],[Attributed GMV PHP]])),IF(tblClean[[#This Row],[Duration Hours]]>0,tblClean[[#This Row],[Attributed GMV PHP]]/tblClean[[#This Row],[Duration Hours]],""),"") -> 8370.6667 | L17: =IF(ISNUMBER(tblClean[[#This Row],[Date]]),DATE(YEAR(tblClean[[#This Row],[Date]]),MONTH(tblClean[[#This Row],[Date]]),1),"") -> 45809 | M17: =IF(ISNUMBER(tblClean[[#This Row],[Date]]),tblClean[[#This Row],[Date]]-WEEKDAY(tblClean[[#This Row],[Date]],2)+1,"") -> 45810 | N17: =IF(ISNUMBER(tblClean[[#This Row],[Week Start]]),(tblClean[[#This Row],[Week Start]]-MIN(tblClean[Week Start]))/7+1,"") -> 1 | O17: =IF(ISNUMBER(tblClean[[#This Row],[Date]]),CHOOSE(WEEKDAY(tblClean[[#This Row],[Date]],2),"Mon","Tue","Wed","Thu","Fri","Sat","Sun"),"") -> Wed | P17: =IF(ISNUMBER(tblClean[[#This Row],[Date]]),IF(WEEKDAY(tblClean[[#This Row],[Date]],2)>=6,"Weekend","Weekday"),"") -> Weekday | Q17: =IF(ISNUMBER(tblClean[[#This Row],[Start Time]]),IF(tblClean[[#This Row],[Start Time]]<TIME(6,0,0),"Late Night",IF(tblClean[[#This Row],[Start Time]]<TIME(12,0,0),"Morning",IF(tblClean[[#This Row],[Start Time]]<TIME(16,0,0),"Afternoon",IF(tblClean[[#This Row],[Start Time]]<TIME(19,0,0),"Early Evening",IF(tblClean[[#This Row],[Start Time]]<TIME(22,0,0),"Prime Time","Late Night"))))),"") -> Early Evening | R17: =IF(ISNUMBER(tblClean[[#This Row],[Duration Hours]]),IF(tblClean[[#This Row],[Duration Hours]]<2,"Short (under 2h)",IF(tblClean[[#This Row],[Duration Hours]]<3,"Standard (2h to under 3h)","Long (3h or more)")),"") -> Long (3h or more) | S17: =IF(OR(NOT(ISNUMBER(tblClean[[#This Row],[Date]])),NOT(ISNUMBER(tblClean[[#This Row],[Start Time]])),NOT(ISNUMBER(tblClean[[#This Row],[End Time]])),NOT(ISNUMBER(tblClean[[#This Row],[Attributed GMV PHP]])),NOT(ISNUMBER(tblClean[[#This Row],[Items Sold]])),NOT(ISNUMBER(tblClean[[#This Row],[Livestream Views]])),NOT(ISNUMBER(tblClean[[#This Row],[New Followers]])),tblClean[[#This Row],[Host Name]]="",tblClean[[#This Row],[Session ID]]=""),1,0) -> 0 | T17: =IF(COUNTIF(tblClean[Session ID],tblClean[[#This Row],[Session ID]])>1,1,0) -> 0 | U17: =IF(OR(N(tblClean[[#This Row],[Attributed GMV PHP]])<0,N(tblClean[[#This Row],[Items Sold]])<0,N(tblClean[[#This Row],[Livestream Views]])<0,N(tblClean[[#This Row],[New Followers]])<0),1,0) -> 0 | V17: =IF(ISNUMBER(tblClean[[#This Row],[Duration Hours]]),IF(OR(tblClean[[#This Row],[Duration Hours]]<=0,tblClean[[#This Row],[Duration Hours]]>12),1,0),1) -> 0 | W17: =IF(COUNTIF(HostRoster,tblClean[[#This Row],[Host Name]])=0,1,0) -> 0 | X17: =IF(tblClean[[#This Row],[Missing Flag]]+tblClean[[#This Row],[Duplicate Flag]]+tblClean[[#This Row],[Negative Flag]]+tblClean[[#This Row],[Duration Flag]]+tblClean[[#This Row],[Host Flag]]=0,1,0) -> 1
A18: =TRIM('Raw Data'!A14) -> LS-0010 | B18: =IF(ISNUMBER('Raw Data'!B14),INT('Raw Data'!B14),IFERROR(DATEVALUE('Raw Data'!B14),"")) -> 45812 | C18: =PROPER(TRIM('Raw Data'!C14)) -> Bianca Reyes | D18: =IF(ISNUMBER('Raw Data'!D14),MOD('Raw Data'!D14,1),IFERROR(TIMEVALUE('Raw Data'!D14),"")) -> 0.79166667 | E18: =IF(ISNUMBER('Raw Data'!E14),MOD('Raw Data'!E14,1),IFERROR(TIMEVALUE('Raw Data'!E14),"")) -> 0.89583333 | F18: =IF(ISNUMBER('Raw Data'!F14),'Raw Data'!F14,IFERROR(VALUE(SUBSTITUTE('Raw Data'!F14,",","")),"")) -> 8207 | G18: =IF(ISNUMBER('Raw Data'!G14),'Raw Data'!G14,IFERROR(VALUE(SUBSTITUTE('Raw Data'!G14,",","")),"")) -> 22 | H18: =IF(ISNUMBER('Raw Data'!H14),'Raw Data'!H14,IFERROR(VALUE(SUBSTITUTE('Raw Data'!H14,",","")),"")) -> 27621 | I18: =IF(ISNUMBER('Raw Data'!I14),'Raw Data'!I14,IFERROR(VALUE(SUBSTITUTE('Raw Data'!I14,",","")),"")) -> 298 | J18: =IF(AND(ISNUMBER(tblClean[[#This Row],[Start Time]]),ISNUMBER(tblClean[[#This Row],[End Time]])),ROUND(MOD(tblClean[[#This Row],[End Time]]-tblClean[[#This Row],[Start Time]],1)*24,2),"") -> 2.5 | K18: =IF(AND(ISNUMBER(tblClean[[#This Row],[Duration Hours]]),ISNUMBER(tblClean[[#This Row],[Attributed GMV PHP]])),IF(tblClean[[#This Row],[Duration Hours]]>0,tblClean[[#This Row],[Attributed GMV PHP]]/tblClean[[#This Row],[Duration Hours]],""),"") -> 3282.8 | L18: =IF(ISNUMBER(tblClean[[#This Row],[Date]]),DATE(YEAR(tblClean[[#This Row],[Date]]),MONTH(tblClean[[#This Row],[Date]]),1),"") -> 45809 | M18: =IF(ISNUMBER(tblClean[[#This Row],[Date]]),tblClean[[#This Row],[Date]]-WEEKDAY(tblClean[[#This Row],[Date]],2)+1,"") -> 45810 | N18: =IF(ISNUMBER(tblClean[[#This Row],[Week Start]]),(tblClean[[#This Row],[Week Start]]-MIN(tblClean[Week Start]))/7+1,"") -> 1 | O18: =IF(ISNUMBER(tblClean[[#This Row],[Date]]),CHOOSE(WEEKDAY(tblClean[[#This Row],[Date]],2),"Mon","Tue","Wed","Thu","Fri","Sat","Sun"),"") -> Wed | P18: =IF(ISNUMBER(tblClean[[#This Row],[Date]]),IF(WEEKDAY(tblClean[[#This Row],[Date]],2)>=6,"Weekend","Weekday"),"") -> Weekday | Q18: =IF(ISNUMBER(tblClean[[#This Row],[Start Time]]),IF(tblClean[[#This Row],[Start Time]]<TIME(6,0,0),"Late Night",IF(tblClean[[#This Row],[Start Time]]<TIME(12,0,0),"Morning",IF(tblClean[[#This Row],[Start Time]]<TIME(16,0,0),"Afternoon",IF(tblClean[[#This Row],[Start Time]]<TIME(19,0,0),"Early Evening",IF(tblClean[[#This Row],[Start Time]]<TIME(22,0,0),"Prime Time","Late Night"))))),"") -> Prime Time | R18: =IF(ISNUMBER(tblClean[[#This Row],[Duration Hours]]),IF(tblClean[[#This Row],[Duration Hours]]<2,"Short (under 2h)",IF(tblClean[[#This Row],[Duration Hours]]<3,"Standard (2h to under 3h)","Long (3h or more)")),"") -> Standard (2h to under 3h) | S18: =IF(OR(NOT(ISNUMBER(tblClean[[#This Row],[Date]])),NOT(ISNUMBER(tblClean[[#This Row],[Start Time]])),NOT(ISNUMBER(tblClean[[#This Row],[End Time]])),NOT(ISNUMBER(tblClean[[#This Row],[Attributed GMV PHP]])),NOT(ISNUMBER(tblClean[[#This Row],[Items Sold]])),NOT(ISNUMBER(tblClean[[#This Row],[Livestream Views]])),NOT(ISNUMBER(tblClean[[#This Row],[New Followers]])),tblClean[[#This Row],[Host Name]]="",tblClean[[#This Row],[Session ID]]=""),1,0) -> 0 | T18: =IF(COUNTIF(tblClean[Session ID],tblClean[[#This Row],[Session ID]])>1,1,0) -> 0 | U18: =IF(OR(N(tblClean[[#This Row],[Attributed GMV PHP]])<0,N(tblClean[[#This Row],[Items Sold]])<0,N(tblClean[[#This Row],[Livestream Views]])<0,N(tblClean[[#This Row],[New Followers]])<0),1,0) -> 0 | V18: =IF(ISNUMBER(tblClean[[#This Row],[Duration Hours]]),IF(OR(tblClean[[#This Row],[Duration Hours]]<=0,tblClean[[#This Row],[Duration Hours]]>12),1,0),1) -> 0 | W18: =IF(COUNTIF(HostRoster,tblClean[[#This Row],[Host Name]])=0,1,0) -> 0 | X18: =IF(tblClean[[#This Row],[Missing Flag]]+tblClean[[#This Row],[Duplicate Flag]]+tblClean[[#This Row],[Negative Flag]]+tblClean[[#This Row],[Duration Flag]]+tblClean[[#This Row],[Host Flag]]=0,1,0) -> 1
A19: =TRIM('Raw Data'!A15) -> LS-0011 | B19: =IF(ISNUMBER('Raw Data'!B15),INT('Raw Data'!B15),IFERROR(DATEVALUE('Raw Data'!B15),"")) -> 45812 | C19: =PROPER(TRIM('Raw Data'!C15)) -> Dani Villanueva | D19: =IF(ISNUMBER('Raw Data'!D15),MOD('Raw Data'!D15,1),IFERROR(TIMEVALUE('Raw Data'!D15),"")) -> 0.91666667 | E19: =IF(ISNUMBER('Raw Data'!E15),MOD('Raw Data'!E15,1),IFERROR(TIMEVALUE('Raw Data'!E15),"")) -> 0.041666667 | F19: =IF(ISNUMBER('Raw Data'!F15),'Raw Data'!F15,IFERROR(VALUE(SUBSTITUTE('Raw Data'!F15,",","")),"")) -> 26243 | G19: =IF(ISNUMBER('Raw Data'!G15),'Raw Data'!G15,IFERROR(VALUE(SUBSTITUTE('Raw Data'!G15,",","")),"")) -> 77 | H19: =IF(ISNUMBER('Raw Data'!H15),'Raw Data'!H15,IFERROR(VALUE(SUBSTITUTE('Raw Data'!H15,",","")),"")) -> 58338 | I19: =IF(ISNUMBER('Raw Data'!I15),'Raw Data'!I15,IFERROR(VALUE(SUBSTITUTE('Raw Data'!I15,",","")),"")) -> 332 | J19: =IF(AND(ISNUMBER(tblClean[[#This Row],[Start Time]]),ISNUMBER(tblClean[[#This Row],[End Time]])),ROUND(MOD(tblClean[[#This Row],[End Time]]-tblClean[[#This Row],[Start Time]],1)*24,2),"") -> 3 | K19: =IF(AND(ISNUMBER(tblClean[[#This Row],[Duration Hours]]),ISNUMBER(tblClean[[#This Row],[Attributed GMV PHP]])),IF(tblClean[[#This Row],[Duration Hours]]>0,tblClean[[#This Row],[Attributed GMV PHP]]/tblClean[[#This Row],[Duration Hours]],""),"") -> 8747.6667 | L19: =IF(ISNUMBER(tblClean[[#This Row],[Date]]),DATE(YEAR(tblClean[[#This Row],[Date]]),MONTH(tblClean[[#This Row],[Date]]),1),"") -> 45809 | M19: =IF(ISNUMBER(tblClean[[#This Row],[Date]]),tblClean[[#This Row],[Date]]-WEEKDAY(tblClean[[#This Row],[Date]],2)+1,"") -> 45810 | N19: =IF(ISNUMBER(tblClean[[#This Row],[Week Start]]),(tblClean[[#This Row],[Week Start]]-MIN(tblClean[Week Start]))/7+1,"") -> 1 | O19: =IF(ISNUMBER(tblClean[[#This Row],[Date]]),CHOOSE(WEEKDAY(tblClean[[#This Row],[Date]],2),"Mon","Tue","Wed","Thu","Fri","Sat","Sun"),"") -> Wed | P19: =IF(ISNUMBER(tblClean[[#This Row],[Date]]),IF(WEEKDAY(tblClean[[#This Row],[Date]],2)>=6,"Weekend","Weekday"),"") -> Weekday | Q19: =IF(ISNUMBER(tblClean[[#This Row],[Start Time]]),IF(tblClean[[#This Row],[Start Time]]<TIME(6,0,0),"Late Night",IF(tblClean[[#This Row],[Start Time]]<TIME(12,0,0),"Morning",IF(tblClean[[#This Row],[Start Time]]<TIME(16,0,0),"Afternoon",IF(tblClean[[#This Row],[Start Time]]<TIME(19,0,0),"Early Evening",IF(tblClean[[#This Row],[Start Time]]<TIME(22,0,0),"Prime Time","Late Night"))))),"") -> Late Night | R19: =IF(ISNUMBER(tblClean[[#This Row],[Duration Hours]]),IF(tblClean[[#This Row],[Duration Hours]]<2,"Short (under 2h)",IF(tblClean[[#This Row],[Duration Hours]]<3,"Standard (2h to under 3h)","Long (3h or more)")),"") -> Long (3h or more) | S19: =IF(OR(NOT(ISNUMBER(tblClean[[#This Row],[Date]])),NOT(ISNUMBER(tblClean[[#This Row],[Start Time]])),NOT(ISNUMBER(tblClean[[#This Row],[End Time]])),NOT(ISNUMBER(tblClean[[#This Row],[Attributed GMV PHP]])),NOT(ISNUMBER(tblClean[[#This Row],[Items Sold]])),NOT(ISNUMBER(tblClean[[#This Row],[Livestream Views]])),NOT(ISNUMBER(tblClean[[#This Row],[New Followers]])),tblClean[[#This Row],[Host Name]]="",tblClean[[#This Row],[Session ID]]=""),1,0) -> 0 | T19: =IF(COUNTIF(tblClean[Session ID],tblClean[[#This Row],[Session ID]])>1,1,0) -> 0 | U19: =IF(OR(N(tblClean[[#This Row],[Attributed GMV PHP]])<0,N(tblClean[[#This Row],[Items Sold]])<0,N(tblClean[[#This Row],[Livestream Views]])<0,N(tblClean[[#This Row],[New Followers]])<0),1,0) -> 0 | V19: =IF(ISNUMBER(tblClean[[#This Row],[Duration Hours]]),IF(OR(tblClean[[#This Row],[Duration Hours]]<=0,tblClean[[#This Row],[Duration Hours]]>12),1,0),1) -> 0 | W19: =IF(COUNTIF(HostRoster,tblClean[[#This Row],[Host Name]])=0,1,0) -> 0 | X19: =IF(tblClean[[#This Row],[Missing Flag]]+tblClean[[#This Row],[Duplicate Flag]]+tblClean[[#This Row],[Negative Flag]]+tblClean[[#This Row],[Duration Flag]]+tblClean[[#This Row],[Host Flag]]=0,1,0) -> 1
A20: =TRIM('Raw Data'!A16) -> LS-0012 | B20: =IF(ISNUMBER('Raw Data'!B16),INT('Raw Data'!B16),IFERROR(DATEVALUE('Raw Data'!B16),"")) -> 45813 | C20: =PROPER(TRIM('Raw Data'!C16)) -> Bianca Reyes | D20: =IF(ISNUMBER('Raw Data'!D16),MOD('Raw Data'!D16,1),IFERROR(TIMEVALUE('Raw Data'!D16),"")) -> 0.54166667 | E20: =IF(ISNUMBER('Raw Data'!E16),MOD('Raw Data'!E16,1),IFERROR(TIMEVALUE('Raw Data'!E16),"")) -> 0.625 | F20: =IF(ISNUMBER('Raw Data'!F16),'Raw Data'!F16,IFERROR(VALUE(SUBSTITUTE('Raw Data'!F16,",","")),"")) -> 6069 | G20: =IF(ISNUMBER('Raw Data'!G16),'Raw Data'!G16,IFERROR(VALUE(SUBSTITUTE('Raw Data'!G16,",","")),"")) -> 17 | H20: =IF(ISNUMBER('Raw Data'!H16),'Raw Data'!H16,IFERROR(VALUE(SUBSTITUTE('Raw Data'!H16,",","")),"")) -> 20285 | I20: =IF(ISNUMBER('Raw Data'!I16),'Raw Data'!I16,IFERROR(VALUE(SUBSTITUTE('Raw Data'!I16,",","")),"")) -> 262 | J20: =IF(AND(ISNUMBER(tblClean[[#This Row],[Start Time]]),ISNUMBER(tblClean[[#This Row],[End Time]])),ROUND(MOD(tblClean[[#This Row],[End Time]]-tblClean[[#This Row],[Start Time]],1)*24,2),"") -> 2 | K20: =IF(AND(ISNUMBER(tblClean[[#This Row],[Duration Hours]]),ISNUMBER(tblClean[[#This Row],[Attributed GMV PHP]])),IF(tblClean[[#This Row],[Duration Hours]]>0,tblClean[[#This Row],[Attributed GMV PHP]]/tblClean[[#This Row],[Duration Hours]],""),"") -> 3034.5 | L20: =IF(ISNUMBER(tblClean[[#This Row],[Date]]),DATE(YEAR(tblClean[[#This Row],[Date]]),MONTH(tblClean[[#This Row],[Date]]),1),"") -> 45809 | M20: =IF(ISNUMBER(tblClean[[#This Row],[Date]]),tblClean[[#This Row],[Date]]-WEEKDAY(tblClean[[#This Row],[Date]],2)+1,"") -> 45810 | N20: =IF(ISNUMBER(tblClean[[#This Row],[Week Start]]),(tblClean[[#This Row],[Week Start]]-MIN(tblClean[Week Start]))/7+1,"") -> 1 | O20: =IF(ISNUMBER(tblClean[[#This Row],[Date]]),CHOOSE(WEEKDAY(tblClean[[#This Row],[Date]],2),"Mon","Tue","Wed","Thu","Fri","Sat","Sun"),"") -> Thu | P20: =IF(ISNUMBER(tblClean[[#This Row],[Date]]),IF(WEEKDAY(tblClean[[#This Row],[Date]],2)>=6,"Weekend","Weekday"),"") -> Weekday | Q20: =IF(ISNUMBER(tblClean[[#This Row],[Start Time]]),IF(tblClean[[#This Row],[Start Time]]<TIME(6,0,0),"Late Night",IF(tblClean[[#This Row],[Start Time]]<TIME(12,0,0),"Morning",IF(tblClean[[#This Row],[Start Time]]<TIME(16,0,0),"Afternoon",IF(tblClean[[#This Row],[Start Time]]<TIME(19,0,0),"Early Evening",IF(tblClean[[#This Row],[Start Time]]<TIME(22,0,0),"Prime Time","Late Night"))))),"") -> Afternoon | R20: =IF(ISNUMBER(tblClean[[#This Row],[Duration Hours]]),IF(tblClean[[#This Row],[Duration Hours]]<2,"Short (under 2h)",IF(tblClean[[#This Row],[Duration Hours]]<3,"Standard (2h to under 3h)","Long (3h or more)")),"") -> Standard (2h to under 3h) | S20: =IF(OR(NOT(ISNUMBER(tblClean[[#This Row],[Date]])),NOT(ISNUMBER(tblClean[[#This Row],[Start Time]])),NOT(ISNUMBER(tblClean[[#This Row],[End Time]])),NOT(ISNUMBER(tblClean[[#This Row],[Attributed GMV PHP]])),NOT(ISNUMBER(tblClean[[#This Row],[Items Sold]])),NOT(ISNUMBER(tblClean[[#This Row],[Livestream Views]])),NOT(ISNUMBER(tblClean[[#This Row],[New Followers]])),tblClean[[#This Row],[Host Name]]="",tblClean[[#This Row],[Session ID]]=""),1,0) -> 0 | T20: =IF(COUNTIF(tblClean[Session ID],tblClean[[#This Row],[Session ID]])>1,1,0) -> 0 | U20: =IF(OR(N(tblClean[[#This Row],[Attributed GMV PHP]])<0,N(tblClean[[#This Row],[Items Sold]])<0,N(tblClean[[#This Row],[Livestream Views]])<0,N(tblClean[[#This Row],[New Followers]])<0),1,0) -> 0 | V20: =IF(ISNUMBER(tblClean[[#This Row],[Duration Hours]]),IF(OR(tblClean[[#This Row],[Duration Hours]]<=0,tblClean[[#This Row],[Duration Hours]]>12),1,0),1) -> 0 | W20: =IF(COUNTIF(HostRoster,tblClean[[#This Row],[Host Name]])=0,1,0) -> 0 | X20: =IF(tblClean[[#This Row],[Missing Flag]]+tblClean[[#This Row],[Duplicate Flag]]+tblClean[[#This Row],[Negative Flag]]+tblClean[[#This Row],[Duration Flag]]+tblClean[[#This Row],[Host Flag]]=0,1,0) -> 1
A21: =TRIM('Raw Data'!A17) -> LS-0013 | B21: =IF(ISNUMBER('Raw Data'!B17),INT('Raw Data'!B17),IFERROR(DATEVALUE('Raw Data'!B17),"")) -> 45813 | C21: =PROPER(TRIM('Raw Data'!C17)) -> Bianca Reyes | D21: =IF(ISNUMBER('Raw Data'!D17),MOD('Raw Data'!D17,1),IFERROR(TIMEVALUE('Raw Data'!D17),"")) -> 0.66666667 | E21: =IF(ISNUMBER('Raw Data'!E17),MOD('Raw Data'!E17,1),IFERROR(TIMEVALUE('Raw Data'!E17),"")) -> 0.79166667 | F21: =IF(ISNUMBER('Raw Data'!F17),'Raw Data'!F17,IFERROR(VALUE(SUBSTITUTE('Raw Data'!F17,",","")),"")) -> 17365 | G21: =IF(ISNUMBER('Raw Data'!G17),'Raw Data'!G17,IFERROR(VALUE(SUBSTITUTE('Raw Data'!G17,",","")),"")) -> 53 | H21: =IF(ISNUMBER('Raw Data'!H17),'Raw Data'!H17,IFERROR(VALUE(SUBSTITUTE('Raw Data'!H17,",","")),"")) -> 61653 | I21: =IF(ISNUMBER('Raw Data'!I17),'Raw Data'!I17,IFERROR(VALUE(SUBSTITUTE('Raw Data'!I17,",","")),"")) -> 627 | J21: =IF(AND(ISNUMBER(tblClean[[#This Row],[Start Time]]),ISNUMBER(tblClean[[#This Row],[End Time]])),ROUND(MOD(tblClean[[#This Row],[End Time]]-tblClean[[#This Row],[Start Time]],1)*24,2),"") -> 3 | K21: =IF(AND(ISNUMBER(tblClean[[#This Row],[Duration Hours]]),ISNUMBER(tblClean[[#This Row],[Attributed GMV PHP]])),IF(tblClean[[#This Row],[Duration Hours]]>0,tblClean[[#This Row],[Attributed GMV PHP]]/tblClean[[#This Row],[Duration Hours]],""),"") -> 5788.3333 | L21: =IF(ISNUMBER(tblClean[[#This Row],[Date]]),DATE(YEAR(tblClean[[#This Row],[Date]]),MONTH(tblClean[[#This Row],[Date]]),1),"") -> 45809 | M21: =IF(ISNUMBER(tblClean[[#This Row],[Date]]),tblClean[[#This Row],[Date]]-WEEKDAY(tblClean[[#This Row],[Date]],2)+1,"") -> 45810 | N21: =IF(ISNUMBER(tblClean[[#This Row],[Week Start]]),(tblClean[[#This Row],[Week Start]]-MIN(tblClean[Week Start]))/7+1,"") -> 1 | O21: =IF(ISNUMBER(tblClean[[#This Row],[Date]]),CHOOSE(WEEKDAY(tblClean[[#This Row],[Date]],2),"Mon","Tue","Wed","Thu","Fri","Sat","Sun"),"") -> Thu | P21: =IF(ISNUMBER(tblClean[[#This Row],[Date]]),IF(WEEKDAY(tblClean[[#This Row],[Date]],2)>=6,"Weekend","Weekday"),"") -> Weekday | Q21: =IF(ISNUMBER(tblClean[[#This Row],[Start Time]]),IF(tblClean[[#This Row],[Start Time]]<TIME(6,0,0),"Late Night",IF(tblClean[[#This Row],[Start Time]]<TIME(12,0,0),"Morning",IF(tblClean[[#This Row],[Start Time]]<TIME(16,0,0),"Afternoon",IF(tblClean[[#This Row],[Start Time]]<TIME(19,0,0),"Early Evening",IF(tblClean[[#This Row],[Start Time]]<TIME(22,0,0),"Prime Time","Late Night"))))),"") -> Early Evening | R21: =IF(ISNUMBER(tblClean[[#This Row],[Duration Hours]]),IF(tblClean[[#This Row],[Duration Hours]]<2,"Short (under 2h)",IF(tblClean[[#This Row],[Duration Hours]]<3,"Standard (2h to under 3h)","Long (3h or more)")),"") -> Long (3h or more) | S21: =IF(OR(NOT(ISNUMBER(tblClean[[#This Row],[Date]])),NOT(ISNUMBER(tblClean[[#This Row],[Start Time]])),NOT(ISNUMBER(tblClean[[#This Row],[End Time]])),NOT(ISNUMBER(tblClean[[#This Row],[Attributed GMV PHP]])),NOT(ISNUMBER(tblClean[[#This Row],[Items Sold]])),NOT(ISNUMBER(tblClean[[#This Row],[Livestream Views]])),NOT(ISNUMBER(tblClean[[#This Row],[New Followers]])),tblClean[[#This Row],[Host Name]]="",tblClean[[#This Row],[Session ID]]=""),1,0) -> 0 | T21: =IF(COUNTIF(tblClean[Session ID],tblClean[[#This Row],[Session ID]])>1,1,0) -> 0 | U21: =IF(OR(N(tblClean[[#This Row],[Attributed GMV PHP]])<0,N(tblClean[[#This Row],[Items Sold]])<0,N(tblClean[[#This Row],[Livestream Views]])<0,N(tblClean[[#This Row],[New Followers]])<0),1,0) -> 0 | V21: =IF(ISNUMBER(tblClean[[#This Row],[Duration Hours]]),IF(OR(tblClean[[#This Row],[Duration Hours]]<=0,tblClean[[#This Row],[Duration Hours]]>12),1,0),1) -> 0 | W21: =IF(COUNTIF(HostRoster,tblClean[[#This Row],[Host Name]])=0,1,0) -> 0 | X21: =IF(tblClean[[#This Row],[Missing Flag]]+tblClean[[#This Row],[Duplicate Flag]]+tblClean[[#This Row],[Negative Flag]]+tblClean[[#This Row],[Duration Flag]]+tblClean[[#This Row],[Host Flag]]=0,1,0) -> 1
A22: =TRIM('Raw Data'!A18) -> LS-0014 | B22: =IF(ISNUMBER('Raw Data'!B18),INT('Raw Data'!B18),IFERROR(DATEVALUE('Raw Data'!B18),"")) -> 45813 | C22: =PROPER(TRIM('Raw Data'!C18)) -> Aira Valdez | D22: =IF(ISNUMBER('Raw Data'!D18),MOD('Raw Data'!D18,1),IFERROR(TIMEVALUE('Raw Data'!D18),"")) -> 0.79166667 | E22: =IF(ISNUMBER('Raw Data'!E18),MOD('Raw Data'!E18,1),IFERROR(TIMEVALUE('Raw Data'!E18),"")) -> 0.85416667 | F22: =IF(ISNUMBER('Raw Data'!F18),'Raw Data'!F18,IFERROR(VALUE(SUBSTITUTE('Raw Data'!F18,",","")),"")) -> 34472 | G22: =IF(ISNUMBER('Raw Data'!G18),'Raw Data'!G18,IFERROR(VALUE(SUBSTITUTE('Raw Data'!G18,",","")),"")) -> 86 | H22: =IF(ISNUMBER('Raw Data'!H18),'Raw Data'!H18,IFERROR(VALUE(SUBSTITUTE('Raw Data'!H18,",","")),"")) -> 190124 | I22: =IF(ISNUMBER('Raw Data'!I18),'Raw Data'!I18,IFERROR(VALUE(SUBSTITUTE('Raw Data'!I18,",","")),"")) -> 1319 | J22: =IF(AND(ISNUMBER(tblClean[[#This Row],[Start Time]]),ISNUMBER(tblClean[[#This Row],[End Time]])),ROUND(MOD(tblClean[[#This Row],[End Time]]-tblClean[[#This Row],[Start Time]],1)*24,2),"") -> 1.5 | K22: =IF(AND(ISNUMBER(tblClean[[#This Row],[Duration Hours]]),ISNUMBER(tblClean[[#This Row],[Attributed GMV PHP]])),IF(tblClean[[#This Row],[Duration Hours]]>0,tblClean[[#This Row],[Attributed GMV PHP]]/tblClean[[#This Row],[Duration Hours]],""),"") -> 22981.333 | L22: =IF(ISNUMBER(tblClean[[#This Row],[Date]]),DATE(YEAR(tblClean[[#This Row],[Date]]),MONTH(tblClean[[#This Row],[Date]]),1),"") -> 45809 | M22: =IF(ISNUMBER(tblClean[[#This Row],[Date]]),tblClean[[#This Row],[Date]]-WEEKDAY(tblClean[[#This Row],[Date]],2)+1,"") -> 45810 | N22: =IF(ISNUMBER(tblClean[[#This Row],[Week Start]]),(tblClean[[#This Row],[Week Start]]-MIN(tblClean[Week Start]))/7+1,"") -> 1 | O22: =IF(ISNUMBER(tblClean[[#This Row],[Date]]),CHOOSE(WEEKDAY(tblClean[[#This Row],[Date]],2),"Mon","Tue","Wed","Thu","Fri","Sat","Sun"),"") -> Thu | P22: =IF(ISNUMBER(tblClean[[#This Row],[Date]]),IF(WEEKDAY(tblClean[[#This Row],[Date]],2)>=6,"Weekend","Weekday"),"") -> Weekday | Q22: =IF(ISNUMBER(tblClean[[#This Row],[Start Time]]),IF(tblClean[[#This Row],[Start Time]]<TIME(6,0,0),"Late Night",IF(tblClean[[#This Row],[Start Time]]<TIME(12,0,0),"Morning",IF(tblClean[[#This Row],[Start Time]]<TIME(16,0,0),"Afternoon",IF(tblClean[[#This Row],[Start Time]]<TIME(19,0,0),"Early Evening",IF(tblClean[[#This Row],[Start Time]]<TIME(22,0,0),"Prime Time","Late Night"))))),"") -> Prime Time | R22: =IF(ISNUMBER(tblClean[[#This Row],[Duration Hours]]),IF(tblClean[[#This Row],[Duration Hours]]<2,"Short (under 2h)",IF(tblClean[[#This Row],[Duration Hours]]<3,"Standard (2h to under 3h)","Long (3h or more)")),"") -> Short (under 2h) | S22: =IF(OR(NOT(ISNUMBER(tblClean[[#This Row],[Date]])),NOT(ISNUMBER(tblClean[[#This Row],[Start Time]])),NOT(ISNUMBER(tblClean[[#This Row],[End Time]])),NOT(ISNUMBER(tblClean[[#This Row],[Attributed GMV PHP]])),NOT(ISNUMBER(tblClean[[#This Row],[Items Sold]])),NOT(ISNUMBER(tblClean[[#This Row],[Livestream Views]])),NOT(ISNUMBER(tblClean[[#This Row],[New Followers]])),tblClean[[#This Row],[Host Name]]="",tblClean[[#This Row],[Session ID]]=""),1,0) -> 0 | T22: =IF(COUNTIF(tblClean[Session ID],tblClean[[#This Row],[Session ID]])>1,1,0) -> 0 | U22: =IF(OR(N(tblClean[[#This Row],[Attributed GMV PHP]])<0,N(tblClean[[#This Row],[Items Sold]])<0,N(tblClean[[#This Row],[Livestream Views]])<0,N(tblClean[[#This Row],[New Followers]])<0),1,0) -> 0 | V22: =IF(ISNUMBER(tblClean[[#This Row],[Duration Hours]]),IF(OR(tblClean[[#This Row],[Duration Hours]]<=0,tblClean[[#This Row],[Duration Hours]]>12),1,0),1) -> 0 | W22: =IF(COUNTIF(HostRoster,tblClean[[#This Row],[Host Name]])=0,1,0) -> 0 | X22: =IF(tblClean[[#This Row],[Missing Flag]]+tblClean[[#This Row],[Duplicate Flag]]+tblClean[[#This Row],[Negative Flag]]+tblClean[[#This Row],[Duration Flag]]+tblClean[[#This Row],[Host Flag]]=0,1,0) -> 1
A23: =TRIM('Raw Data'!A19) -> LS-0015 | B23: =IF(ISNUMBER('Raw Data'!B19),INT('Raw Data'!B19),IFERROR(DATEVALUE('Raw Data'!B19),"")) -> 45813 | C23: =PROPER(TRIM('Raw Data'!C19)) -> Bianca Reyes | D23: =IF(ISNUMBER('Raw Data'!D19),MOD('Raw Data'!D19,1),IFERROR(TIMEVALUE('Raw Data'!D19),"")) -> 0.91666667 | E23: =IF(ISNUMBER('Raw Data'!E19),MOD('Raw Data'!E19,1),IFERROR(TIMEVALUE('Raw Data'!E19),"")) -> 0.020833333 | F23: =IF(ISNUMBER('Raw Data'!F19),'Raw Data'!F19,IFERROR(VALUE(SUBSTITUTE('Raw Data'!F19,",","")),"")) -> 26259 | G23: =IF(ISNUMBER('Raw Data'!G19),'Raw Data'!G19,IFERROR(VALUE(SUBSTITUTE('Raw Data'!G19,",","")),"")) -> 72 | H23: =IF(ISNUMBER('Raw Data'!H19),'Raw Data'!H19,IFERROR(VALUE(SUBSTITUTE('Raw Data'!H19,",","")),"")) -> 72608 | I23: =IF(ISNUMBER('Raw Data'!I19),'Raw Data'!I19,IFERROR(VALUE(SUBSTITUTE('Raw Data'!I19,",","")),"")) -> 892 | J23: =IF(AND(ISNUMBER(tblClean[[#This Row],[Start Time]]),ISNUMBER(tblClean[[#This Row],[End Time]])),ROUND(MOD(tblClean[[#This Row],[End Time]]-tblClean[[#This Row],[Start Time]],1)*24,2),"") -> 2.5 | K23: =IF(AND(ISNUMBER(tblClean[[#This Row],[Duration Hours]]),ISNUMBER(tblClean[[#This Row],[Attributed GMV PHP]])),IF(tblClean[[#This Row],[Duration Hours]]>0,tblClean[[#This Row],[Attributed GMV PHP]]/tblClean[[#This Row],[Duration Hours]],""),"") -> 10503.6 | L23: =IF(ISNUMBER(tblClean[[#This Row],[Date]]),DATE(YEAR(tblClean[[#This Row],[Date]]),MONTH(tblClean[[#This Row],[Date]]),1),"") -> 45809 | M23: =IF(ISNUMBER(tblClean[[#This Row],[Date]]),tblClean[[#This Row],[Date]]-WEEKDAY(tblClean[[#This Row],[Date]],2)+1,"") -> 45810 | N23: =IF(ISNUMBER(tblClean[[#This Row],[Week Start]]),(tblClean[[#This Row],[Week Start]]-MIN(tblClean[Week Start]))/7+1,"") -> 1 | O23: =IF(ISNUMBER(tblClean[[#This Row],[Date]]),CHOOSE(WEEKDAY(tblClean[[#This Row],[Date]],2),"Mon","Tue","Wed","Thu","Fri","Sat","Sun"),"") -> Thu | P23: =IF(ISNUMBER(tblClean[[#This Row],[Date]]),IF(WEEKDAY(tblClean[[#This Row],[Date]],2)>=6,"Weekend","Weekday"),"") -> Weekday | Q23: =IF(ISNUMBER(tblClean[[#This Row],[Start Time]]),IF(tblClean[[#This Row],[Start Time]]<TIME(6,0,0),"Late Night",IF(tblClean[[#This Row],[Start Time]]<TIME(12,0,0),"Morning",IF(tblClean[[#This Row],[Start Time]]<TIME(16,0,0),"Afternoon",IF(tblClean[[#This Row],[Start Time]]<TIME(19,0,0),"Early Evening",IF(tblClean[[#This Row],[Start Time]]<TIME(22,0,0),"Prime Time","Late Night"))))),"") -> Late Night | R23: =IF(ISNUMBER(tblClean[[#This Row],[Duration Hours]]),IF(tblClean[[#This Row],[Duration Hours]]<2,"Short (under 2h)",IF(tblClean[[#This Row],[Duration Hours]]<3,"Standard (2h to under 3h)","Long (3h or more)")),"") -> Standard (2h to under 3h) | S23: =IF(OR(NOT(ISNUMBER(tblClean[[#This Row],[Date]])),NOT(ISNUMBER(tblClean[[#This Row],[Start Time]])),NOT(ISNUMBER(tblClean[[#This Row],[End Time]])),NOT(ISNUMBER(tblClean[[#This Row],[Attributed GMV PHP]])),NOT(ISNUMBER(tblClean[[#This Row],[Items Sold]])),NOT(ISNUMBER(tblClean[[#This Row],[Livestream Views]])),NOT(ISNUMBER(tblClean[[#This Row],[New Followers]])),tblClean[[#This Row],[Host Name]]="",tblClean[[#This Row],[Session ID]]=""),1,0) -> 0 | T23: =IF(COUNTIF(tblClean[Session ID],tblClean[[#This Row],[Session ID]])>1,1,0) -> 0 | U23: =IF(OR(N(tblClean[[#This Row],[Attributed GMV PHP]])<0,N(tblClean[[#This Row],[Items Sold]])<0,N(tblClean[[#This Row],[Livestream Views]])<0,N(tblClean[[#This Row],[New Followers]])<0),1,0) -> 0 | V23: =IF(ISNUMBER(tblClean[[#This Row],[Duration Hours]]),IF(OR(tblClean[[#This Row],[Duration Hours]]<=0,tblClean[[#This Row],[Duration Hours]]>12),1,0),1) -> 0 | W23: =IF(COUNTIF(HostRoster,tblClean[[#This Row],[Host Name]])=0,1,0) -> 0 | X23: =IF(tblClean[[#This Row],[Missing Flag]]+tblClean[[#This Row],[Duplicate Flag]]+tblClean[[#This Row],[Negative Flag]]+tblClean[[#This Row],[Duration Flag]]+tblClean[[#This Row],[Host Flag]]=0,1,0) -> 1
A24: =TRIM('Raw Data'!A20) -> LS-0016 | B24: =IF(ISNUMBER('Raw Data'!B20),INT('Raw Data'!B20),IFERROR(DATEVALUE('Raw Data'!B20),"")) -> 45814 | C24: =PROPER(TRIM('Raw Data'!C20)) -> Bianca Reyes | D24: =IF(ISNUMBER('Raw Data'!D20),MOD('Raw Data'!D20,1),IFERROR(TIMEVALUE('Raw Data'!D20),"")) -> 0.41666667 | E24: =IF(ISNUMBER('Raw Data'!E20),MOD('Raw Data'!E20,1),IFERROR(TIMEVALUE('Raw Data'!E20),"")) -> 0.5 | F24: =IF(ISNUMBER('Raw Data'!F20),'Raw Data'!F20,IFERROR(VALUE(SUBSTITUTE('Raw Data'!F20,",","")),"")) -> 15845 | G24: =IF(ISNUMBER('Raw Data'!G20),'Raw Data'!G20,IFERROR(VALUE(SUBSTITUTE('Raw Data'!G20,",","")),"")) -> 55 | H24: =IF(ISNUMBER('Raw Data'!H20),'Raw Data'!H20,IFERROR(VALUE(SUBSTITUTE('Raw Data'!H20,",","")),"")) -> 55723 | I24: =IF(ISNUMBER('Raw Data'!I20),'Raw Data'!I20,IFERROR(VALUE(SUBSTITUTE('Raw Data'!I20,",","")),"")) -> 348 | J24: =IF(AND(ISNUMBER(tblClean[[#This Row],[Start Time]]),ISNUMBER(tblClean[[#This Row],[End Time]])),ROUND(MOD(tblClean[[#This Row],[End Time]]-tblClean[[#This Row],[Start Time]],1)*24,2),"") -> 2 | K24: =IF(AND(ISNUMBER(tblClean[[#This Row],[Duration Hours]]),ISNUMBER(tblClean[[#This Row],[Attributed GMV PHP]])),IF(tblClean[[#This Row],[Duration Hours]]>0,tblClean[[#This Row],[Attributed GMV PHP]]/tblClean[[#This Row],[Duration Hours]],""),"") -> 7922.5 | L24: =IF(ISNUMBER(tblClean[[#This Row],[Date]]),DATE(YEAR(tblClean[[#This Row],[Date]]),MONTH(tblClean[[#This Row],[Date]]),1),"") -> 45809 | M24: =IF(ISNUMBER(tblClean[[#This Row],[Date]]),tblClean[[#This Row],[Date]]-WEEKDAY(tblClean[[#This Row],[Date]],2)+1,"") -> 45810 | N24: =IF(ISNUMBER(tblClean[[#This Row],[Week Start]]),(tblClean[[#This Row],[Week Start]]-MIN(tblClean[Week Start]))/7+1,"") -> 1 | O24: =IF(ISNUMBER(tblClean[[#This Row],[Date]]),CHOOSE(WEEKDAY(tblClean[[#This Row],[Date]],2),"Mon","Tue","Wed","Thu","Fri","Sat","Sun"),"") -> Fri | P24: =IF(ISNUMBER(tblClean[[#This Row],[Date]]),IF(WEEKDAY(tblClean[[#This Row],[Date]],2)>=6,"Weekend","Weekday"),"") -> Weekday | Q24: =IF(ISNUMBER(tblClean[[#This Row],[Start Time]]),IF(tblClean[[#This Row],[Start Time]]<TIME(6,0,0),"Late Night",IF(tblClean[[#This Row],[Start Time]]<TIME(12,0,0),"Morning",IF(tblClean[[#This Row],[Start Time]]<TIME(16,0,0),"Afternoon",IF(tblClean[[#This Row],[Start Time]]<TIME(19,0,0),"Early Evening",IF(tblClean[[#This Row],[Start Time]]<TIME(22,0,0),"Prime Time","Late Night"))))),"") -> Morning | R24: =IF(ISNUMBER(tblClean[[#This Row],[Duration Hours]]),IF(tblClean[[#This Row],[Duration Hours]]<2,"Short (under 2h)",IF(tblClean[[#This Row],[Duration Hours]]<3,"Standard (2h to under 3h)","Long (3h or more)")),"") -> Standard (2h to under 3h) | S24: =IF(OR(NOT(ISNUMBER(tblClean[[#This Row],[Date]])),NOT(ISNUMBER(tblClean[[#This Row],[Start Time]])),NOT(ISNUMBER(tblClean[[#This Row],[End Time]])),NOT(ISNUMBER(tblClean[[#This Row],[Attributed GMV PHP]])),NOT(ISNUMBER(tblClean[[#This Row],[Items Sold]])),NOT(ISNUMBER(tblClean[[#This Row],[Livestream Views]])),NOT(ISNUMBER(tblClean[[#This Row],[New Followers]])),tblClean[[#This Row],[Host Name]]="",tblClean[[#This Row],[Session ID]]=""),1,0) -> 0 | T24: =IF(COUNTIF(tblClean[Session ID],tblClean[[#This Row],[Session ID]])>1,1,0) -> 0 | U24: =IF(OR(N(tblClean[[#This Row],[Attributed GMV PHP]])<0,N(tblClean[[#This Row],[Items Sold]])<0,N(tblClean[[#This Row],[Livestream Views]])<0,N(tblClean[[#This Row],[New Followers]])<0),1,0) -> 0 | V24: =IF(ISNUMBER(tblClean[[#This Row],[Duration Hours]]),IF(OR(tblClean[[#This Row],[Duration Hours]]<=0,tblClean[[#This Row],[Duration Hours]]>12),1,0),1) -> 0 | W24: =IF(COUNTIF(HostRoster,tblClean[[#This Row],[Host Name]])=0,1,0) -> 0 | X24: =IF(tblClean[[#This Row],[Missing Flag]]+tblClean[[#This Row],[Duplicate Flag]]+tblClean[[#This Row],[Negative Flag]]+tblClean[[#This Row],[Duration Flag]]+tblClean[[#This Row],[Host Flag]]=0,1,0) -> 1
A25: =TRIM('Raw Data'!A21) -> LS-0017 | B25: =IF(ISNUMBER('Raw Data'!B21),INT('Raw Data'!B21),IFERROR(DATEVALUE('Raw Data'!B21),"")) -> 45814 | C25: =PROPER(TRIM('Raw Data'!C21)) -> Dani Villanueva | D25: =IF(ISNUMBER('Raw Data'!D21),MOD('Raw Data'!D21,1),IFERROR(TIMEVALUE('Raw Data'!D21),"")) -> 0.54166667 | E25: =IF(ISNUMBER('Raw Data'!E21),MOD('Raw Data'!E21,1),IFERROR(TIMEVALUE('Raw Data'!E21),"")) -> 0.66666667 | F25: =IF(ISNUMBER('Raw Data'!F21),'Raw Data'!F21,IFERROR(VALUE(SUBSTITUTE('Raw Data'!F21,",","")),"")) -> 35724 | G25: =IF(ISNUMBER('Raw Data'!G21),'Raw Data'!G21,IFERROR(VALUE(SUBSTITUTE('Raw Data'!G21,",","")),"")) -> 100 | H25: =IF(ISNUMBER('Raw Data'!H21),'Raw Data'!H21,IFERROR(VALUE(SUBSTITUTE('Raw Data'!H21,",","")),"")) -> 84918 | I25: =IF(ISNUMBER('Raw Data'!I21),'Raw Data'!I21,IFERROR(VALUE(SUBSTITUTE('Raw Data'!I21,",","")),"")) -> 1102 | J25: =IF(AND(ISNUMBER(tblClean[[#This Row],[Start Time]]),ISNUMBER(tblClean[[#This Row],[End Time]])),ROUND(MOD(tblClean[[#This Row],[End Time]]-tblClean[[#This Row],[Start Time]],1)*24,2),"") -> 3 | K25: =IF(AND(ISNUMBER(tblClean[[#This Row],[Duration Hours]]),ISNUMBER(tblClean[[#This Row],[Attributed GMV PHP]])),IF(tblClean[[#This Row],[Duration Hours]]>0,tblClean[[#This Row],[Attributed GMV PHP]]/tblClean[[#This Row],[Duration Hours]],""),"") -> 11908 | L25: =IF(ISNUMBER(tblClean[[#This Row],[Date]]),DATE(YEAR(tblClean[[#This Row],[Date]]),MONTH(tblClean[[#This Row],[Date]]),1),"") -> 45809 | M25: =IF(ISNUMBER(tblClean[[#This Row],[Date]]),tblClean[[#This Row],[Date]]-WEEKDAY(tblClean[[#This Row],[Date]],2)+1,"") -> 45810 | N25: =IF(ISNUMBER(tblClean[[#This Row],[Week Start]]),(tblClean[[#This Row],[Week Start]]-MIN(tblClean[Week Start]))/7+1,"") -> 1 | O25: =IF(ISNUMBER(tblClean[[#This Row],[Date]]),CHOOSE(WEEKDAY(tblClean[[#This Row],[Date]],2),"Mon","Tue","Wed","Thu","Fri","Sat","Sun"),"") -> Fri | P25: =IF(ISNUMBER(tblClean[[#This Row],[Date]]),IF(WEEKDAY(tblClean[[#This Row],[Date]],2)>=6,"Weekend","Weekday"),"") -> Weekday | Q25: =IF(ISNUMBER(tblClean[[#This Row],[Start Time]]),IF(tblClean[[#This Row],[Start Time]]<TIME(6,0,0),"Late Night",IF(tblClean[[#This Row],[Start Time]]<TIME(12,0,0),"Morning",IF(tblClean[[#This Row],[Start Time]]<TIME(16,0,0),"Afternoon",IF(tblClean[[#This Row],[Start Time]]<TIME(19,0,0),"Early Evening",IF(tblClean[[#This Row],[Start Time]]<TIME(22,0,0),"Prime Time","Late Night"))))),"") -> Afternoon | R25: =IF(ISNUMBER(tblClean[[#This Row],[Duration Hours]]),IF(tblClean[[#This Row],[Duration Hours]]<2,"Short (under 2h)",IF(tblClean[[#This Row],[Duration Hours]]<3,"Standard (2h to under 3h)","Long (3h or more)")),"") -> Long (3h or more) | S25: =IF(OR(NOT(ISNUMBER(tblClean[[#This Row],[Date]])),NOT(ISNUMBER(tblClean[[#This Row],[Start Time]])),NOT(ISNUMBER(tblClean[[#This Row],[End Time]])),NOT(ISNUMBER(tblClean[[#This Row],[Attributed GMV PHP]])),NOT(ISNUMBER(tblClean[[#This Row],[Items Sold]])),NOT(ISNUMBER(tblClean[[#This Row],[Livestream Views]])),NOT(ISNUMBER(tblClean[[#This Row],[New Followers]])),tblClean[[#This Row],[Host Name]]="",tblClean[[#This Row],[Session ID]]=""),1,0) -> 0 | T25: =IF(COUNTIF(tblClean[Session ID],tblClean[[#This Row],[Session ID]])>1,1,0) -> 0 | U25: =IF(OR(N(tblClean[[#This Row],[Attributed GMV PHP]])<0,N(tblClean[[#This Row],[Items Sold]])<0,N(tblClean[[#This Row],[Livestream Views]])<0,N(tblClean[[#This Row],[New Followers]])<0),1,0) -> 0 | V25: =IF(ISNUMBER(tblClean[[#This Row],[Duration Hours]]),IF(OR(tblClean[[#This Row],[Duration Hours]]<=0,tblClean[[#This Row],[Duration Hours]]>12),1,0),1) -> 0 | W25: =IF(COUNTIF(HostRoster,tblClean[[#This Row],[Host Name]])=0,1,0) -> 0 | X25: =IF(tblClean[[#This Row],[Missing Flag]]+tblClean[[#This Row],[Duplicate Flag]]+tblClean[[#This Row],[Negative Flag]]+tblClean[[#This Row],[Duration Flag]]+tblClean[[#This Row],[Host Flag]]=0,1,0) -> 1
A26: =TRIM('Raw Data'!A22) -> LS-0018 | B26: =IF(ISNUMBER('Raw Data'!B22),INT('Raw Data'!B22),IFERROR(DATEVALUE('Raw Data'!B22),"")) -> 45814 | C26: =PROPER(TRIM('Raw Data'!C22)) -> Carlo Mendoza | D26: =IF(ISNUMBER('Raw Data'!D22),MOD('Raw Data'!D22,1),IFERROR(TIMEVALUE('Raw Data'!D22),"")) -> 0.66666667 | E26: =IF(ISNUMBER('Raw Data'!E22),MOD('Raw Data'!E22,1),IFERROR(TIMEVALUE('Raw Data'!E22),"")) -> 0.75 | F26: =IF(ISNUMBER('Raw Data'!F22),'Raw Data'!F22,IFERROR(VALUE(SUBSTITUTE('Raw Data'!F22,",","")),"")) -> 34920 | G26: =IF(ISNUMBER('Raw Data'!G22),'Raw Data'!G22,IFERROR(VALUE(SUBSTITUTE('Raw Data'!G22,",","")),"")) -> 120 | H26: =IF(ISNUMBER('Raw Data'!H22),'Raw Data'!H22,IFERROR(VALUE(SUBSTITUTE('Raw Data'!H22,",","")),"")) -> 110731 | I26: =IF(ISNUMBER('Raw Data'!I22),'Raw Data'!I22,IFERROR(VALUE(SUBSTITUTE('Raw Data'!I22,",","")),"")) -> 952 | J26: =IF(AND(ISNUMBER(tblClean[[#This Row],[Start Time]]),ISNUMBER(tblClean[[#This Row],[End Time]])),ROUND(MOD(tblClean[[#This Row],[End Time]]-tblClean[[#This Row],[Start Time]],1)*24,2),"") -> 2 | K26: =IF(AND(ISNUMBER(tblClean[[#This Row],[Duration Hours]]),ISNUMBER(tblClean[[#This Row],[Attributed GMV PHP]])),IF(tblClean[[#This Row],[Duration Hours]]>0,tblClean[[#This Row],[Attributed GMV PHP]]/tblClean[[#This Row],[Duration Hours]],""),"") -> 17460 | L26: =IF(ISNUMBER(tblClean[[#This Row],[Date]]),DATE(YEAR(tblClean[[#This Row],[Date]]),MONTH(tblClean[[#This Row],[Date]]),1),"") -> 45809 | M26: =IF(ISNUMBER(tblClean[[#This Row],[Date]]),tblClean[[#This Row],[Date]]-WEEKDAY(tblClean[[#This Row],[Date]],2)+1,"") -> 45810 | N26: =IF(ISNUMBER(tblClean[[#This Row],[Week Start]]),(tblClean[[#This Row],[Week Start]]-MIN(tblClean[Week Start]))/7+1,"") -> 1 | O26: =IF(ISNUMBER(tblClean[[#This Row],[Date]]),CHOOSE(WEEKDAY(tblClean[[#This Row],[Date]],2),"Mon","Tue","Wed","Thu","Fri","Sat","Sun"),"") -> Fri | P26: =IF(ISNUMBER(tblClean[[#This Row],[Date]]),IF(WEEKDAY(tblClean[[#This Row],[Date]],2)>=6,"Weekend","Weekday"),"") -> Weekday | Q26: =IF(ISNUMBER(tblClean[[#This Row],[Start Time]]),IF(tblClean[[#This Row],[Start Time]]<TIME(6,0,0),"Late Night",IF(tblClean[[#This Row],[Start Time]]<TIME(12,0,0),"Morning",IF(tblClean[[#This Row],[Start Time]]<TIME(16,0,0),"Afternoon",IF(tblClean[[#This Row],[Start Time]]<TIME(19,0,0),"Early Evening",IF(tblClean[[#This Row],[Start Time]]<TIME(22,0,0),"Prime Time","Late Night"))))),"") -> Early Evening | R26: =IF(ISNUMBER(tblClean[[#This Row],[Duration Hours]]),IF(tblClean[[#This Row],[Duration Hours]]<2,"Short (under 2h)",IF(tblClean[[#This Row],[Duration Hours]]<3,"Standard (2h to under 3h)","Long (3h or more)")),"") -> Standard (2h to under 3h) | S26: =IF(OR(NOT(ISNUMBER(tblClean[[#This Row],[Date]])),NOT(ISNUMBER(tblClean[[#This Row],[Start Time]])),NOT(ISNUMBER(tblClean[[#This Row],[End Time]])),NOT(ISNUMBER(tblClean[[#This Row],[Attributed GMV PHP]])),NOT(ISNUMBER(tblClean[[#This Row],[Items Sold]])),NOT(ISNUMBER(tblClean[[#This Row],[Livestream Views]])),NOT(ISNUMBER(tblClean[[#This Row],[New Followers]])),tblClean[[#This Row],[Host Name]]="",tblClean[[#This Row],[Session ID]]=""),1,0) -> 0 | T26: =IF(COUNTIF(tblClean[Session ID],tblClean[[#This Row],[Session ID]])>1,1,0) -> 0 | U26: =IF(OR(N(tblClean[[#This Row],[Attributed GMV PHP]])<0,N(tblClean[[#This Row],[Items Sold]])<0,N(tblClean[[#This Row],[Livestream Views]])<0,N(tblClean[[#This Row],[New Followers]])<0),1,0) -> 0 | V26: =IF(ISNUMBER(tblClean[[#This Row],[Duration Hours]]),IF(OR(tblClean[[#This Row],[Duration Hours]]<=0,tblClean[[#This Row],[Duration Hours]]>12),1,0),1) -> 0 | W26: =IF(COUNTIF(HostRoster,tblClean[[#This Row],[Host Name]])=0,1,0) -> 0 | X26: =IF(tblClean[[#This Row],[Missing Flag]]+tblClean[[#This Row],[Duplicate Flag]]+tblClean[[#This Row],[Negative Flag]]+tblClean[[#This Row],[Duration Flag]]+tblClean[[#This Row],[Host Flag]]=0,1,0) -> 1
... A382: =TRIM('Raw Data'!A378) -> LS-0374 | B382: =IF(ISNUMBER('Raw Data'!B378),INT('Raw Data'!B378),IFERROR(DATEVALUE('Raw Data'!B378),"")) -> 45900 | C382: =PROPER(TRIM('Raw Data'!C378)) -> Carlo Mendoza | D382: =IF(ISNUMBER('Raw Data'!D378),MOD('Raw Data'!D378,1),IFERROR(TIMEVALUE('Raw Data'!D378),"")) -> 0.91666667 | E382: =IF(ISNUMBER('Raw Data'!E378),MOD('Raw Data'!E378,1),IFERROR(TIMEVALUE('Raw Data'!E378),"")) -> 0.020833333 | F382: =IF(ISNUMBER('Raw Data'!F378),'Raw Data'!F378,IFERROR(VALUE(SUBSTITUTE('Raw Data'!F378,",","")),"")) -> 51021 | G382: =IF(ISNUMBER('Raw Data'!G378),'Raw Data'!G378,IFERROR(VALUE(SUBSTITUTE('Raw Data'!G378,",","")),"")) -> 139 | H382: =IF(ISNUMBER('Raw Data'!H378),'Raw Data'!H378,IFERROR(VALUE(SUBSTITUTE('Raw Data'!H378,",","")),"")) -> 216876 | I382: =IF(ISNUMBER('Raw Data'!I378),'Raw Data'!I378,IFERROR(VALUE(SUBSTITUTE('Raw Data'!I378,",","")),"")) -> 1414 | J382: =IF(AND(ISNUMBER(tblClean[[#This Row],[Start Time]]),ISNUMBER(tblClean[[#This Row],[End Time]])),ROUND(MOD(tblClean[[#This Row],[End Time]]-tblClean[[#This Row],[Start Time]],1)*24,2),"") -> 2.5 | K382: =IF(AND(ISNUMBER(tblClean[[#This Row],[Duration Hours]]),ISNUMBER(tblClean[[#This Row],[Attributed GMV PHP]])),IF(tblClean[[#This Row],[Duration Hours]]>0,tblClean[[#This Row],[Attributed GMV PHP]]/tblClean[[#This Row],[Duration Hours]],""),"") -> 20408.4 | L382: =IF(ISNUMBER(tblClean[[#This Row],[Date]]),DATE(YEAR(tblClean[[#This Row],[Date]]),MONTH(tblClean[[#This Row],[Date]]),1),"") -> 45870 | M382: =IF(ISNUMBER(tblClean[[#This Row],[Date]]),tblClean[[#This Row],[Date]]-WEEKDAY(tblClean[[#This Row],[Date]],2)+1,"") -> 45894 | N382: =IF(ISNUMBER(tblClean[[#This Row],[Week Start]]),(tblClean[[#This Row],[Week Start]]-MIN(tblClean[Week Start]))/7+1,"") -> 13 | O382: =IF(ISNUMBER(tblClean[[#This Row],[Date]]),CHOOSE(WEEKDAY(tblClean[[#This Row],[Date]],2),"Mon","Tue","Wed","Thu","Fri","Sat","Sun"),"") -> Sun | P382: =IF(ISNUMBER(tblClean[[#This Row],[Date]]),IF(WEEKDAY(tblClean[[#This Row],[Date]],2)>=6,"Weekend","Weekday"),"") -> Weekend | Q382: =IF(ISNUMBER(tblClean[[#This Row],[Start Time]]),IF(tblClean[[#This Row],[Start Time]]<TIME(6,0,0),"Late Night",IF(tblClean[[#This Row],[Start Time]]<TIME(12,0,0),"Morning",IF(tblClean[[#This Row],[Start Time]]<TIME(16,0,0),"Afternoon",IF(tblClean[[#This Row],[Start Time]]<TIME(19,0,0),"Early Evening",IF(tblClean[[#This Row],[Start Time]]<TIME(22,0,0),"Prime Time","Late Night"))))),"") -> Late Night | R382: =IF(ISNUMBER(tblClean[[#This Row],[Duration Hours]]),IF(tblClean[[#This Row],[Duration Hours]]<2,"Short (under 2h)",IF(tblClean[[#This Row],[Duration Hours]]<3,"Standard (2h to under 3h)","Long (3h or more)")),"") -> Standard (2h to under 3h) | S382: =IF(OR(NOT(ISNUMBER(tblClean[[#This Row],[Date]])),NOT(ISNUMBER(tblClean[[#This Row],[Start Time]])),NOT(ISNUMBER(tblClean[[#This Row],[End Time]])),NOT(ISNUMBER(tblClean[[#This Row],[Attributed GMV PHP]])),NOT(ISNUMBER(tblClean[[#This Row],[Items Sold]])),NOT(ISNUMBER(tblClean[[#This Row],[Livestream Views]])),NOT(ISNUMBER(tblClean[[#This Row],[New Followers]])),tblClean[[#This Row],[Host Name]]="",tblClean[[#This Row],[Session ID]]=""),1,0) -> 0 | T382: =IF(COUNTIF(tblClean[Session ID],tblClean[[#This Row],[Session ID]])>1,1,0) -> 0 | U382: =IF(OR(N(tblClean[[#This Row],[Attributed GMV PHP]])<0,N(tblClean[[#This Row],[Items Sold]])<0,N(tblClean[[#This Row],[Livestream Views]])<0,N(tblClean[[#This Row],[New Followers]])<0),1,0) -> 0 | V382: =IF(ISNUMBER(tblClean[[#This Row],[Duration Hours]]),IF(OR(tblClean[[#This Row],[Duration Hours]]<=0,tblClean[[#This Row],[Duration Hours]]>12),1,0),1) -> 0 | W382: =IF(COUNTIF(HostRoster,tblClean[[#This Row],[Host Name]])=0,1,0) -> 0 | X382: =IF(tblClean[[#This Row],[Missing Flag]]+tblClean[[#This Row],[Duplicate Flag]]+tblClean[[#This Row],[Negative Flag]]+tblClean[[#This Row],[Duration Flag]]+tblClean[[#This Row],[Host Flag]]=0,1,0) -> 1

Sheet Daily Sales
A1: DAILY SALES PERFORMANCE
A2: One row per calendar day, calculated from Cleaned Data (SUMIFS / COUNTIFS). Synthetic data — portfolio demonstration.
A3: Highlights: green = top 10% GMV per Hour, red = bottom 10%. 7-Day Avg GMV = trailing average (fewer days at the start of the period). GMV per Hour = GMV ÷ hours (weighted).
A5: Date | B5: Day | C5: Sessions | D5: Livestream Hours | E5: Total GMV | F5: Items Sold | G5: GMV per Hour | H5: 7-Day Avg GMV
A6: =MIN(tblClean[Date]) -> 45810 | B6: =CHOOSE(WEEKDAY(A6,2),"Mon","Tue","Wed","Thu","Fri","Sat","Sun") -> Mon | C6: =COUNTIFS(tblClean[Date],$A6,tblClean[Include],1) -> 3 | D6: =SUMIFS(tblClean[Duration Hours],tblClean[Date],$A6,tblClean[Include],1) -> 7.5 | E6: =SUMIFS(tblClean[Attributed GMV PHP],tblClean[Date],$A6,tblClean[Include],1) -> 85426 | F6: =SUMIFS(tblClean[Items Sold],tblClean[Date],$A6,tblClean[Include],1) -> 234 | G6: =IF(D6>0,E6/D6,"n/a") -> 11390.133 | H6: =AVERAGE(INDEX($E$6:$E$96,MAX(1,ROW()-ROW($E$6)-5)):E6) -> 85426
A7: =A6+1 -> 45811 | B7: =CHOOSE(WEEKDAY(A7,2),"Mon","Tue","Wed","Thu","Fri","Sat","Sun") -> Tue | C7: =COUNTIFS(tblClean[Date],$A7,tblClean[Include],1) -> 5 | D7: =SUMIFS(tblClean[Duration Hours],tblClean[Date],$A7,tblClean[Include],1) -> 12 | E7: =SUMIFS(tblClean[Attributed GMV PHP],tblClean[Date],$A7,tblClean[Include],1) -> 177219 | F7: =SUMIFS(tblClean[Items Sold],tblClean[Date],$A7,tblClean[Include],1) -> 523 | G7: =IF(D7>0,E7/D7,"n/a") -> 14768.25 | H7: =AVERAGE(INDEX($E$6:$E$96,MAX(1,ROW()-ROW($E$6)-5)):E7) -> 131322.5
A8: =A7+1 -> 45812 | B8: =CHOOSE(WEEKDAY(A8,2),"Mon","Tue","Wed","Thu","Fri","Sat","Sun") -> Wed | C8: =COUNTIFS(tblClean[Date],$A8,tblClean[Include],1) -> 3 | D8: =SUMIFS(tblClean[Duration Hours],tblClean[Date],$A8,tblClean[Include],1) -> 8.5 | E8: =SUMIFS(tblClean[Attributed GMV PHP],tblClean[Date],$A8,tblClean[Include],1) -> 59562 | F8: =SUMIFS(tblClean[Items Sold],tblClean[Date],$A8,tblClean[Include],1) -> 172 | G8: =IF(D8>0,E8/D8,"n/a") -> 7007.2941 | H8: =AVERAGE(INDEX($E$6:$E$96,MAX(1,ROW()-ROW($E$6)-5)):E8) -> 107402.33
A9: =A8+1 -> 45813 | B9: =CHOOSE(WEEKDAY(A9,2),"Mon","Tue","Wed","Thu","Fri","Sat","Sun") -> Thu | C9: =COUNTIFS(tblClean[Date],$A9,tblClean[Include],1) -> 4 | D9: =SUMIFS(tblClean[Duration Hours],tblClean[Date],$A9,tblClean[Include],1) -> 9 | E9: =SUMIFS(tblClean[Attributed GMV PHP],tblClean[Date],$A9,tblClean[Include],1) -> 84165 | F9: =SUMIFS(tblClean[Items Sold],tblClean[Date],$A9,tblClean[Include],1) -> 228 | G9: =IF(D9>0,E9/D9,"n/a") -> 9351.6667 | H9: =AVERAGE(INDEX($E$6:$E$96,MAX(1,ROW()-ROW($E$6)-5)):E9) -> 101593
A10: =A9+1 -> 45814 | B10: =CHOOSE(WEEKDAY(A10,2),"Mon","Tue","Wed","Thu","Fri","Sat","Sun") -> Fri | C10: =COUNTIFS(tblClean[Date],$A10,tblClean[Include],1) -> 5 | D10: =SUMIFS(tblClean[Duration Hours],tblClean[Date],$A10,tblClean[Include],1) -> 11.5 | E10: =SUMIFS(tblClean[Attributed GMV PHP],tblClean[Date],$A10,tblClean[Include],1) -> 176989 | F10: =SUMIFS(tblClean[Items Sold],tblClean[Date],$A10,tblClean[Include],1) -> 548 | G10: =IF(D10>0,E10/D10,"n/a") -> 15390.348 | H10: =AVERAGE(INDEX($E$6:$E$96,MAX(1,ROW()-ROW($E$6)-5)):E10) -> 116672.2
A11: =A10+1 -> 45815 | B11: =CHOOSE(WEEKDAY(A11,2),"Mon","Tue","Wed","Thu","Fri","Sat","Sun") -> Sat | C11: =COUNTIFS(tblClean[Date],$A11,tblClean[Include],1) -> 5 | D11: =SUMIFS(tblClean[Duration Hours],tblClean[Date],$A11,tblClean[Include],1) -> 9.5 | E11: =SUMIFS(tblClean[Attributed GMV PHP],tblClean[Date],$A11,tblClean[Include],1) -> 116380 | F11: =SUMIFS(tblClean[Items Sold],tblClean[Date],$A11,tblClean[Include],1) -> 355 | G11: =IF(D11>0,E11/D11,"n/a") -> 12250.526 | H11: =AVERAGE(INDEX($E$6:$E$96,MAX(1,ROW()-ROW($E$6)-5)):E11) -> 116623.5
A12: =A11+1 -> 45816 | B12: =CHOOSE(WEEKDAY(A12,2),"Mon","Tue","Wed","Thu","Fri","Sat","Sun") -> Sun | C12: =COUNTIFS(tblClean[Date],$A12,tblClean[Include],1) -> 4 | D12: =SUMIFS(tblClean[Duration Hours],tblClean[Date],$A12,tblClean[Include],1) -> 10 | E12: =SUMIFS(tblClean[Attributed GMV PHP],tblClean[Date],$A12,tblClean[Include],1) -> 68562 | F12: =SUMIFS(tblClean[Items Sold],tblClean[Date],$A12,tblClean[Include],1) -> 208 | G12: =IF(D12>0,E12/D12,"n/a") -> 6856.2 | H12: =AVERAGE(INDEX($E$6:$E$96,MAX(1,ROW()-ROW($E$6)-5)):E12) -> 109757.57
A13: =A12+1 -> 45817 | B13: =CHOOSE(WEEKDAY(A13,2),"Mon","Tue","Wed","Thu","Fri","Sat","Sun") -> Mon | C13: =COUNTIFS(tblClean[Date],$A13,tblClean[Include],1) -> 3 | D13: =SUMIFS(tblClean[Duration Hours],tblClean[Date],$A13,tblClean[Include],1) -> 7.5 | E13: =SUMIFS(tblClean[Attributed GMV PHP],tblClean[Date],$A13,tblClean[Include],1) -> 92331 | F13: =SUMIFS(tblClean[Items Sold],tblClean[Date],$A13,tblClean[Include],1) -> 317 | G13: =IF(D13>0,E13/D13,"n/a") -> 12310.8 | H13: =AVERAGE(INDEX($E$6:$E$96,MAX(1,ROW()-ROW($E$6)-5)):E13) -> 110744
A14: =A13+1 -> 45818 | B14: =CHOOSE(WEEKDAY(A14,2),"Mon","Tue","Wed","Thu","Fri","Sat","Sun") -> Tue | C14: =COUNTIFS(tblClean[Date],$A14,tblClean[Include],1) -> 5 | D14: =SUMIFS(tblClean[Duration Hours],tblClean[Date],$A14,tblClean[Include],1) -> 12 | E14: =SUMIFS(tblClean[Attributed GMV PHP],tblClean[Date],$A14,tblClean[Include],1) -> 111327 | F14: =SUMIFS(tblClean[Items Sold],tblClean[Date],$A14,tblClean[Include],1) -> 318 | G14: =IF(D14>0,E14/D14,"n/a") -> 9277.25 | H14: =AVERAGE(INDEX($E$6:$E$96,MAX(1,ROW()-ROW($E$6)-5)):E14) -> 101330.86
A15: =A14+1 -> 45819 | B15: =CHOOSE(WEEKDAY(A15,2),"Mon","Tue","Wed","Thu","Fri","Sat","Sun") -> Wed | C15: =COUNTIFS(tblClean[Date],$A15,tblClean[Include],1) -> 5 | D15: =SUMIFS(tblClean[Duration Hours],tblClean[Date],$A15,tblClean[Include],1) -> 11 | E15: =SUMIFS(tblClean[Attributed GMV PHP],tblClean[Date],$A15,tblClean[Include],1) -> 93704 | F15: =SUMIFS(tblClean[Items Sold],tblClean[Date],$A15,tblClean[Include],1) -> 269 | G15: =IF(D15>0,E15/D15,"n/a") -> 8518.5455 | H15: =AVERAGE(INDEX($E$6:$E$96,MAX(1,ROW()-ROW($E$6)-5)):E15) -> 106208.29
A16: =A15+1 -> 45820 | B16: =CHOOSE(WEEKDAY(A16,2),"Mon","Tue","Wed","Thu","Fri","Sat","Sun") -> Thu | C16: =COUNTIFS(tblClean[Date],$A16,tblClean[Include],1) -> 3 | D16: =SUMIFS(tblClean[Duration Hours],tblClean[Date],$A16,tblClean[Include],1) -> 8 | E16: =SUMIFS(tblClean[Attributed GMV PHP],tblClean[Date],$A16,tblClean[Include],1) -> 36562 | F16: =SUMIFS(tblClean[Items Sold],tblClean[Date],$A16,tblClean[Include],1) -> 105 | G16: =IF(D16>0,E16/D16,"n/a") -> 4570.25 | H16: =AVERAGE(INDEX($E$6:$E$96,MAX(1,ROW()-ROW($E$6)-5)):E16) -> 99407.857
A17: =A16+1 -> 45821 | B17: =CHOOSE(WEEKDAY(A17,2),"Mon","Tue","Wed","Thu","Fri","Sat","Sun") -> Fri | C17: =COUNTIFS(tblClean[Date],$A17,tblClean[Include],1) -> 4 | D17: =SUMIFS(tblClean[Duration Hours],tblClean[Date],$A17,tblClean[Include],1) -> 10.5 | E17: =SUMIFS(tblClean[Attributed GMV PHP],tblClean[Date],$A17,tblClean[Include],1) -> 123902 | F17: =SUMIFS(tblClean[Items Sold],tblClean[Date],$A17,tblClean[Include],1) -> 356 | G17: =IF(D17>0,E17/D17,"n/a") -> 11800.19 | H17: =AVERAGE(INDEX($E$6:$E$96,MAX(1,ROW()-ROW($E$6)-5)):E17) -> 91824
A18: =A17+1 -> 45822 | B18: =CHOOSE(WEEKDAY(A18,2),"Mon","Tue","Wed","Thu","Fri","Sat","Sun") -> Sat | C18: =COUNTIFS(tblClean[Date],$A18,tblClean[Include],1) -> 4 | D18: =SUMIFS(tblClean[Duration Hours],tblClean[Date],$A18,tblClean[Include],1) -> 9 | E18: =SUMIFS(tblClean[Attributed GMV PHP],tblClean[Date],$A18,tblClean[Include],1) -> 134548 | F18: =SUMIFS(tblClean[Items Sold],tblClean[Date],$A18,tblClean[Include],1) -> 417 | G18: =IF(D18>0,E18/D18,"n/a") -> 14949.778 | H18: =AVERAGE(INDEX($E$6:$E$96,MAX(1,ROW()-ROW($E$6)-5)):E18) -> 94419.429
... A96: =A95+1 -> 45900 | B96: =CHOOSE(WEEKDAY(A96,2),"Mon","Tue","Wed","Thu","Fri","Sat","Sun") -> Sun | C96: =COUNTIFS(tblClean[Date],$A96,tblClean[Include],1) -> 3 | D96: =SUMIFS(tblClean[Duration Hours],tblClean[Date],$A96,tblClean[Include],1) -> 6 | E96: =SUMIFS(tblClean[Attributed GMV PHP],tblClean[Date],$A96,tblClean[Include],1) -> 134981 | F96: =SUMIFS(tblClean[Items Sold],tblClean[Date],$A96,tblClean[Include],1) -> 385 | G96: =IF(D96>0,E96/D96,"n/a") -> 22496.833 | H96: =AVERAGE(INDEX($E$6:$E$96,MAX(1,ROW()-ROW($E$6)-5)):E96) -> 113286.57
A97: TOTAL | C97: =SUM(C6:C96) -> 374 | D97: =SUM(D6:D96) -> 885.5 | E97: =SUM(E6:E96) -> 11153095 | F97: =SUM(F6:F96) -> 33116 | G97: =IF(D97>0,E97/D97,0) -> 12595.251
A98: Raw Data total | C98: =ROWS(tblRaw[Session ID]) -> 374 | D98: =SUMPRODUCT(MOD(tblRaw[End Time]-tblRaw[Start Time],1))*24 -> 885.5 | E98: =SUM(tblRaw[Attributed GMV PHP]) -> 11153095 | F98: =SUM(tblRaw[Items Sold]) -> 33116
A99: Difference | C99: =C97-C98 -> 0 | D99: =ROUND(D97-D98,2) -> 0 | E99: =E97-E98 -> 0 | F99: =F97-F98 -> 0 | G99: =IF(AND(C99=0,D99=0,E99=0,F99=0),"✔ Reconciled","✖ Check") -> ✔ Reconciled

Sheet Weekly Summary
A1: WEEKLY SALES SUMMARY
A2: Weeks run Monday–Sunday and are derived from Cleaned Data. Synthetic data — portfolio demonstration.
A3: Week-over-week (WoW) % = (current − previous) ÷ previous. Shown as n/a for the first week or when the previous week's GMV is zero or missing.
A5: Week # | B5: Week Start | C5: Week End | D5: Total GMV | E5: Items Sold | F5: Sessions | G5: Livestream Hours | H5: GMV per Hour | I5: WoW GMV Change | J5: WoW GMV Change %
A6: 1 | B6: =MIN(tblClean[Week Start])+(A6-1)*7 -> 45810 | C6: =B6+6 -> 45816 | D6: =SUMIFS(tblClean[Attributed GMV PHP],tblClean[Week Start],$B6,tblClean[Include],1) -> 768303 | E6: =SUMIFS(tblClean[Items Sold],tblClean[Week Start],$B6,tblClean[Include],1) -> 2268 | F6: =COUNTIFS(tblClean[Week Start],$B6,tblClean[Include],1) -> 29 | G6: =SUMIFS(tblClean[Duration Hours],tblClean[Week Start],$B6,tblClean[Include],1) -> 68 | H6: =IF(G6>0,D6/G6,"n/a") -> 11298.574 | I6: =IF(ISNUMBER(D5),D6-D5,"n/a") -> n/a | J6: =IF(ISNUMBER(D5),IF(D5>0,(D6-D5)/D5,"n/a"),"n/a") -> n/a
A7: 2 | B7: =MIN(tblClean[Week Start])+(A7-1)*7 -> 45817 | C7: =B7+6 -> 45823 | D7: =SUMIFS(tblClean[Attributed GMV PHP],tblClean[Week Start],$B7,tblClean[Include],1) -> 698741 | E7: =SUMIFS(tblClean[Items Sold],tblClean[Week Start],$B7,tblClean[Include],1) -> 2104 | F7: =COUNTIFS(tblClean[Week Start],$B7,tblClean[Include],1) -> 27 | G7: =SUMIFS(tblClean[Duration Hours],tblClean[Week Start],$B7,tblClean[Include],1) -> 65 | H7: =IF(G7>0,D7/G7,"n/a") -> 10749.862 | I7: =IF(ISNUMBER(D6),D7-D6,"n/a") -> -69562 | J7: =IF(ISNUMBER(D6),IF(D6>0,(D7-D6)/D6,"n/a"),"n/a") -> -0.0905398
A8: 3 | B8: =MIN(tblClean[Week Start])+(A8-1)*7 -> 45824 | C8: =B8+6 -> 45830 | D8: =SUMIFS(tblClean[Attributed GMV PHP],tblClean[Week Start],$B8,tblClean[Include],1) -> 678714 | E8: =SUMIFS(tblClean[Items Sold],tblClean[Week Start],$B8,tblClean[Include],1) -> 1968 | F8: =COUNTIFS(tblClean[Week Start],$B8,tblClean[Include],1) -> 27 | G8: =SUMIFS(tblClean[Duration Hours],tblClean[Week Start],$B8,tblClean[Include],1) -> 67 | H8: =IF(G8>0,D8/G8,"n/a") -> 10130.06 | I8: =IF(ISNUMBER(D7),D8-D7,"n/a") -> -20027 | J8: =IF(ISNUMBER(D7),IF(D7>0,(D8-D7)/D7,"n/a"),"n/a") -> -0.02866155
A9: 4 | B9: =MIN(tblClean[Week Start])+(A9-1)*7 -> 45831 | C9: =B9+6 -> 45837 | D9: =SUMIFS(tblClean[Attributed GMV PHP],tblClean[Week Start],$B9,tblClean[Include],1) -> 746297 | E9: =SUMIFS(tblClean[Items Sold],tblClean[Week Start],$B9,tblClean[Include],1) -> 2207 | F9: =COUNTIFS(tblClean[Week Start],$B9,tblClean[Include],1) -> 31 | G9: =SUMIFS(tblClean[Duration Hours],tblClean[Week Start],$B9,tblClean[Include],1) -> 74 | H9: =IF(G9>0,D9/G9,"n/a") -> 10085.095 | I9: =IF(ISNUMBER(D8),D9-D8,"n/a") -> 67583 | J9: =IF(ISNUMBER(D8),IF(D8>0,(D9-D8)/D8,"n/a"),"n/a") -> 0.099575079
A10: 5 | B10: =MIN(tblClean[Week Start])+(A10-1)*7 -> 45838 | C10: =B10+6 -> 45844 | D10: =SUMIFS(tblClean[Attributed GMV PHP],tblClean[Week Start],$B10,tblClean[Include],1) -> 908150 | E10: =SUMIFS(tblClean[Items Sold],tblClean[Week Start],$B10,tblClean[Include],1) -> 2750 | F10: =COUNTIFS(tblClean[Week Start],$B10,tblClean[Include],1) -> 28 | G10: =SUMIFS(tblClean[Duration Hours],tblClean[Week Start],$B10,tblClean[Include],1) -> 65 | H10: =IF(G10>0,D10/G10,"n/a") -> 13971.538 | I10: =IF(ISNUMBER(D9),D10-D9,"n/a") -> 161853 | J10: =IF(ISNUMBER(D9),IF(D9>0,(D10-D9)/D9,"n/a"),"n/a") -> 0.21687478
A11: 6 | B11: =MIN(tblClean[Week Start])+(A11-1)*7 -> 45845 | C11: =B11+6 -> 45851 | D11: =SUMIFS(tblClean[Attributed GMV PHP],tblClean[Week Start],$B11,tblClean[Include],1) -> 920555 | E11: =SUMIFS(tblClean[Items Sold],tblClean[Week Start],$B11,tblClean[Include],1) -> 2726 | F11: =COUNTIFS(tblClean[Week Start],$B11,tblClean[Include],1) -> 28 | G11: =SUMIFS(tblClean[Duration Hours],tblClean[Week Start],$B11,tblClean[Include],1) -> 66.5 | H11: =IF(G11>0,D11/G11,"n/a") -> 13842.932 | I11: =IF(ISNUMBER(D10),D11-D10,"n/a") -> 12405 | J11: =IF(ISNUMBER(D10),IF(D10>0,(D11-D10)/D10,"n/a"),"n/a") -> 0.013659638
A12: 7 | B12: =MIN(tblClean[Week Start])+(A12-1)*7 -> 45852 | C12: =B12+6 -> 45858 | D12: =SUMIFS(tblClean[Attributed GMV PHP],tblClean[Week Start],$B12,tblClean[Include],1) -> 845071 | E12: =SUMIFS(tblClean[Items Sold],tblClean[Week Start],$B12,tblClean[Include],1) -> 2506 | F12: =COUNTIFS(tblClean[Week Start],$B12,tblClean[Include],1) -> 25 | G12: =SUMIFS(tblClean[Duration Hours],tblClean[Week Start],$B12,tblClean[Include],1) -> 58 | H12: =IF(G12>0,D12/G12,"n/a") -> 14570.19 | I12: =IF(ISNUMBER(D11),D12-D11,"n/a") -> -75484 | J12: =IF(ISNUMBER(D11),IF(D11>0,(D12-D11)/D11,"n/a"),"n/a") -> -0.08199836
A13: 8 | B13: =MIN(tblClean[Week Start])+(A13-1)*7 -> 45859 | C13: =B13+6 -> 45865 | D13: =SUMIFS(tblClean[Attributed GMV PHP],tblClean[Week Start],$B13,tblClean[Include],1) -> 790818 | E13: =SUMIFS(tblClean[Items Sold],tblClean[Week Start],$B13,tblClean[Include],1) -> 2370 | F13: =COUNTIFS(tblClean[Week Start],$B13,tblClean[Include],1) -> 32 | G13: =SUMIFS(tblClean[Duration Hours],tblClean[Week Start],$B13,tblClean[Include],1) -> 74.5 | H13: =IF(G13>0,D13/G13,"n/a") -> 10615.007 | I13: =IF(ISNUMBER(D12),D13-D12,"n/a") -> -54253 | J13: =IF(ISNUMBER(D12),IF(D12>0,(D13-D12)/D12,"n/a"),"n/a") -> -0.064199339
A14: 9 | B14: =MIN(tblClean[Week Start])+(A14-1)*7 -> 45866 | C14: =B14+6 -> 45872 | D14: =SUMIFS(tblClean[Attributed GMV PHP],tblClean[Week Start],$B14,tblClean[Include],1) -> 1170261 | E14: =SUMIFS(tblClean[Items Sold],tblClean[Week Start],$B14,tblClean[Include],1) -> 3639 | F14: =COUNTIFS(tblClean[Week Start],$B14,tblClean[Include],1) -> 30 | G14: =SUMIFS(tblClean[Duration Hours],tblClean[Week Start],$B14,tblClean[Include],1) -> 73.5 | H14: =IF(G14>0,D14/G14,"n/a") -> 15921.918 | I14: =IF(ISNUMBER(D13),D14-D13,"n/a") -> 379443 | J14: =IF(ISNUMBER(D13),IF(D13>0,(D14-D13)/D13,"n/a"),"n/a") -> 0.47981078
A15: 10 | B15: =MIN(tblClean[Week Start])+(A15-1)*7 -> 45873 | C15: =B15+6 -> 45879 | D15: =SUMIFS(tblClean[Attributed GMV PHP],tblClean[Week Start],$B15,tblClean[Include],1) -> 1038468 | E15: =SUMIFS(tblClean[Items Sold],tblClean[Week Start],$B15,tblClean[Include],1) -> 3007 | F15: =COUNTIFS(tblClean[Week Start],$B15,tblClean[Include],1) -> 31 | G15: =SUMIFS(tblClean[Duration Hours],tblClean[Week Start],$B15,tblClean[Include],1) -> 76.5 | H15: =IF(G15>0,D15/G15,"n/a") -> 13574.745 | I15: =IF(ISNUMBER(D14),D15-D14,"n/a") -> -131793 | J15: =IF(ISNUMBER(D14),IF(D14>0,(D15-D14)/D14,"n/a"),"n/a") -> -0.11261847
A16: 11 | B16: =MIN(tblClean[Week Start])+(A16-1)*7 -> 45880 | C16: =B16+6 -> 45886 | D16: =SUMIFS(tblClean[Attributed GMV PHP],tblClean[Week Start],$B16,tblClean[Include],1) -> 888080 | E16: =SUMIFS(tblClean[Items Sold],tblClean[Week Start],$B16,tblClean[Include],1) -> 2642 | F16: =COUNTIFS(tblClean[Week Start],$B16,tblClean[Include],1) -> 29 | G16: =SUMIFS(tblClean[Duration Hours],tblClean[Week Start],$B16,tblClean[Include],1) -> 66.5 | H16: =IF(G16>0,D16/G16,"n/a") -> 13354.586 | I16: =IF(ISNUMBER(D15),D16-D15,"n/a") -> -150388 | J16: =IF(ISNUMBER(D15),IF(D15>0,(D16-D15)/D15,"n/a"),"n/a") -> -0.14481717
A17: 12 | B17: =MIN(tblClean[Week Start])+(A17-1)*7 -> 45887 | C17: =B17+6 -> 45893 | D17: =SUMIFS(tblClean[Attributed GMV PHP],tblClean[Week Start],$B17,tblClean[Include],1) -> 906631 | E17: =SUMIFS(tblClean[Items Sold],tblClean[Week Start],$B17,tblClean[Include],1) -> 2598 | F17: =COUNTIFS(tblClean[Week Start],$B17,tblClean[Include],1) -> 31 | G17: =SUMIFS(tblClean[Duration Hours],tblClean[Week Start],$B17,tblClean[Include],1) -> 73 | H17: =IF(G17>0,D17/G17,"n/a") -> 12419.603 | I17: =IF(ISNUMBER(D16),D17-D16,"n/a") -> 18551 | J17: =IF(ISNUMBER(D16),IF(D16>0,(D17-D16)/D16,"n/a"),"n/a") -> 0.020888884
A18: 13 | B18: =MIN(tblClean[Week Start])+(A18-1)*7 -> 45894 | C18: =B18+6 -> 45900 | D18: =SUMIFS(tblClean[Attributed GMV PHP],tblClean[Week Start],$B18,tblClean[Include],1) -> 793006 | E18: =SUMIFS(tblClean[Items Sold],tblClean[Week Start],$B18,tblClean[Include],1) -> 2331 | F18: =COUNTIFS(tblClean[Week Start],$B18,tblClean[Include],1) -> 26 | G18: =SUMIFS(tblClean[Duration Hours],tblClean[Week Start],$B18,tblClean[Include],1) -> 58 | H18: =IF(G18>0,D18/G18,"n/a") -> 13672.517 | I18: =IF(ISNUMBER(D17),D18-D17,"n/a") -> -113625 | J18: =IF(ISNUMBER(D17),IF(D17>0,(D18-D17)/D17,"n/a"),"n/a") -> -0.12532662
A19: TOTAL | D19: =SUM(D6:D18) -> 11153095 | E19: =SUM(E6:E18) -> 33116 | F19: =SUM(F6:F18) -> 374 | G19: =SUM(G6:G18) -> 885.5 | H19: =IF(G19>0,D19/G19,0) -> 12595.251
A20: Raw Data total | D20: =SUM(tblRaw[Attributed GMV PHP]) -> 11153095 | E20: =SUM(tblRaw[Items Sold]) -> 33116 | F20: =ROWS(tblRaw[Session ID]) -> 374 | G20: =SUMPRODUCT(MOD(tblRaw[End Time]-tblRaw[Start Time],1))*24 -> 885.5
A21: Difference | D21: =D19-D20 -> 0 | E21: =E19-E20 -> 0 | F21: =F19-F20 -> 0 | G21: =ROUND(G19-G20,2) -> 0 | H21: =IF(AND(D21=0,E21=0,F21=0,G21=0),"✔ Reconciled","✖ Check") -> ✔ Reconciled
A23: Green row = highest-GMV week. Weekly GMV is volatile: promotions, paydays and a few unusually strong sessions can move a single week.

Sheet Host Performance
A1: HOST PERFORMANCE ANALYSIS
A2: Calculated from Cleaned Data. Synthetic hosts — portfolio demonstration.
A5: Host Name | B5: Sessions | C5: Livestream Hours | D5: Total GMV | E5: Items Sold | F5: Avg GMV per Session | G5: GMV per Hour | H5: Avg Items per Session | I5: % of Total GMV | J5: % of Total Hours | K5: Efficiency Index | L5: GMV per 1K Views | M5: Performance Rank (GMV per Hour) | N5: Total GMV Rank | O5: Profile
A6: ='Cleaned Data'!Z9 -> Aira Valdez | B6: =COUNTIFS(tblClean[Host Name],$A6,tblClean[Include],1) -> 49 | C6: =SUMIFS(tblClean[Duration Hours],tblClean[Host Name],$A6,tblClean[Include],1) -> 107 | D6: =SUMIFS(tblClean[Attributed GMV PHP],tblClean[Host Name],$A6,tblClean[Include],1) -> 2439929 | E6: =SUMIFS(tblClean[Items Sold],tblClean[Host Name],$A6,tblClean[Include],1) -> 7368 | F6: =IF(B6>0,D6/B6,0) -> 49794.469 | G6: =IF(C6>0,D6/C6,0) -> 22803.075 | H6: =IF(B6>0,E6/B6,0) -> 150.36735 | I6: =IF($D$11>0,D6/$D$11,0) -> 0.21876699 | J6: =IF($C$11>0,C6/$C$11,0) -> 0.12083569 | K6: =IF(J6>0,I6/J6,0) -> 1.8104502 | L6: =IFERROR(D6/SUMIFS(tblClean[Livestream Views],tblClean[Host Name],$A6,tblClean[Include],1)*1000,0) -> 292.89032 | M6: =RANK(G6,$G$6:$G$10,0)+COUNTIFS($G$6:$G$10,G6,$D$6:$D$10,">"&D6) -> 1 | N6: =RANK(D6,$D$6:$D$10,0) -> 3 | O6: =IF(AND(M6<=2,N6<=2),"Leader on both",IF(M6<=2,"Efficiency-led",IF(N6<=2,"Volume-led",IF(M6=MAX($M$6:$M$10),"Review: lowest efficiency","Mid-pack")))) -> Efficiency-led
A7: ='Cleaned Data'!Z10 -> Bianca Reyes | B7: =COUNTIFS(tblClean[Host Name],$A7,tblClean[Include],1) -> 146 | C7: =SUMIFS(tblClean[Duration Hours],tblClean[Host Name],$A7,tblClean[Include],1) -> 352 | D7: =SUMIFS(tblClean[Attributed GMV PHP],tblClean[Host Name],$A7,tblClean[Include],1) -> 3731707 | E7: =SUMIFS(tblClean[Items Sold],tblClean[Host Name],$A7,tblClean[Include],1) -> 11230 | F7: =IF(B7>0,D7/B7,0) -> 25559.637 | G7: =IF(C7>0,D7/C7,0) -> 10601.44 | H7: =IF(B7>0,E7/B7,0) -> 76.917808 | I7: =IF($D$11>0,D7/$D$11,0) -> 0.33458937 | J7: =IF($C$11>0,C7/$C$11,0) -> 0.39751553 | K7: =IF(J7>0,I7/J7,0) -> 0.84170138 | L7: =IFERROR(D7/SUMIFS(tblClean[Livestream Views],tblClean[Host Name],$A7,tblClean[Include],1)*1000,0) -> 292.85761 | M7: =RANK(G7,$G$6:$G$10,0)+COUNTIFS($G$6:$G$10,G7,$D$6:$D$10,">"&D7) -> 4 | N7: =RANK(D7,$D$6:$D$10,0) -> 1 | O7: =IF(AND(M7<=2,N7<=2),"Leader on both",IF(M7<=2,"Efficiency-led",IF(N7<=2,"Volume-led",IF(M7=MAX($M$6:$M$10),"Review: lowest efficiency","Mid-pack")))) -> Volume-led
A8: ='Cleaned Data'!Z11 -> Carlo Mendoza | B8: =COUNTIFS(tblClean[Host Name],$A8,tblClean[Include],1) -> 81 | C8: =SUMIFS(tblClean[Duration Hours],tblClean[Host Name],$A8,tblClean[Include],1) -> 190.5 | D8: =SUMIFS(tblClean[Attributed GMV PHP],tblClean[Host Name],$A8,tblClean[Include],1) -> 2674714 | E8: =SUMIFS(tblClean[Items Sold],tblClean[Host Name],$A8,tblClean[Include],1) -> 7850 | F8: =IF(B8>0,D8/B8,0) -> 33021.16 | G8: =IF(C8>0,D8/C8,0) -> 14040.493 | H8: =IF(B8>0,E8/B8,0) -> 96.91358 | I8: =IF($D$11>0,D8/$D$11,0) -> 0.2398181 | J8: =IF($C$11>0,C8/$C$11,0) -> 0.21513269 | K8: =IF(J8>0,I8/J8,0) -> 1.114745 | L8: =IFERROR(D8/SUMIFS(tblClean[Livestream Views],tblClean[Host Name],$A8,tblClean[Include],1)*1000,0) -> 283.57308 | M8: =RANK(G8,$G$6:$G$10,0)+COUNTIFS($G$6:$G$10,G8,$D$6:$D$10,">"&D8) -> 2 | N8: =RANK(D8,$D$6:$D$10,0) -> 2 | O8: =IF(AND(M8<=2,N8<=2),"Leader on both",IF(M8<=2,"Efficiency-led",IF(N8<=2,"Volume-led",IF(M8=MAX($M$6:$M$10),"Review: lowest efficiency","Mid-pack")))) -> Leader on both
A9: ='Cleaned Data'!Z12 -> Dani Villanueva | B9: =COUNTIFS(tblClean[Host Name],$A9,tblClean[Include],1) -> 67 | C9: =SUMIFS(tblClean[Duration Hours],tblClean[Host Name],$A9,tblClean[Include],1) -> 164 | D9: =SUMIFS(tblClean[Attributed GMV PHP],tblClean[Host Name],$A9,tblClean[Include],1) -> 1303370 | E9: =SUMIFS(tblClean[Items Sold],tblClean[Host Name],$A9,tblClean[Include],1) -> 3775 | F9: =IF(B9>0,D9/B9,0) -> 19453.284 | G9: =IF(C9>0,D9/C9,0) -> 7947.378 | H9: =IF(B9>0,E9/B9,0) -> 56.343284 | I9: =IF($D$11>0,D9/$D$11,0) -> 0.11686173 | J9: =IF($C$11>0,C9/$C$11,0) -> 0.1852061 | K9: =IF(J9>0,I9/J9,0) -> 0.6309821 | L9: =IFERROR(D9/SUMIFS(tblClean[Livestream Views],tblClean[Host Name],$A9,tblClean[Include],1)*1000,0) -> 272.62854 | M9: =RANK(G9,$G$6:$G$10,0)+COUNTIFS($G$6:$G$10,G9,$D$6:$D$10,">"&D9) -> 5 | N9: =RANK(D9,$D$6:$D$10,0) -> 4 | O9: =IF(AND(M9<=2,N9<=2),"Leader on both",IF(M9<=2,"Efficiency-led",IF(N9<=2,"Volume-led",IF(M9=MAX($M$6:$M$10),"Review: lowest efficiency","Mid-pack")))) -> Review: lowest efficiency
A10: ='Cleaned Data'!Z13 -> Elise Navarro | B10: =COUNTIFS(tblClean[Host Name],$A10,tblClean[Include],1) -> 31 | C10: =SUMIFS(tblClean[Duration Hours],tblClean[Host Name],$A10,tblClean[Include],1) -> 72 | D10: =SUMIFS(tblClean[Attributed GMV PHP],tblClean[Host Name],$A10,tblClean[Include],1) -> 1003375 | E10: =SUMIFS(tblClean[Items Sold],tblClean[Host Name],$A10,tblClean[Include],1) -> 2893 | F10: =IF(B10>0,D10/B10,0) -> 32366.935 | G10: =IF(C10>0,D10/C10,0) -> 13935.764 | H10: =IF(B10>0,E10/B10,0) -> 93.322581 | I10: =IF($D$11>0,D10/$D$11,0) -> 0.089963817 | J10: =IF($C$11>0,C10/$C$11,0) -> 0.081309994 | K10: =IF(J10>0,I10/J10,0) -> 1.10643 | L10: =IFERROR(D10/SUMIFS(tblClean[Livestream Views],tblClean[Host Name],$A10,tblClean[Include],1)*1000,0) -> 296.95631 | M10: =RANK(G10,$G$6:$G$10,0)+COUNTIFS($G$6:$G$10,G10,$D$6:$D$10,">"&D10) -> 3 | N10: =RANK(D10,$D$6:$D$10,0) -> 5 | O10: =IF(AND(M10<=2,N10<=2),"Leader on both",IF(M10<=2,"Efficiency-led",IF(N10<=2,"Volume-led",IF(M10=MAX($M$6:$M$10),"Review: lowest efficiency","Mid-pack")))) -> Mid-pack
A11: ALL HOSTS | B11: =SUM(B6:B10) -> 374 | C11: =SUM(C6:C10) -> 885.5 | D11: =SUM(D6:D10) -> 11153095 | E11: =SUM(E6:E10) -> 33116 | F11: =IF(B11>0,D11/B11,0) -> 29821.11 | G11: =IF(C11>0,D11/C11,0) -> 12595.251 | H11: =IF(B11>0,E11/B11,0) -> 88.545455 | I11: =SUM(I6:I10) -> 1 | J11: =SUM(J6:J10) -> 1 | L11: =IFERROR(D11/SUMIFS(tblClean[Livestream Views],tblClean[Include],1)*1000,0) -> 288.45664
A12: Raw Data total | B12: =ROWS(tblRaw[Session ID]) -> 374 | D12: =SUM(tblRaw[Attributed GMV PHP]) -> 11153095 | E12: =SUM(tblRaw[Items Sold]) -> 33116
A13: Difference | B13: =B11-B12 -> 0 | D13: =D11-D12 -> 0 | E13: =E11-E12 -> 0 | G13: =IF(AND(B13=0,D13=0,E13=0),"✔ Reconciled","✖ Check") -> ✔ Reconciled
A15: HOW HOSTS ARE RANKED
A16: Ranking rule: hosts are ranked by GMV per Hour (host total GMV ÷ host total livestream hours — a weighted rate, not an average of session rates). Ties would be broken by Total GMV. The Total GMV rank is shown beside it for scale.
A17: Why the two ranks can differ: Total GMV rewards time on air — a host who streams more hours can lead on volume without being the most productive per hour. GMV per Hour removes the effect of schedule length and shows selling efficiency.
A18: Efficiency Index = % of Total GMV ÷ % of Total Hours. Above 1.00 means the host produces a larger share of GMV than the share of airtime used; below 1.00 means the opposite.
A19: Interpret with care: time slot, day of week, product mix and promotion dates differ across sessions, so the table describes observed results and does not prove that one host is better. See the Host × Time Slot table below.
A22: GMV PER HOUR BY HOST AND TIME SLOT (PHP)
A23: Slot by session start: Morning 06–12h, Afternoon 12–16h, Early Evening 16–19h, Prime Time 19–22h, Late Night 22–06h. Blank = no sessions.
A24: Host Name | B24: Morning | C24: Afternoon | D24: Early Evening | E24: Prime Time | F24: Late Night | G24: All Slots
A25: =A6 -> Aira Valdez | B25: =IF(SUMIFS(tblClean[Duration Hours],tblClean[Host Name],$A25,tblClean[Time Slot],B$24,tblClean[Include],1)>0,SUMIFS(tblClean[Attributed GMV PHP],tblClean[Host Name],$A25,tblClean[Time Slot],B$24,tblClean[Include],1)/SUMIFS(tblClean[Duration Hours],tblClean[Host Name],$A25,tblClean[Time Slot],B$24,tblClean[Include],1),"") | C25: =IF(SUMIFS(tblClean[Duration Hours],tblClean[Host Name],$A25,tblClean[Time Slot],C$24,tblClean[Include],1)>0,SUMIFS(tblClean[Attributed GMV PHP],tblClean[Host Name],$A25,tblClean[Time Slot],C$24,tblClean[Include],1)/SUMIFS(tblClean[Duration Hours],tblClean[Host Name],$A25,tblClean[Time Slot],C$24,tblClean[Include],1),"") -> 15098.941 | D25: =IF(SUMIFS(tblClean[Duration Hours],tblClean[Host Name],$A25,tblClean[Time Slot],D$24,tblClean[Include],1)>0,SUMIFS(tblClean[Attributed GMV PHP],tblClean[Host Name],$A25,tblClean[Time Slot],D$24,tblClean[Include],1)/SUMIFS(tblClean[Duration Hours],tblClean[Host Name],$A25,tblClean[Time Slot],D$24,tblClean[Include],1),"") -> 18044.926 | E25: =IF(SUMIFS(tblClean[Duration Hours],tblClean[Host Name],$A25,tblClean[Time Slot],E$24,tblClean[Include],1)>0,SUMIFS(tblClean[Attributed GMV PHP],tblClean[Host Name],$A25,tblClean[Time Slot],E$24,tblClean[Include],1)/SUMIFS(tblClean[Duration Hours],tblClean[Host Name],$A25,tblClean[Time Slot],E$24,tblClean[Include],1),"") -> 26766.333 | F25: =IF(SUMIFS(tblClean[Duration Hours],tblClean[Host Name],$A25,tblClean[Time Slot],F$24,tblClean[Include],1)>0,SUMIFS(tblClean[Attributed GMV PHP],tblClean[Host Name],$A25,tblClean[Time Slot],F$24,tblClean[Include],1)/SUMIFS(tblClean[Duration Hours],tblClean[Host Name],$A25,tblClean[Time Slot],F$24,tblClean[Include],1),"") -> 18990.87 | G25: =G6 -> 22803.075
A26: =A7 -> Bianca Reyes | B26: =IF(SUMIFS(tblClean[Duration Hours],tblClean[Host Name],$A26,tblClean[Time Slot],B$24,tblClean[Include],1)>0,SUMIFS(tblClean[Attributed GMV PHP],tblClean[Host Name],$A26,tblClean[Time Slot],B$24,tblClean[Include],1)/SUMIFS(tblClean[Duration Hours],tblClean[Host Name],$A26,tblClean[Time Slot],B$24,tblClean[Include],1),"") -> 8789.6892 | C26: =IF(SUMIFS(tblClean[Duration Hours],tblClean[Host Name],$A26,tblClean[Time Slot],C$24,tblClean[Include],1)>0,SUMIFS(tblClean[Attributed GMV PHP],tblClean[Host Name],$A26,tblClean[Time Slot],C$24,tblClean[Include],1)/SUMIFS(tblClean[Duration Hours],tblClean[Host Name],$A26,tblClean[Time Slot],C$24,tblClean[Include],1),"") -> 8335.1504 | D26: =IF(SUMIFS(tblClean[Duration Hours],tblClean[Host Name],$A26,tblClean[Time Slot],D$24,tblClean[Include],1)>0,SUMIFS(tblClean[Attributed GMV PHP],tblClean[Host Name],$A26,tblClean[Time Slot],D$24,tblClean[Include],1)/SUMIFS(tblClean[Duration Hours],tblClean[Host Name],$A26,tblClean[Time Slot],D$24,tblClean[Include],1),"") -> 9613.2571 | E26: =IF(SUMIFS(tblClean[Duration Hours],tblClean[Host Name],$A26,tblClean[Time Slot],E$24,tblClean[Include],1)>0,SUMIFS(tblClean[Attributed GMV PHP],tblClean[Host Name],$A26,tblClean[Time Slot],E$24,tblClean[Include],1)/SUMIFS(tblClean[Duration Hours],tblClean[Host Name],$A26,tblClean[Time Slot],E$24,tblClean[Include],1),"") -> 14310.83 | F26: =IF(SUMIFS(tblClean[Duration Hours],tblClean[Host Name],$A26,tblClean[Time Slot],F$24,tblClean[Include],1)>0,SUMIFS(tblClean[Attributed GMV PHP],tblClean[Host Name],$A26,tblClean[Time Slot],F$24,tblClean[Include],1)/SUMIFS(tblClean[Duration Hours],tblClean[Host Name],$A26,tblClean[Time Slot],F$24,tblClean[Include],1),"") -> 10815.606 | G26: =G7 -> 10601.44
A27: =A8 -> Carlo Mendoza | B27: =IF(SUMIFS(tblClean[Duration Hours],tblClean[Host Name],$A27,tblClean[Time Slot],B$24,tblClean[Include],1)>0,SUMIFS(tblClean[Attributed GMV PHP],tblClean[Host Name],$A27,tblClean[Time Slot],B$24,tblClean[Include],1)/SUMIFS(tblClean[Duration Hours],tblClean[Host Name],$A27,tblClean[Time Slot],B$24,tblClean[Include],1),"") -> 8851.6111 | C27: =IF(SUMIFS(tblClean[Duration Hours],tblClean[Host Name],$A27,tblClean[Time Slot],C$24,tblClean[Include],1)>0,SUMIFS(tblClean[Attributed GMV PHP],tblClean[Host Name],$A27,tblClean[Time Slot],C$24,tblClean[Include],1)/SUMIFS(tblClean[Duration Hours],tblClean[Host Name],$A27,tblClean[Time Slot],C$24,tblClean[Include],1),"") -> 15669.594 | D27: =IF(SUMIFS(tblClean[Duration Hours],tblClean[Host Name],$A27,tblClean[Time Slot],D$24,tblClean[Include],1)>0,SUMIFS(tblClean[Attributed GMV PHP],tblClean[Host Name],$A27,tblClean[Time Slot],D$24,tblClean[Include],1)/SUMIFS(tblClean[Duration Hours],tblClean[Host Name],$A27,tblClean[Time Slot],D$24,tblClean[Include],1),"") -> 13533.35 | E27: =IF(SUMIFS(tblClean[Duration Hours],tblClean[Host Name],$A27,tblClean[Time Slot],E$24,tblClean[Include],1)>0,SUMIFS(tblClean[Attributed GMV PHP],tblClean[Host Name],$A27,tblClean[Time Slot],E$24,tblClean[Include],1)/SUMIFS(tblClean[Duration Hours],tblClean[Host Name],$A27,tblClean[Time Slot],E$24,tblClean[Include],1),"") -> 15666.091 | F27: =IF(SUMIFS(tblClean[Duration Hours],tblClean[Host Name],$A27,tblClean[Time Slot],F$24,tblClean[Include],1)>0,SUMIFS(tblClean[Attributed GMV PHP],tblClean[Host Name],$A27,tblClean[Time Slot],F$24,tblClean[Include],1)/SUMIFS(tblClean[Duration Hours],tblClean[Host Name],$A27,tblClean[Time Slot],F$24,tblClean[Include],1),"") -> 14045.178 | G27: =G8 -> 14040.493
A28: =A9 -> Dani Villanueva | B28: =IF(SUMIFS(tblClean[Duration Hours],tblClean[Host Name],$A28,tblClean[Time Slot],B$24,tblClean[Include],1)>0,SUMIFS(tblClean[Attributed GMV PHP],tblClean[Host Name],$A28,tblClean[Time Slot],B$24,tblClean[Include],1)/SUMIFS(tblClean[Duration Hours],tblClean[Host Name],$A28,tblClean[Time Slot],B$24,tblClean[Include],1),"") -> 4993.4757 | C28: =IF(SUMIFS(tblClean[Duration Hours],tblClean[Host Name],$A28,tblClean[Time Slot],C$24,tblClean[Include],1)>0,SUMIFS(tblClean[Attributed GMV PHP],tblClean[Host Name],$A28,tblClean[Time Slot],C$24,tblClean[Include],1)/SUMIFS(tblClean[Duration Hours],tblClean[Host Name],$A28,tblClean[Time Slot],C$24,tblClean[Include],1),"") -> 7377.6842 | D28: =IF(SUMIFS(tblClean[Duration Hours],tblClean[Host Name],$A28,tblClean[Time Slot],D$24,tblClean[Include],1)>0,SUMIFS(tblClean[Attributed GMV PHP],tblClean[Host Name],$A28,tblClean[Time Slot],D$24,tblClean[Include],1)/SUMIFS(tblClean[Duration Hours],tblClean[Host Name],$A28,tblClean[Time Slot],D$24,tblClean[Include],1),"") -> 10569.963 | E28: =IF(SUMIFS(tblClean[Duration Hours],tblClean[Host Name],$A28,tblClean[Time Slot],E$24,tblClean[Include],1)>0,SUMIFS(tblClean[Attributed GMV PHP],tblClean[Host Name],$A28,tblClean[Time Slot],E$24,tblClean[Include],1)/SUMIFS(tblClean[Duration Hours],tblClean[Host Name],$A28,tblClean[Time Slot],E$24,tblClean[Include],1),"") -> 12644.889 | F28: =IF(SUMIFS(tblClean[Duration Hours],tblClean[Host Name],$A28,tblClean[Time Slot],F$24,tblClean[Include],1)>0,SUMIFS(tblClean[Attributed GMV PHP],tblClean[Host Name],$A28,tblClean[Time Slot],F$24,tblClean[Include],1)/SUMIFS(tblClean[Duration Hours],tblClean[Host Name],$A28,tblClean[Time Slot],F$24,tblClean[Include],1),"") -> 10226.655 | G28: =G9 -> 7947.378
A29: =A10 -> Elise Navarro | B29: =IF(SUMIFS(tblClean[Duration Hours],tblClean[Host Name],$A29,tblClean[Time Slot],B$24,tblClean[Include],1)>0,SUMIFS(tblClean[Attributed GMV PHP],tblClean[Host Name],$A29,tblClean[Time Slot],B$24,tblClean[Include],1)/SUMIFS(tblClean[Duration Hours],tblClean[Host Name],$A29,tblClean[Time Slot],B$24,tblClean[Include],1),"") -> 5888.5714 | C29: =IF(SUMIFS(tblClean[Duration Hours],tblClean[Host Name],$A29,tblClean[Time Slot],C$24,tblClean[Include],1)>0,SUMIFS(tblClean[Attributed GMV PHP],tblClean[Host Name],$A29,tblClean[Time Slot],C$24,tblClean[Include],1)/SUMIFS(tblClean[Duration Hours],tblClean[Host Name],$A29,tblClean[Time Slot],C$24,tblClean[Include],1),"") -> 14138.533 | D29: =IF(SUMIFS(tblClean[Duration Hours],tblClean[Host Name],$A29,tblClean[Time Slot],D$24,tblClean[Include],1)>0,SUMIFS(tblClean[Attributed GMV PHP],tblClean[Host Name],$A29,tblClean[Time Slot],D$24,tblClean[Include],1)/SUMIFS(tblClean[Duration Hours],tblClean[Host Name],$A29,tblClean[Time Slot],D$24,tblClean[Include],1),"") -> 14398.098 | E29: =IF(SUMIFS(tblClean[Duration Hours],tblClean[Host Name],$A29,tblClean[Time Slot],E$24,tblClean[Include],1)>0,SUMIFS(tblClean[Attributed GMV PHP],tblClean[Host Name],$A29,tblClean[Time Slot],E$24,tblClean[Include],1)/SUMIFS(tblClean[Duration Hours],tblClean[Host Name],$A29,tblClean[Time Slot],E$24,tblClean[Include],1),"") -> 20710.833 | F29: =IF(SUMIFS(tblClean[Duration Hours],tblClean[Host Name],$A29,tblClean[Time Slot],F$24,tblClean[Include],1)>0,SUMIFS(tblClean[Attributed GMV PHP],tblClean[Host Name],$A29,tblClean[Time Slot],F$24,tblClean[Include],1)/SUMIFS(tblClean[Duration Hours],tblClean[Host Name],$A29,tblClean[Time Slot],F$24,tblClean[Include],1),"") -> 13949.765 | G29: =G10 -> 13935.764
A30: All hosts | B30: =IF(SUMIFS(tblClean[Duration Hours],tblClean[Time Slot],B$24,tblClean[Include],1)>0,SUMIFS(tblClean[Attributed GMV PHP],tblClean[Time Slot],B$24,tblClean[Include],1)/SUMIFS(tblClean[Duration Hours],tblClean[Time Slot],B$24,tblClean[Include],1),"") -> 7363.1229 | C30: =IF(SUMIFS(tblClean[Duration Hours],tblClean[Time Slot],C$24,tblClean[Include],1)>0,SUMIFS(tblClean[Attributed GMV PHP],tblClean[Time Slot],C$24,tblClean[Include],1)/SUMIFS(tblClean[Duration Hours],tblClean[Time Slot],C$24,tblClean[Include],1),"") -> 10746.705 | D30: =IF(SUMIFS(tblClean[Duration Hours],tblClean[Time Slot],D$24,tblClean[Include],1)>0,SUMIFS(tblClean[Attributed GMV PHP],tblClean[Time Slot],D$24,tblClean[Include],1)/SUMIFS(tblClean[Duration Hours],tblClean[Time Slot],D$24,tblClean[Include],1),"") -> 12482.601 | E30: =IF(SUMIFS(tblClean[Duration Hours],tblClean[Time Slot],E$24,tblClean[Include],1)>0,SUMIFS(tblClean[Attributed GMV PHP],tblClean[Time Slot],E$24,tblClean[Include],1)/SUMIFS(tblClean[Duration Hours],tblClean[Time Slot],E$24,tblClean[Include],1),"") -> 18371.311 | F30: =IF(SUMIFS(tblClean[Duration Hours],tblClean[Time Slot],F$24,tblClean[Include],1)>0,SUMIFS(tblClean[Attributed GMV PHP],tblClean[Time Slot],F$24,tblClean[Include],1)/SUMIFS(tblClean[Duration Hours],tblClean[Time Slot],F$24,tblClean[Include],1),"") -> 12277.36 | G30: =G11 -> 12595.251
A33: WEEKLY GMV BY HOST (PHP)
A34: Heat-map view of consistency across the 13 reporting weeks. Row totals reconcile to the Weekly Summary.
A35: Week Start | B35: =A6 -> Aira Valdez | C35: =A7 -> Bianca Reyes | D35: =A8 -> Carlo Mendoza | E35: =A9 -> Dani Villanueva | F35: =A10 -> Elise Navarro | G35: All Hosts
A36: ='Weekly Summary'!B6 -> 45810 | B36: =SUMIFS(tblClean[Attributed GMV PHP],tblClean[Week Start],$A36,tblClean[Host Name],B$35,tblClean[Include],1) -> 285967 | C36: =SUMIFS(tblClean[Attributed GMV PHP],tblClean[Week Start],$A36,tblClean[Host Name],C$35,tblClean[Include],1) -> 142391 | D36: =SUMIFS(tblClean[Attributed GMV PHP],tblClean[Week Start],$A36,tblClean[Host Name],D$35,tblClean[Include],1) -> 255803 | E36: =SUMIFS(tblClean[Attributed GMV PHP],tblClean[Week Start],$A36,tblClean[Host Name],E$35,tblClean[Include],1) -> 84142 | F36: =SUMIFS(tblClean[Attributed GMV PHP],tblClean[Week Start],$A36,tblClean[Host Name],F$35,tblClean[Include],1) -> 0 | G36: =SUM(B36:F36) -> 768303
A37: ='Weekly Summary'!B7 -> 45817 | B37: =SUMIFS(tblClean[Attributed GMV PHP],tblClean[Week Start],$A37,tblClean[Host Name],B$35,tblClean[Include],1) -> 129715 | C37: =SUMIFS(tblClean[Attributed GMV PHP],tblClean[Week Start],$A37,tblClean[Host Name],C$35,tblClean[Include],1) -> 368927 | D37: =SUMIFS(tblClean[Attributed GMV PHP],tblClean[Week Start],$A37,tblClean[Host Name],D$35,tblClean[Include],1) -> 125577 | E37: =SUMIFS(tblClean[Attributed GMV PHP],tblClean[Week Start],$A37,tblClean[Host Name],E$35,tblClean[Include],1) -> 74522 | F37: =SUMIFS(tblClean[Attributed GMV PHP],tblClean[Week Start],$A37,tblClean[Host Name],F$35,tblClean[Include],1) -> 0 | G37: =SUM(B37:F37) -> 698741
A38: ='Weekly Summary'!B8 -> 45824 | B38: =SUMIFS(tblClean[Attributed GMV PHP],tblClean[Week Start],$A38,tblClean[Host Name],B$35,tblClean[Include],1) -> 167973 | C38: =SUMIFS(tblClean[Attributed GMV PHP],tblClean[Week Start],$A38,tblClean[Host Name],C$35,tblClean[Include],1) -> 318878 | D38: =SUMIFS(tblClean[Attributed GMV PHP],tblClean[Week Start],$A38,tblClean[Host Name],D$35,tblClean[Include],1) -> 140201 | E38: =SUMIFS(tblClean[Attributed GMV PHP],tblClean[Week Start],$A38,tblClean[Host Name],E$35,tblClean[Include],1) -> 42662 | F38: =SUMIFS(tblClean[Attributed GMV PHP],tblClean[Week Start],$A38,tblClean[Host Name],F$35,tblClean[Include],1) -> 9000 | G38: =SUM(B38:F38) -> 678714
A39: ='Weekly Summary'!B9 -> 45831 | B39: =SUMIFS(tblClean[Attributed GMV PHP],tblClean[Week Start],$A39,tblClean[Host Name],B$35,tblClean[Include],1) -> 129011 | C39: =SUMIFS(tblClean[Attributed GMV PHP],tblClean[Week Start],$A39,tblClean[Host Name],C$35,tblClean[Include],1) -> 317190 | D39: =SUMIFS(tblClean[Attributed GMV PHP],tblClean[Week Start],$A39,tblClean[Host Name],D$35,tblClean[Include],1) -> 155662 | E39: =SUMIFS(tblClean[Attributed GMV PHP],tblClean[Week Start],$A39,tblClean[Host Name],E$35,tblClean[Include],1) -> 83551 | F39: =SUMIFS(tblClean[Attributed GMV PHP],tblClean[Week Start],$A39,tblClean[Host Name],F$35,tblClean[Include],1) -> 60883 | G39: =SUM(B39:F39) -> 746297
A40: ='Weekly Summary'!B10 -> 45838 | B40: =SUMIFS(tblClean[Attributed GMV PHP],tblClean[Week Start],$A40,tblClean[Host Name],B$35,tblClean[Include],1) -> 415469 | C40: =SUMIFS(tblClean[Attributed GMV PHP],tblClean[Week Start],$A40,tblClean[Host Name],C$35,tblClean[Include],1) -> 243167 | D40: =SUMIFS(tblClean[Attributed GMV PHP],tblClean[Week Start],$A40,tblClean[Host Name],D$35,tblClean[Include],1) -> 183347 | E40: =SUMIFS(tblClean[Attributed GMV PHP],tblClean[Week Start],$A40,tblClean[Host Name],E$35,tblClean[Include],1) -> 66167 | F40: =SUMIFS(tblClean[Attributed GMV PHP],tblClean[Week Start],$A40,tblClean[Host Name],F$35,tblClean[Include],1) -> 0 | G40: =SUM(B40:F40) -> 908150
A41: ='Weekly Summary'!B11 -> 45845 | B41: =SUMIFS(tblClean[Attributed GMV PHP],tblClean[Week Start],$A41,tblClean[Host Name],B$35,tblClean[Include],1) -> 317849 | C41: =SUMIFS(tblClean[Attributed GMV PHP],tblClean[Week Start],$A41,tblClean[Host Name],C$35,tblClean[Include],1) -> 132802 | D41: =SUMIFS(tblClean[Attributed GMV PHP],tblClean[Week Start],$A41,tblClean[Host Name],D$35,tblClean[Include],1) -> 422404 | E41: =SUMIFS(tblClean[Attributed GMV PHP],tblClean[Week Start],$A41,tblClean[Host Name],E$35,tblClean[Include],1) -> 47500 | F41: =SUMIFS(tblClean[Attributed GMV PHP],tblClean[Week Start],$A41,tblClean[Host Name],F$35,tblClean[Include],1) -> 0 | G41: =SUM(B41:F41) -> 920555
A42: ='Weekly Summary'!B12 -> 45852 | B42: =SUMIFS(tblClean[Attributed GMV PHP],tblClean[Week Start],$A42,tblClean[Host Name],B$35,tblClean[Include],1) -> 254381 | C42: =SUMIFS(tblClean[Attributed GMV PHP],tblClean[Week Start],$A42,tblClean[Host Name],C$35,tblClean[Include],1) -> 179005 | D42: =SUMIFS(tblClean[Attributed GMV PHP],tblClean[Week Start],$A42,tblClean[Host Name],D$35,tblClean[Include],1) -> 139306 | E42: =SUMIFS(tblClean[Attributed GMV PHP],tblClean[Week Start],$A42,tblClean[Host Name],E$35,tblClean[Include],1) -> 218778 | F42: =SUMIFS(tblClean[Attributed GMV PHP],tblClean[Week Start],$A42,tblClean[Host Name],F$35,tblClean[Include],1) -> 53601 | G42: =SUM(B42:F42) -> 845071
A43: ='Weekly Summary'!B13 -> 45859 | B43: =SUMIFS(tblClean[Attributed GMV PHP],tblClean[Week Start],$A43,tblClean[Host Name],B$35,tblClean[Include],1) -> 25121 | C43: =SUMIFS(tblClean[Attributed GMV PHP],tblClean[Week Start],$A43,tblClean[Host Name],C$35,tblClean[Include],1) -> 326173 | D43: =SUMIFS(tblClean[Attributed GMV PHP],tblClean[Week Start],$A43,tblClean[Host Name],D$35,tblClean[Include],1) -> 246759 | E43: =SUMIFS(tblClean[Attributed GMV PHP],tblClean[Week Start],$A43,tblClean[Host Name],E$35,tblClean[Include],1) -> 102756 | F43: =SUMIFS(tblClean[Attributed GMV PHP],tblClean[Week Start],$A43,tblClean[Host Name],F$35,tblClean[Include],1) -> 90009 | G43: =SUM(B43:F43) -> 790818
A44: ='Weekly Summary'!B14 -> 45866 | B44: =SUMIFS(tblClean[Attributed GMV PHP],tblClean[Week Start],$A44,tblClean[Host Name],B$35,tblClean[Include],1) -> 345947 | C44: =SUMIFS(tblClean[Attributed GMV PHP],tblClean[Week Start],$A44,tblClean[Host Name],C$35,tblClean[Include],1) -> 461326 | D44: =SUMIFS(tblClean[Attributed GMV PHP],tblClean[Week Start],$A44,tblClean[Host Name],D$35,tblClean[Include],1) -> 240729 | E44: =SUMIFS(tblClean[Attributed GMV PHP],tblClean[Week Start],$A44,tblClean[Host Name],E$35,tblClean[Include],1) -> 88382 | F44: =SUMIFS(tblClean[Attributed GMV PHP],tblClean[Week Start],$A44,tblClean[Host Name],F$35,tblClean[Include],1) -> 33877 | G44: =SUM(B44:F44) -> 1170261
A45: ='Weekly Summary'!B15 -> 45873 | B45: =SUMIFS(tblClean[Attributed GMV PHP],tblClean[Week Start],$A45,tblClean[Host Name],B$35,tblClean[Include],1) -> 68370 | C45: =SUMIFS(tblClean[Attributed GMV PHP],tblClean[Week Start],$A45,tblClean[Host Name],C$35,tblClean[Include],1) -> 311062 | D45: =SUMIFS(tblClean[Attributed GMV PHP],tblClean[Week Start],$A45,tblClean[Host Name],D$35,tblClean[Include],1) -> 268851 | E45: =SUMIFS(tblClean[Attributed GMV PHP],tblClean[Week Start],$A45,tblClean[Host Name],E$35,tblClean[Include],1) -> 297431 | F45: =SUMIFS(tblClean[Attributed GMV PHP],tblClean[Week Start],$A45,tblClean[Host Name],F$35,tblClean[Include],1) -> 92754 | G45: =SUM(B45:F45) -> 1038468
A46: ='Weekly Summary'!B16 -> 45880 | B46: =SUMIFS(tblClean[Attributed GMV PHP],tblClean[Week Start],$A46,tblClean[Host Name],B$35,tblClean[Include],1) -> 75770 | C46: =SUMIFS(tblClean[Attributed GMV PHP],tblClean[Week Start],$A46,tblClean[Host Name],C$35,tblClean[Include],1) -> 471798 | D46: =SUMIFS(tblClean[Attributed GMV PHP],tblClean[Week Start],$A46,tblClean[Host Name],D$35,tblClean[Include],1) -> 119843 | E46: =SUMIFS(tblClean[Attributed GMV PHP],tblClean[Week Start],$A46,tblClean[Host Name],E$35,tblClean[Include],1) -> 46557 | F46: =SUMIFS(tblClean[Attributed GMV PHP],tblClean[Week Start],$A46,tblClean[Host Name],F$35,tblClean[Include],1) -> 174112 | G46: =SUM(B46:F46) -> 888080
A47: ='Weekly Summary'!B17 -> 45887 | B47: =SUMIFS(tblClean[Attributed GMV PHP],tblClean[Week Start],$A47,tblClean[Host Name],B$35,tblClean[Include],1) -> 80934 | C47: =SUMIFS(tblClean[Attributed GMV PHP],tblClean[Week Start],$A47,tblClean[Host Name],C$35,tblClean[Include],1) -> 229120 | D47: =SUMIFS(tblClean[Attributed GMV PHP],tblClean[Week Start],$A47,tblClean[Host Name],D$35,tblClean[Include],1) -> 221146 | E47: =SUMIFS(tblClean[Attributed GMV PHP],tblClean[Week Start],$A47,tblClean[Host Name],E$35,tblClean[Include],1) -> 71283 | F47: =SUMIFS(tblClean[Attributed GMV PHP],tblClean[Week Start],$A47,tblClean[Host Name],F$35,tblClean[Include],1) -> 304148 | G47: =SUM(B47:F47) -> 906631
A48: ='Weekly Summary'!B18 -> 45894 | B48: =SUMIFS(tblClean[Attributed GMV PHP],tblClean[Week Start],$A48,tblClean[Host Name],B$35,tblClean[Include],1) -> 143422 | C48: =SUMIFS(tblClean[Attributed GMV PHP],tblClean[Week Start],$A48,tblClean[Host Name],C$35,tblClean[Include],1) -> 229868 | D48: =SUMIFS(tblClean[Attributed GMV PHP],tblClean[Week Start],$A48,tblClean[Host Name],D$35,tblClean[Include],1) -> 155086 | E48: =SUMIFS(tblClean[Attributed GMV PHP],tblClean[Week Start],$A48,tblClean[Host Name],E$35,tblClean[Include],1) -> 79639 | F48: =SUMIFS(tblClean[Attributed GMV PHP],tblClean[Week Start],$A48,tblClean[Host Name],F$35,tblClean[Include],1) -> 184991 | G48: =SUM(B48:F48) -> 793006
A49: TOTAL | B49: =SUM(B36:B48) -> 2439929 | C49: =SUM(C36:C48) -> 3731707 | D49: =SUM(D36:D48) -> 2674714 | E49: =SUM(E36:E48) -> 1303370 | F49: =SUM(F36:F48) -> 1003375 | G49: =SUM(G36:G48) -> 11153095
A50: Check vs summary | G50: =G49-D11 -> 0 | H50: =IF(G50=0,"✔ Reconciled","✖ Check") -> ✔ Reconciled

Sheet Dashboard
B1: LIVE COMMERCE SALES PERFORMANCE ANALYSIS
B2: Excel-Based GMV Tracking, Host Performance Reporting, and Sales Analytics | Sample Live Commerce Store (fictional)
B3: Reporting period: 02 Jun 2025 – 31 Aug 2025 | Currency: Philippine peso (PHP) | GMV = gross merchandise value, not net revenue or profit
R4: CHART DATA — helper ranges (formula-driven, do not edit). NA() placeholders mark days/weeks outside the selected filters (intentionally skipped by the charts). | AD4: Host criterion: | AE4: =IF(F6="All Hosts","*",F6) -> *
B5: FROM DATE | D5: TO DATE | F5: HOST | I5: ◄ Change the yellow filter cells. KPI cards, the daily trend and the weekly trend respond to date range and host. Host charts always show every host for the selected dates so hosts can be compared.
B6: 45810 | D6: 45900 | F6: All Hosts | R6: Date | S6: Daily GMV | T6: 7-Day Avg GMV | V6: Week Start | W6: Weekly GMV | Y6: Host | Z6: GMV | AA6: Items | AB6: Hours | AC6: GMV per Hour | AE6: Host list
R7: =MIN(tblClean[Date]) -> 45810 | S7: =IF(AND(R7>=dFrom,R7<=dTo),SUMIFS(tblClean[Attributed GMV PHP],tblClean[Date],R7,tblClean[Host Name],dHost,tblClean[Include],1),NA()) -> 85426 | T7: =IF(AND(R7>=dFrom,R7<=dTo),SUMIFS(tblClean[Attributed GMV PHP],tblClean[Date],">="&MAX(R7-6,dFrom),tblClean[Date],"<="&R7,tblClean[Host Name],dHost,tblClean[Include],1)/(R7-MAX(R7-6,dFrom)+1),NA()) -> 85426 | V7: ='Weekly Summary'!B6 -> 45810 | W7: =IF(AND(V7+6>=dFrom,V7<=dTo),SUMIFS(tblClean[Attributed GMV PHP],tblClean[Date],">="&MAX(V7,dFrom),tblClean[Date],"<="&MIN(V7+6,dTo),tblClean[Host Name],dHost,tblClean[Include],1),NA()) -> 768303 | Y7: ='Cleaned Data'!Z9 -> Aira Valdez | Z7: =SUMIFS(tblClean[Attributed GMV PHP],tblClean[Host Name],Y7,tblClean[Date],">="&dFrom,tblClean[Date],"<="&dTo,tblClean[Include],1) -> 2439929 | AA7: =SUMIFS(tblClean[Items Sold],tblClean[Host Name],Y7,tblClean[Date],">="&dFrom,tblClean[Date],"<="&dTo,tblClean[Include],1) -> 7368 | AB7: =SUMIFS(tblClean[Duration Hours],tblClean[Host Name],Y7,tblClean[Date],">="&dFrom,tblClean[Date],"<="&dTo,tblClean[Include],1) -> 107 | AC7: =IF(AB7>0,Z7/AB7,0) -> 22803.075 | AE7: All Hosts
B8: TOTAL GMV | D8: TOTAL ITEMS SOLD | F8: LIVESTREAM SESSIONS | H8: LIVESTREAM HOURS | J8: AVG GMV PER HOUR | L8: TOP HOST BY TOTAL GMV | R8: =R7+1 -> 45811 | S8: =IF(AND(R8>=dFrom,R8<=dTo),SUMIFS(tblClean[Attributed GMV PHP],tblClean[Date],R8,tblClean[Host Name],dHost,tblClean[Include],1),NA()) -> 177219 | T8: =IF(AND(R8>=dFrom,R8<=dTo),SUMIFS(tblClean[Attributed GMV PHP],tblClean[Date],">="&MAX(R8-6,dFrom),tblClean[Date],"<="&R8,tblClean[Host Name],dHost,tblClean[Include],1)/(R8-MAX(R8-6,dFrom)+1),NA()) -> 131322.5 | V8: ='Weekly Summary'!B7 -> 45817 | W8: =IF(AND(V8+6>=dFrom,V8<=dTo),SUMIFS(tblClean[Attributed GMV PHP],tblClean[Date],">="&MAX(V8,dFrom),tblClean[Date],"<="&MIN(V8+6,dTo),tblClean[Host Name],dHost,tblClean[Include],1),NA()) -> 698741 | Y8: ='Cleaned Data'!Z10 -> Bianca Reyes | Z8: =SUMIFS(tblClean[Attributed GMV PHP],tblClean[Host Name],Y8,tblClean[Date],">="&dFrom,tblClean[Date],"<="&dTo,tblClean[Include],1) -> 3731707 | AA8: =SUMIFS(tblClean[Items Sold],tblClean[Host Name],Y8,tblClean[Date],">="&dFrom,tblClean[Date],"<="&dTo,tblClean[Include],1) -> 11230 | AB8: =SUMIFS(tblClean[Duration Hours],tblClean[Host Name],Y8,tblClean[Date],">="&dFrom,tblClean[Date],"<="&dTo,tblClean[Include],1) -> 352 | AC8: =IF(AB8>0,Z8/AB8,0) -> 10601.44 | AE8: =Y7 -> Aira Valdez
B9: =SUMIFS(tblClean[Attributed GMV PHP],tblClean[Date],">="&dFrom,tblClean[Date],"<="&dTo,tblClean[Host Name],dHost,tblClean[Include],1) -> 11153095 | D9: =SUMIFS(tblClean[Items Sold],tblClean[Date],">="&dFrom,tblClean[Date],"<="&dTo,tblClean[Host Name],dHost,tblClean[Include],1) -> 33116 | F9: =COUNTIFS(tblClean[Date],">="&dFrom,tblClean[Date],"<="&dTo,tblClean[Host Name],dHost,tblClean[Include],1) -> 374 | H9: =SUMIFS(tblClean[Duration Hours],tblClean[Date],">="&dFrom,tblClean[Date],"<="&dTo,tblClean[Host Name],dHost,tblClean[Include],1) -> 885.5 | J9: =IF(H9>0,B9/H9,0) -> 12595.251 | L9: =IF(SUM(Z7:Z11)=0,"—",IF(F6="All Hosts",INDEX(Y7:Y11,MATCH(MAX(Z7:Z11),Z7:Z11,0)),F6)) -> Bianca Reyes | R9: =R8+1 -> 45812 | S9: =IF(AND(R9>=dFrom,R9<=dTo),SUMIFS(tblClean[Attributed GMV PHP],tblClean[Date],R9,tblClean[Host Name],dHost,tblClean[Include],1),NA()) -> 59562 | T9: =IF(AND(R9>=dFrom,R9<=dTo),SUMIFS(tblClean[Attributed GMV PHP],tblClean[Date],">="&MAX(R9-6,dFrom),tblClean[Date],"<="&R9,tblClean[Host Name],dHost,tblClean[Include],1)/(R9-MAX(R9-6,dFrom)+1),NA()) -> 107402.33 | V9: ='Weekly Summary'!B8 -> 45824 | W9: =IF(AND(V9+6>=dFrom,V9<=dTo),SUMIFS(tblClean[Attributed GMV PHP],tblClean[Date],">="&MAX(V9,dFrom),tblClean[Date],"<="&MIN(V9+6,dTo),tblClean[Host Name],dHost,tblClean[Include],1),NA()) -> 678714 | Y9: ='Cleaned Data'!Z11 -> Carlo Mendoza | Z9: =SUMIFS(tblClean[Attributed GMV PHP],tblClean[Host Name],Y9,tblClean[Date],">="&dFrom,tblClean[Date],"<="&dTo,tblClean[Include],1) -> 2674714 | AA9: =SUMIFS(tblClean[Items Sold],tblClean[Host Name],Y9,tblClean[Date],">="&dFrom,tblClean[Date],"<="&dTo,tblClean[Include],1) -> 7850 | AB9: =SUMIFS(tblClean[Duration Hours],tblClean[Host Name],Y9,tblClean[Date],">="&dFrom,tblClean[Date],"<="&dTo,tblClean[Include],1) -> 190.5 | AC9: =IF(AB9>0,Z9/AB9,0) -> 14040.493 | AE9: =Y8 -> Bianca Reyes
B10: ="Avg ₱"&TEXT(IF(F9>0,B9/F9,0),"#,##0")&" per session" -> Avg ₱29,821 per session | D10: ="Avg "&TEXT(IF(F9>0,D9/F9,0),"0.0")&" items per session" -> Avg 88.5 items per session | F10: =TEXT(IF(dTo>=dFrom,F9/(dTo-dFrom+1),0),"0.0")&" sessions per day" -> 4.1 sessions per day | H10: ="Avg "&TEXT(IF(F9>0,H9/F9,0),"0.0")&" hrs per session" -> Avg 2.4 hrs per session | J10: Total GMV ÷ total hours (weighted) | L10: =IFERROR("₱"&TEXT(INDEX(Z7:Z11,MATCH(L9,Y7:Y11,0)),"#,##0")&" ("&TEXT(INDEX(Z7:Z11,MATCH(L9,Y7:Y11,0))/SUM(Z7:Z11),"0.0%")&" of period GMV)","") -> ₱3,731,707 (33.5% of period GMV) | R10: =R9+1 -> 45813 | S10: =IF(AND(R10>=dFrom,R10<=dTo),SUMIFS(tblClean[Attributed GMV PHP],tblClean[Date],R10,tblClean[Host Name],dHost,tblClean[Include],1),NA()) -> 84165 | T10: =IF(AND(R10>=dFrom,R10<=dTo),SUMIFS(tblClean[Attributed GMV PHP],tblClean[Date],">="&MAX(R10-6,dFrom),tblClean[Date],"<="&R10,tblClean[Host Name],dHost,tblClean[Include],1)/(R10-MAX(R10-6,dFrom)+1),NA()) -> 101593 | V10: ='Weekly Summary'!B9 -> 45831 | W10: =IF(AND(V10+6>=dFrom,V10<=dTo),SUMIFS(tblClean[Attributed GMV PHP],tblClean[Date],">="&MAX(V10,dFrom),tblClean[Date],"<="&MIN(V10+6,dTo),tblClean[Host Name],dHost,tblClean[Include],1),NA()) -> 746297 | Y10: ='Cleaned Data'!Z12 -> Dani Villanueva | Z10: =SUMIFS(tblClean[Attributed GMV PHP],tblClean[Host Name],Y10,tblClean[Date],">="&dFrom,tblClean[Date],"<="&dTo,tblClean[Include],1) -> 1303370 | AA10: =SUMIFS(tblClean[Items Sold],tblClean[Host Name],Y10,tblClean[Date],">="&dFrom,tblClean[Date],"<="&dTo,tblClean[Include],1) -> 3775 | AB10: =SUMIFS(tblClean[Duration Hours],tblClean[Host Name],Y10,tblClean[Date],">="&dFrom,tblClean[Date],"<="&dTo,tblClean[Include],1) -> 164 | AC10: =IF(AB10>0,Z10/AB10,0) -> 7947.378 | AE10: =Y9 -> Carlo Mendoza
R11: =R10+1 -> 45814 | S11: =IF(AND(R11>=dFrom,R11<=dTo),SUMIFS(tblClean[Attributed GMV PHP],tblClean[Date],R11,tblClean[Host Name],dHost,tblClean[Include],1),NA()) -> 176989 | T11: =IF(AND(R11>=dFrom,R11<=dTo),SUMIFS(tblClean[Attributed GMV PHP],tblClean[Date],">="&MAX(R11-6,dFrom),tblClean[Date],"<="&R11,tblClean[Host Name],dHost,tblClean[Include],1)/(R11-MAX(R11-6,dFrom)+1),NA()) -> 116672.2 | V11: ='Weekly Summary'!B10 -> 45838 | W11: =IF(AND(V11+6>=dFrom,V11<=dTo),SUMIFS(tblClean[Attributed GMV PHP],tblClean[Date],">="&MAX(V11,dFrom),tblClean[Date],"<="&MIN(V11+6,dTo),tblClean[Host Name],dHost,tblClean[Include],1),NA()) -> 908150 | Y11: ='Cleaned Data'!Z13 -> Elise Navarro | Z11: =SUMIFS(tblClean[Attributed GMV PHP],tblClean[Host Name],Y11,tblClean[Date],">="&dFrom,tblClean[Date],"<="&dTo,tblClean[Include],1) -> 1003375 | AA11: =SUMIFS(tblClean[Items Sold],tblClean[Host Name],Y11,tblClean[Date],">="&dFrom,tblClean[Date],"<="&dTo,tblClean[Include],1) -> 2893 | AB11: =SUMIFS(tblClean[Duration Hours],tblClean[Host Name],Y11,tblClean[Date],">="&dFrom,tblClean[Date],"<="&dTo,tblClean[Include],1) -> 72 | AC11: =IF(AB11>0,Z11/AB11,0) -> 13935.764 | AE11: =Y10 -> Dani Villanueva
R12: =R11+1 -> 45815 | S12: =IF(AND(R12>=dFrom,R12<=dTo),SUMIFS(tblClean[Attributed GMV PHP],tblClean[Date],R12,tblClean[Host Name],dHost,tblClean[Include],1),NA()) -> 116380 | T12: =IF(AND(R12>=dFrom,R12<=dTo),SUMIFS(tblClean[Attributed GMV PHP],tblClean[Date],">="&MAX(R12-6,dFrom),tblClean[Date],"<="&R12,tblClean[Host Name],dHost,tblClean[Include],1)/(R12-MAX(R12-6,dFrom)+1),NA()) -> 116623.5 | V12: ='Weekly Summary'!B11 -> 45845 | W12: =IF(AND(V12+6>=dFrom,V12<=dTo),SUMIFS(tblClean[Attributed GMV PHP],tblClean[Date],">="&MAX(V12,dFrom),tblClean[Date],"<="&MIN(V12+6,dTo),tblClean[Host Name],dHost,tblClean[Include],1),NA()) -> 920555 | AE12: =Y11 -> Elise Navarro
R13: =R12+1 -> 45816 | S13: =IF(AND(R13>=dFrom,R13<=dTo),SUMIFS(tblClean[Attributed GMV PHP],tblClean[Date],R13,tblClean[Host Name],dHost,tblClean[Include],1),NA()) -> 68562 | T13: =IF(AND(R13>=dFrom,R13<=dTo),SUMIFS(tblClean[Attributed GMV PHP],tblClean[Date],">="&MAX(R13-6,dFrom),tblClean[Date],"<="&R13,tblClean[Host Name],dHost,tblClean[Include],1)/(R13-MAX(R13-6,dFrom)+1),NA()) -> 109757.57 | V13: ='Weekly Summary'!B12 -> 45852 | W13: =IF(AND(V13+6>=dFrom,V13<=dTo),SUMIFS(tblClean[Attributed GMV PHP],tblClean[Date],">="&MAX(V13,dFrom),tblClean[Date],"<="&MIN(V13+6,dTo),tblClean[Host Name],dHost,tblClean[Include],1),NA()) -> 845071
R14: =R13+1 -> 45817 | S14: =IF(AND(R14>=dFrom,R14<=dTo),SUMIFS(tblClean[Attributed GMV PHP],tblClean[Date],R14,tblClean[Host Name],dHost,tblClean[Include],1),NA()) -> 92331 | T14: =IF(AND(R14>=dFrom,R14<=dTo),SUMIFS(tblClean[Attributed GMV PHP],tblClean[Date],">="&MAX(R14-6,dFrom),tblClean[Date],"<="&R14,tblClean[Host Name],dHost,tblClean[Include],1)/(R14-MAX(R14-6,dFrom)+1),NA()) -> 110744 | V14: ='Weekly Summary'!B13 -> 45859 | W14: =IF(AND(V14+6>=dFrom,V14<=dTo),SUMIFS(tblClean[Attributed GMV PHP],tblClean[Date],">="&MAX(V14,dFrom),tblClean[Date],"<="&MIN(V14+6,dTo),tblClean[Host Name],dHost,tblClean[Include],1),NA()) -> 790818
R15: =R14+1 -> 45818 | S15: =IF(AND(R15>=dFrom,R15<=dTo),SUMIFS(tblClean[Attributed GMV PHP],tblClean[Date],R15,tblClean[Host Name],dHost,tblClean[Include],1),NA()) -> 111327 | T15: =IF(AND(R15>=dFrom,R15<=dTo),SUMIFS(tblClean[Attributed GMV PHP],tblClean[Date],">="&MAX(R15-6,dFrom),tblClean[Date],"<="&R15,tblClean[Host Name],dHost,tblClean[Include],1)/(R15-MAX(R15-6,dFrom)+1),NA()) -> 101330.86 | V15: ='Weekly Summary'!B14 -> 45866 | W15: =IF(AND(V15+6>=dFrom,V15<=dTo),SUMIFS(tblClean[Attributed GMV PHP],tblClean[Date],">="&MAX(V15,dFrom),tblClean[Date],"<="&MIN(V15+6,dTo),tblClean[Host Name],dHost,tblClean[Include],1),NA()) -> 1170261
R16: =R15+1 -> 45819 | S16: =IF(AND(R16>=dFrom,R16<=dTo),SUMIFS(tblClean[Attributed GMV PHP],tblClean[Date],R16,tblClean[Host Name],dHost,tblClean[Include],1),NA()) -> 93704 | T16: =IF(AND(R16>=dFrom,R16<=dTo),SUMIFS(tblClean[Attributed GMV PHP],tblClean[Date],">="&MAX(R16-6,dFrom),tblClean[Date],"<="&R16,tblClean[Host Name],dHost,tblClean[Include],1)/(R16-MAX(R16-6,dFrom)+1),NA()) -> 106208.29 | V16: ='Weekly Summary'!B15 -> 45873 | W16: =IF(AND(V16+6>=dFrom,V16<=dTo),SUMIFS(tblClean[Attributed GMV PHP],tblClean[Date],">="&MAX(V16,dFrom),tblClean[Date],"<="&MIN(V16+6,dTo),tblClean[Host Name],dHost,tblClean[Include],1),NA()) -> 1038468
R17: =R16+1 -> 45820 | S17: =IF(AND(R17>=dFrom,R17<=dTo),SUMIFS(tblClean[Attributed GMV PHP],tblClean[Date],R17,tblClean[Host Name],dHost,tblClean[Include],1),NA()) -> 36562 | T17: =IF(AND(R17>=dFrom,R17<=dTo),SUMIFS(tblClean[Attributed GMV PHP],tblClean[Date],">="&MAX(R17-6,dFrom),tblClean[Date],"<="&R17,tblClean[Host Name],dHost,tblClean[Include],1)/(R17-MAX(R17-6,dFrom)+1),NA()) -> 99407.857 | V17: ='Weekly Summary'!B16 -> 45880 | W17: =IF(AND(V17+6>=dFrom,V17<=dTo),SUMIFS(tblClean[Attributed GMV PHP],tblClean[Date],">="&MAX(V17,dFrom),tblClean[Date],"<="&MIN(V17+6,dTo),tblClean[Host Name],dHost,tblClean[Include],1),NA()) -> 888080
R18: =R17+1 -> 45821 | S18: =IF(AND(R18>=dFrom,R18<=dTo),SUMIFS(tblClean[Attributed GMV PHP],tblClean[Date],R18,tblClean[Host Name],dHost,tblClean[Include],1),NA()) -> 123902 | T18: =IF(AND(R18>=dFrom,R18<=dTo),SUMIFS(tblClean[Attributed GMV PHP],tblClean[Date],">="&MAX(R18-6,dFrom),tblClean[Date],"<="&R18,tblClean[Host Name],dHost,tblClean[Include],1)/(R18-MAX(R18-6,dFrom)+1),NA()) -> 91824 | V18: ='Weekly Summary'!B17 -> 45887 | W18: =IF(AND(V18+6>=dFrom,V18<=dTo),SUMIFS(tblClean[Attributed GMV PHP],tblClean[Date],">="&MAX(V18,dFrom),tblClean[Date],"<="&MIN(V18+6,dTo),tblClean[Host Name],dHost,tblClean[Include],1),NA()) -> 906631
R19: =R18+1 -> 45822 | S19: =IF(AND(R19>=dFrom,R19<=dTo),SUMIFS(tblClean[Attributed GMV PHP],tblClean[Date],R19,tblClean[Host Name],dHost,tblClean[Include],1),NA()) -> 134548 | T19: =IF(AND(R19>=dFrom,R19<=dTo),SUMIFS(tblClean[Attributed GMV PHP],tblClean[Date],">="&MAX(R19-6,dFrom),tblClean[Date],"<="&R19,tblClean[Host Name],dHost,tblClean[Include],1)/(R19-MAX(R19-6,dFrom)+1),NA()) -> 94419.429 | V19: ='Weekly Summary'!B18 -> 45894 | W19: =IF(AND(V19+6>=dFrom,V19<=dTo),SUMIFS(tblClean[Attributed GMV PHP],tblClean[Date],">="&MAX(V19,dFrom),tblClean[Date],"<="&MIN(V19+6,dTo),tblClean[Host Name],dHost,tblClean[Include],1),NA()) -> 793006
R20: =R19+1 -> 45823 | S20: =IF(AND(R20>=dFrom,R20<=dTo),SUMIFS(tblClean[Attributed GMV PHP],tblClean[Date],R20,tblClean[Host Name],dHost,tblClean[Include],1),NA()) -> 106367 | T20: =IF(AND(R20>=dFrom,R20<=dTo),SUMIFS(tblClean[Attributed GMV PHP],tblClean[Date],">="&MAX(R20-6,dFrom),tblClean[Date],"<="&R20,tblClean[Host Name],dHost,tblClean[Include],1)/(R20-MAX(R20-6,dFrom)+1),NA()) -> 99820.143
R21: =R20+1 -> 45824 | S21: =IF(AND(R21>=dFrom,R21<=dTo),SUMIFS(tblClean[Attributed GMV PHP],tblClean[Date],R21,tblClean[Host Name],dHost,tblClean[Include],1),NA()) -> 70318 | T21: =IF(AND(R21>=dFrom,R21<=dTo),SUMIFS(tblClean[Attributed GMV PHP],tblClean[Date],">="&MAX(R21-6,dFrom),tblClean[Date],"<="&R21,tblClean[Host Name],dHost,tblClean[Include],1)/(R21-MAX(R21-6,dFrom)+1),NA()) -> 96675.429
R22: =R21+1 -> 45825 | S22: =IF(AND(R22>=dFrom,R22<=dTo),SUMIFS(tblClean[Attributed GMV PHP],tblClean[Date],R22,tblClean[Host Name],dHost,tblClean[Include],1),NA()) -> 86201 | T22: =IF(AND(R22>=dFrom,R22<=dTo),SUMIFS(tblClean[Attributed GMV PHP],tblClean[Date],">="&MAX(R22-6,dFrom),tblClean[Date],"<="&R22,tblClean[Host Name],dHost,tblClean[Include],1)/(R22-MAX(R22-6,dFrom)+1),NA()) -> 93086
R23: =R22+1 -> 45826 | S23: =IF(AND(R23>=dFrom,R23<=dTo),SUMIFS(tblClean[Attributed GMV PHP],tblClean[Date],R23,tblClean[Host Name],dHost,tblClean[Include],1),NA()) -> 89868 | T23: =IF(AND(R23>=dFrom,R23<=dTo),SUMIFS(tblClean[Attributed GMV PHP],tblClean[Date],">="&MAX(R23-6,dFrom),tblClean[Date],"<="&R23,tblClean[Host Name],dHost,tblClean[Include],1)/(R23-MAX(R23-6,dFrom)+1),NA()) -> 92538
R24: =R23+1 -> 45827 | S24: =IF(AND(R24>=dFrom,R24<=dTo),SUMIFS(tblClean[Attributed GMV PHP],tblClean[Date],R24,tblClean[Host Name],dHost,tblClean[Include],1),NA()) -> 49961 | T24: =IF(AND(R24>=dFrom,R24<=dTo),SUMIFS(tblClean[Attributed GMV PHP],tblClean[Date],">="&MAX(R24-6,dFrom),tblClean[Date],"<="&R24,tblClean[Host Name],dHost,tblClean[Include],1)/(R24-MAX(R24-6,dFrom)+1),NA()) -> 94452.143
R25: =R24+1 -> 45828 | S25: =IF(AND(R25>=dFrom,R25<=dTo),SUMIFS(tblClean[Attributed GMV PHP],tblClean[Date],R25,tblClean[Host Name],dHost,tblClean[Include],1),NA()) -> 125088 | T25: =IF(AND(R25>=dFrom,R25<=dTo),SUMIFS(tblClean[Attributed GMV PHP],tblClean[Date],">="&MAX(R25-6,dFrom),tblClean[Date],"<="&R25,tblClean[Host Name],dHost,tblClean[Include],1)/(R25-MAX(R25-6,dFrom)+1),NA()) -> 94621.571
R26: =R25+1 -> 45829 | S26: =IF(AND(R26>=dFrom,R26<=dTo),SUMIFS(tblClean[Attributed GMV PHP],tblClean[Date],R26,tblClean[Host Name],dHost,tblClean[Include],1),NA()) -> 137301 | T26: =IF(AND(R26>=dFrom,R26<=dTo),SUMIFS(tblClean[Attributed GMV PHP],tblClean[Date],">="&MAX(R26-6,dFrom),tblClean[Date],"<="&R26,tblClean[Host Name],dHost,tblClean[Include],1)/(R26-MAX(R26-6,dFrom)+1),NA()) -> 95014.857
R27: =R26+1 -> 45830 | S27: =IF(AND(R27>=dFrom,R27<=dTo),SUMIFS(tblClean[Attributed GMV PHP],tblClean[Date],R27,tblClean[Host Name],dHost,tblClean[Include],1),NA()) -> 119977 | T27: =IF(AND(R27>=dFrom,R27<=dTo),SUMIFS(tblClean[Attributed GMV PHP],tblClean[Date],">="&MAX(R27-6,dFrom),tblClean[Date],"<="&R27,tblClean[Host Name],dHost,tblClean[Include],1)/(R27-MAX(R27-6,dFrom)+1),NA()) -> 96959.143
R28: =R27+1 -> 45831 | S28: =IF(AND(R28>=dFrom,R28<=dTo),SUMIFS(tblClean[Attributed GMV PHP],tblClean[Date],R28,tblClean[Host Name],dHost,tblClean[Include],1),NA()) -> 97093 | T28: =IF(AND(R28>=dFrom,R28<=dTo),SUMIFS(tblClean[Attributed GMV PHP],tblClean[Date],">="&MAX(R28-6,dFrom),tblClean[Date],"<="&R28,tblClean[Host Name],dHost,tblClean[Include],1)/(R28-MAX(R28-6,dFrom)+1),NA()) -> 100784.14
R29: =R28+1 -> 45832 | S29: =IF(AND(R29>=dFrom,R29<=dTo),SUMIFS(tblClean[Attributed GMV PHP],tblClean[Date],R29,tblClean[Host Name],dHost,tblClean[Include],1),NA()) -> 82009 | T29: =IF(AND(R29>=dFrom,R29<=dTo),SUMIFS(tblClean[Attributed GMV PHP],tblClean[Date],">="&MAX(R29-6,dFrom),tblClean[Date],"<="&R29,tblClean[Host Name],dHost,tblClean[Include],1)/(R29-MAX(R29-6,dFrom)+1),NA()) -> 100185.29
R30: =R29+1 -> 45833 | S30: =IF(AND(R30>=dFrom,R30<=dTo),SUMIFS(tblClean[Attributed GMV PHP],tblClean[Date],R30,tblClean[Host Name],dHost,tblClean[Include],1),NA()) -> 70932 | T30: =IF(AND(R30>=dFrom,R30<=dTo),SUMIFS(tblClean[Attributed GMV PHP],tblClean[Date],">="&MAX(R30-6,dFrom),tblClean[Date],"<="&R30,tblClean[Host Name],dHost,tblClean[Include],1)/(R30-MAX(R30-6,dFrom)+1),NA()) -> 97480.143
R31: =R30+1 -> 45834 | S31: =IF(AND(R31>=dFrom,R31<=dTo),SUMIFS(tblClean[Attributed GMV PHP],tblClean[Date],R31,tblClean[Host Name],dHost,tblClean[Include],1),NA()) -> 135191 | T31: =IF(AND(R31>=dFrom,R31<=dTo),SUMIFS(tblClean[Attributed GMV PHP],tblClean[Date],">="&MAX(R31-6,dFrom),tblClean[Date],"<="&R31,tblClean[Host Name],dHost,tblClean[Include],1)/(R31-MAX(R31-6,dFrom)+1),NA()) -> 109655.86
... R59: =R58+1 -> 45862 | S59: =IF(AND(R59>=dFrom,R59<=dTo),SUMIFS(tblClean[Attributed GMV PHP],tblClean[Date],R59,tblClean[Host Name],dHost,tblClean[Include],1),NA()) -> 163106 | T59: =IF(AND(R59>=dFrom,R59<=dTo),SUMIFS(tblClean[Attributed GMV PHP],tblClean[Date],">="&MAX(R59-6,dFrom),tblClean[Date],"<="&R59,tblClean[Host Name],dHost,tblClean[Include],1)/(R59-MAX(R59-6,dFrom)+1),NA()) -> 125957.43
B60: Portfolio project using synthetic data. Figures, hosts, and business information are fictional and do not represent any actual company's performance. GMV (gross merchandise value) is a sales-volume measure and is not net revenue, profit or cash received. Conversion rate and average order value are not shown because order and click counts are not in the dataset. | R60: =R59+1 -> 45863 | S60: =IF(AND(R60>=dFrom,R60<=dTo),SUMIFS(tblClean[Attributed GMV PHP],tblClean[Date],R60,tblClean[Host Name],dHost,tblClean[Include],1),NA()) -> 149585 | T60: =IF(AND(R60>=dFrom,R60<=dTo),SUMIFS(tblClean[Attributed GMV PHP],tblClean[Date],">="&MAX(R60-6,dFrom),tblClean[Date],"<="&R60,tblClean[Host Name],dHost,tblClean[Include],1)/(R60-MAX(R60-6,dFrom)+1),NA()) -> 126274
R61: =R60+1 -> 45864 | S61: =IF(AND(R61>=dFrom,R61<=dTo),SUMIFS(tblClean[Attributed GMV PHP],tblClean[Date],R61,tblClean[Host Name],dHost,tblClean[Include],1),NA()) -> 106730 | T61: =IF(AND(R61>=dFrom,R61<=dTo),SUMIFS(tblClean[Attributed GMV PHP],tblClean[Date],">="&MAX(R61-6,dFrom),tblClean[Date],"<="&R61,tblClean[Host Name],dHost,tblClean[Include],1)/(R61-MAX(R61-6,dFrom)+1),NA()) -> 125556.14
R62: =R61+1 -> 45865 | S62: =IF(AND(R62>=dFrom,R62<=dTo),SUMIFS(tblClean[Attributed GMV PHP],tblClean[Date],R62,tblClean[Host Name],dHost,tblClean[Include],1),NA()) -> 122907 | T62: =IF(AND(R62>=dFrom,R62<=dTo),SUMIFS(tblClean[Attributed GMV PHP],tblClean[Date],">="&MAX(R62-6,dFrom),tblClean[Date],"<="&R62,tblClean[Host Name],dHost,tblClean[Include],1)/(R62-MAX(R62-6,dFrom)+1),NA()) -> 112974
R63: =R62+1 -> 45866 | S63: =IF(AND(R63>=dFrom,R63<=dTo),SUMIFS(tblClean[Attributed GMV PHP],tblClean[Date],R63,tblClean[Host Name],dHost,tblClean[Include],1),NA()) -> 105663 | T63: =IF(AND(R63>=dFrom,R63<=dTo),SUMIFS(tblClean[Attributed GMV PHP],tblClean[Date],">="&MAX(R63-6,dFrom),tblClean[Date],"<="&R63,tblClean[Host Name],dHost,tblClean[Include],1)/(R63-MAX(R63-6,dFrom)+1),NA()) -> 115214.14
R64: =R63+1 -> 45867 | S64: =IF(AND(R64>=dFrom,R64<=dTo),SUMIFS(tblClean[Attributed GMV PHP],tblClean[Date],R64,tblClean[Host Name],dHost,tblClean[Include],1),NA()) -> 149525 | T64: =IF(AND(R64>=dFrom,R64<=dTo),SUMIFS(tblClean[Attributed GMV PHP],tblClean[Date],">="&MAX(R64-6,dFrom),tblClean[Date],"<="&R64,tblClean[Host Name],dHost,tblClean[Include],1)/(R64-MAX(R64-6,dFrom)+1),NA()) -> 128465.86
R65: =R64+1 -> 45868 | S65: =IF(AND(R65>=dFrom,R65<=dTo),SUMIFS(tblClean[Attributed GMV PHP],tblClean[Date],R65,tblClean[Host Name],dHost,tblClean[Include],1),NA()) -> 197202 | T65: =IF(AND(R65>=dFrom,R65<=dTo),SUMIFS(tblClean[Attributed GMV PHP],tblClean[Date],">="&MAX(R65-6,dFrom),tblClean[Date],"<="&R65,tblClean[Host Name],dHost,tblClean[Include],1)/(R65-MAX(R65-6,dFrom)+1),NA()) -> 142102.57
R66: =R65+1 -> 45869 | S66: =IF(AND(R66>=dFrom,R66<=dTo),SUMIFS(tblClean[Attributed GMV PHP],tblClean[Date],R66,tblClean[Host Name],dHost,tblClean[Include],1),NA()) -> 146612 | T66: =IF(AND(R66>=dFrom,R66<=dTo),SUMIFS(tblClean[Attributed GMV PHP],tblClean[Date],">="&MAX(R66-6,dFrom),tblClean[Date],"<="&R66,tblClean[Host Name],dHost,tblClean[Include],1)/(R66-MAX(R66-6,dFrom)+1),NA()) -> 139746.29
R67: =R66+1 -> 45870 | S67: =IF(AND(R67>=dFrom,R67<=dTo),SUMIFS(tblClean[Attributed GMV PHP],tblClean[Date],R67,tblClean[Host Name],dHost,tblClean[Include],1),NA()) -> 184262 | T67: =IF(AND(R67>=dFrom,R67<=dTo),SUMIFS(tblClean[Attributed GMV PHP],tblClean[Date],">="&MAX(R67-6,dFrom),tblClean[Date],"<="&R67,tblClean[Host Name],dHost,tblClean[Include],1)/(R67-MAX(R67-6,dFrom)+1),NA()) -> 144700.14
R68: =R67+1 -> 45871 | S68: =IF(AND(R68>=dFrom,R68<=dTo),SUMIFS(tblClean[Attributed GMV PHP],tblClean[Date],R68,tblClean[Host Name],dHost,tblClean[Include],1),NA()) -> 212937 | T68: =IF(AND(R68>=dFrom,R68<=dTo),SUMIFS(tblClean[Attributed GMV PHP],tblClean[Date],">="&MAX(R68-6,dFrom),tblClean[Date],"<="&R68,tblClean[Host Name],dHost,tblClean[Include],1)/(R68-MAX(R68-6,dFrom)+1),NA()) -> 159872.57
R69: =R68+1 -> 45872 | S69: =IF(AND(R69>=dFrom,R69<=dTo),SUMIFS(tblClean[Attributed GMV PHP],tblClean[Date],R69,tblClean[Host Name],dHost,tblClean[Include],1),NA()) -> 174060 | T69: =IF(AND(R69>=dFrom,R69<=dTo),SUMIFS(tblClean[Attributed GMV PHP],tblClean[Date],">="&MAX(R69-6,dFrom),tblClean[Date],"<="&R69,tblClean[Host Name],dHost,tblClean[Include],1)/(R69-MAX(R69-6,dFrom)+1),NA()) -> 167180.14
R70: =R69+1 -> 45873 | S70: =IF(AND(R70>=dFrom,R70<=dTo),SUMIFS(tblClean[Attributed GMV PHP],tblClean[Date],R70,tblClean[Host Name],dHost,tblClean[Include],1),NA()) -> 87593 | T70: =IF(AND(R70>=dFrom,R70<=dTo),SUMIFS(tblClean[Attributed GMV PHP],tblClean[Date],">="&MAX(R70-6,dFrom),tblClean[Date],"<="&R70,tblClean[Host Name],dHost,tblClean[Include],1)/(R70-MAX(R70-6,dFrom)+1),NA()) -> 164598.71
R71: =R70+1 -> 45874 | S71: =IF(AND(R71>=dFrom,R71<=dTo),SUMIFS(tblClean[Attributed GMV PHP],tblClean[Date],R71,tblClean[Host Name],dHost,tblClean[Include],1),NA()) -> 82980 | T71: =IF(AND(R71>=dFrom,R71<=dTo),SUMIFS(tblClean[Attributed GMV PHP],tblClean[Date],">="&MAX(R71-6,dFrom),tblClean[Date],"<="&R71,tblClean[Host Name],dHost,tblClean[Include],1)/(R71-MAX(R71-6,dFrom)+1),NA()) -> 155092.29
R72: =R71+1 -> 45875 | S72: =IF(AND(R72>=dFrom,R72<=dTo),SUMIFS(tblClean[Attributed GMV PHP],tblClean[Date],R72,tblClean[Host Name],dHost,tblClean[Include],1),NA()) -> 99313 | T72: =IF(AND(R72>=dFrom,R72<=dTo),SUMIFS(tblClean[Attributed GMV PHP],tblClean[Date],">="&MAX(R72-6,dFrom),tblClean[Date],"<="&R72,tblClean[Host Name],dHost,tblClean[Include],1)/(R72-MAX(R72-6,dFrom)+1),NA()) -> 141108.14
... R97: =R96+1 -> 45900 | S97: =IF(AND(R97>=dFrom,R97<=dTo),SUMIFS(tblClean[Attributed GMV PHP],tblClean[Date],R97,tblClean[Host Name],dHost,tblClean[Include],1),NA()) -> 134981 | T97: =IF(AND(R97>=dFrom,R97<=dTo),SUMIFS(tblClean[Attributed GMV PHP],tblClean[Date],">="&MAX(R97-6,dFrom),tblClean[Date],"<="&R97,tblClean[Host Name],dHost,tblClean[Include],1)/(R97-MAX(R97-6,dFrom)+1),NA()) -> 113286.57

Sheet Insights
A1: BUSINESS INSIGHTS
A2: Findings are formulas (they recalculate with the data). Interpretation and next steps describe observed results and possible explanations, not proven causes.
A4: # | B4: Business question | C4: Finding (calculated) | G4: Why it might matter | J4: Suggested next step
A5: 1 | B5: Which host generated the highest total GMV? | C5: =INDEX('Host Performance'!$A$6:$A$10,MATCH(1,'Host Performance'!$N$6:$N$10,0))&" generated the highest total GMV: ₱"&TEXT(MAX('Host Performance'!$D$6:$D$10),"#,##0")&" ("&TEXT(MAX('Host Performance'!$D$6:$D$10)/'Host Performance'!$D$11,"0.0%")&" of all GMV) from "&INDEX('Host Performance'!$B$6:$B$10,MATCH(1,'Host Performance'!$N$6:$N$10,0))&" sessions and "&TEXT(INDEX('Host Performance'!$C$6:$C$10,MATCH(1,'Host Performance'!$N$6:$N$10,0)),"#,##0.0")&" livestream hours." -> Bianca Reyes generated the highest total GMV: ₱3,731,707 (33.5% of all GMV) from 146 sessions and 352.0 livestream hours. | G5: Total GMV shows who contributes most to overall sales, but it also reflects how many hours and which time slots a host is scheduled for, so it measures contribution rather than skill. | J5: Read together with Insight 2 before calling this host the top performer; check how their hours are split across time slots.
A6: 2 | B6: Which host had the highest GMV per hour? | C6: =INDEX('Host Performance'!$A$6:$A$10,MATCH(1,'Host Performance'!$M$6:$M$10,0))&" had the highest GMV per hour (₱"&TEXT(INDEX('Host Performance'!$G$6:$G$10,MATCH(1,'Host Performance'!$M$6:$M$10,0)),"#,##0")&" vs ₱"&TEXT('Host Performance'!$G$11,"#,##0")&" overall). "&IF(INDEX('Host Performance'!$A$6:$A$10,MATCH(1,'Host Performance'!$M$6:$M$10,0))=INDEX('Host Performance'!$A$6:$A$10,MATCH(1,'Host Performance'!$N$6:$N$10,0)),"The same host also leads on total GMV.","The total-GMV leader, "&INDEX('Host Performance'!$A$6:$A$10,MATCH(1,'Host Performance'!$N$6:$N$10,0))&", ranks #"&INDEX('Host Performance'!$M$6:$M$10,MATCH(1,'Host Performance'!$N$6:$N$10,0))&" on efficiency (₱"&TEXT(INDEX('Host Performance'!$G$6:$G$10,MATCH(1,'Host Performance'!$N$6:$N$10,0)),"#,##0")&" per hour).") -> Aira Valdez had the highest GMV per hour (₱22,803 vs ₱12,595 overall). The total-GMV leader, Bianca Reyes, ranks #4 on efficiency (₱10,601 per hour). | G6: GMV per hour adjusts for time on air, so it is a fairer comparison of selling efficiency when hosts stream different amounts. Differences between the two rankings show where volume and efficiency diverge. | J6: Test giving the efficiency leader additional prime slots, then check whether GMV per hour holds as hours increase.
A7: 3 | B7: Which week recorded the highest GMV? | C7: ="Week "&C52&" ("&TEXT(INDEX('Weekly Summary'!$B$6:$B$18,C52),"d mmm")&" – "&TEXT(INDEX('Weekly Summary'!$C$6:$C$18,C52),"d mmm yyyy")&") recorded the highest weekly GMV at ₱"&TEXT(C53,"#,##0")&", "&TEXT(C53/C56-1,"0%")&" above the average week (₱"&TEXT(C56,"#,##0")&"). The lowest was week "&C54&" (₱"&TEXT(C55,"#,##0")&")." -> Week 9 (28 Jul – 3 Aug 2025) recorded the highest weekly GMV at ₱1,170,261, 36% above the average week (₱857,930). The lowest was week 3 (₱678,714). | G7: Peak and low weeks show how volatile sales are. Promotions, paydays or a handful of unusually strong sessions can lift a single week, so the peak may not be repeatable. | J7: Filter Cleaned Data to that week and review the top sessions to see if the peak was broad-based or driven by a few sessions; tag campaign dates in future data.
A8: 4 | B8: Is GMV increasing or decreasing across the period? | C8: ="Average weekly GMV "&IF(C50>=0,"rose","fell")&" from ₱"&TEXT(C48,"#,##0")&" (weeks 1–4) to ₱"&TEXT(C49,"#,##0")&" (weeks 10–13), a change of "&TEXT(C50,"+0.0%;-0.0%")&". The fitted linear trend is "&IF(C51>=0,"+","-")&"₱"&TEXT(ABS(C51),"#,##0")&" per week, and GMV fell week-over-week in "&C57&" of "&C58&" comparisons." -> Average weekly GMV rose from ₱723,014 (weeks 1–4) to ₱906,546 (weeks 10–13), a change of +25.4%. The fitted linear trend is +₱18,111 per week, and GMV fell week-over-week in 7 of 12 comparisons. | G8: Direction over 13 weeks hints at whether the channel is growing, but weekly GMV is noisy and 13 data points are too few to call a sustained trend. | J8: Extend the tracker with more weeks and compare against promotion dates before drawing a conclusion about growth.
A9: 5 | B9: Which hosts sold the most items? | C9: =INDEX('Host Performance'!$A$6:$A$10,MATCH(MAX('Host Performance'!$E$6:$E$10),'Host Performance'!$E$6:$E$10,0))&" sold the most items ("&TEXT(MAX('Host Performance'!$E$6:$E$10),"#,##0")&" units, "&TEXT(MAX('Host Performance'!$E$6:$E$10)/'Host Performance'!$E$11,"0.0%")&" of all items). "&INDEX('Host Performance'!$A$6:$A$10,MATCH(MAX('Host Performance'!$H$6:$H$10),'Host Performance'!$H$6:$H$10,0))&" had the highest average items per session ("&TEXT(MAX('Host Performance'!$H$6:$H$10),"0.0")&" vs "&TEXT('Host Performance'!$H$11,"0.0")&" overall)." -> Bianca Reyes sold the most items (11,230 units, 33.9% of all items). Aira Valdez had the highest average items per session (150.4 vs 88.5 overall). | G9: Units sold reflect throughput and can rank hosts differently from GMV because of product mix and price points. Observed differences are not proof of better selling. | J9: Add product category or SKU fields to separate price-mix effects from sales volume.
A10: 6 | B10: How does performance vary by day of the week? | C10: ="GMV per hour was highest on "&INDEX(B22:B28,MATCH(MAX(F22:F28),F22:F28,0))&" (₱"&TEXT(MAX(F22:F28),"#,##0")&") and lowest on "&INDEX(B22:B28,MATCH(MIN(F22:F28),F22:F28,0))&" (₱"&TEXT(MIN(F22:F28),"#,##0")&"). Weekends averaged ₱"&TEXT(F30,"#,##0")&" per hour versus ₱"&TEXT(F29,"#,##0")&" on weekdays ("&TEXT(F30/F29-1,"+0%;-0%")&")." -> GMV per hour was highest on Sat (₱14,938) and lowest on Wed (₱10,121). Weekends averaged ₱14,868 per hour versus ₱11,666 on weekdays (+27%). | G10: Day-of-week patterns inform scheduling and staffing. Hosts are not scheduled evenly across days, so part of the pattern may come from who streams when. | J10: Prioritise key launches on the strongest days and test shifting weaker days only after confirming the pattern persists with more weeks.
A11: 7 | B11: Are longer livestreams associated with higher GMV? | C11: ="Session duration and session GMV show a "&IF(ABS(E37)<0.1,"negligible",IF(ABS(E37)<0.3,"weak",IF(ABS(E37)<0.5,"moderate","strong")))&IF(E37>=0," positive"," negative")&" correlation (r = "&TEXT(E37,"0.00")&"). Long sessions (3h+) averaged ₱"&TEXT(E36,"#,##0")&" GMV per session versus ₱"&TEXT(E34,"#,##0")&" for short ones (under 2h), but GMV per hour was ₱"&TEXT(F36,"#,##0")&" versus ₱"&TEXT(F34,"#,##0")&"." -> Session duration and session GMV show a weak positive correlation (r = 0.18). Long sessions (3h+) averaged ₱33,787 GMV per session versus ₱23,172 for short ones (under 2h), but GMV per hour was ₱11,262 versus ₱15,448. | G11: This tests whether extra airtime tends to pay off. A weak correlation suggests duration alone explains little of session GMV; longer shows may also earn less per hour. | J11: Compare sessions of different lengths within the same host and time slot before changing schedule length. Correlation does not show that longer streams cause higher GMV.
A12: 8 | B12: Which host may warrant further investigation? | C12: =INDEX('Host Performance'!$A$6:$A$10,MATCH(MAX('Host Performance'!$M$6:$M$10),'Host Performance'!$M$6:$M$10,0))&" has the lowest GMV per hour (₱"&TEXT(INDEX('Host Performance'!$G$6:$G$10,MATCH(MAX('Host Performance'!$M$6:$M$10),'Host Performance'!$M$6:$M$10,0)),"#,##0")&", "&TEXT(1-INDEX('Host Performance'!$G$6:$G$10,MATCH(MAX('Host Performance'!$M$6:$M$10),'Host Performance'!$M$6:$M$10,0))/'Host Performance'!$G$11,"0%")&" below the overall rate). It produced "&TEXT(INDEX('Host Performance'!$I$6:$I$10,MATCH(MAX('Host Performance'!$M$6:$M$10),'Host Performance'!$M$6:$M$10,0)),"0.0%")&" of GMV from "&TEXT(INDEX('Host Performance'!$J$6:$J$10,MATCH(MAX('Host Performance'!$M$6:$M$10),'Host Performance'!$M$6:$M$10,0)),"0.0%")&" of livestream hours (efficiency index "&TEXT(INDEX('Host Performance'!$K$6:$K$10,MATCH(MAX('Host Performance'!$M$6:$M$10),'Host Performance'!$M$6:$M$10,0)),"0.00")&")." -> Dani Villanueva has the lowest GMV per hour (₱7,947, 37% below the overall rate). It produced 11.7% of GMV from 18.5% of livestream hours (efficiency index 0.63). | G12: A host whose share of GMV is below their share of airtime is using hours less productively. Possible causes (slot mix, product assortment, session length, experience) cannot be separated with this data. | J12: Compare this host with others within the same time slots (Host × Time Slot table on Host Performance), review their best and worst sessions, then consider coaching or schedule changes.
A14: Reading notes
B15: • All figures are synthetic and come from the 374-row sample dataset; they illustrate method, not a real business.
B16: • GMV is gross merchandise value attributed to livestream sessions. It is not revenue, profit or cash received, and returns/cancellations are not modelled.
B17: • Overall and host-level GMV per hour = total GMV ÷ total hours (weighted), never an average of session rates.
B18: • Findings describe what happened in the data. Explanations are hypotheses that would need further data or testing.
A19: SUPPORTING ANALYSIS (feeds the findings above)
B20: A. Performance by day of week
B21: Day | C21: Sessions | D21: Hours | E21: Total GMV | F21: GMV per Hour | G21: Avg GMV per Session
B22: Mon | C22: =COUNTIFS(tblClean[Day of Week],$B22,tblClean[Include],1) -> 50 | D22: =SUMIFS(tblClean[Duration Hours],tblClean[Day of Week],$B22,tblClean[Include],1) -> 115.5 | E22: =SUMIFS(tblClean[Attributed GMV PHP],tblClean[Day of Week],$B22,tblClean[Include],1) -> 1315187 | F22: =IF(D22>0,E22/D22,0) -> 11386.9 | G22: =IF(C22>0,E22/C22,0) -> 26303.74
B23: Tue | C23: =COUNTIFS(tblClean[Day of Week],$B23,tblClean[Include],1) -> 53 | D23: =SUMIFS(tblClean[Duration Hours],tblClean[Day of Week],$B23,tblClean[Include],1) -> 124.5 | E23: =SUMIFS(tblClean[Attributed GMV PHP],tblClean[Day of Week],$B23,tblClean[Include],1) -> 1307438 | F23: =IF(D23>0,E23/D23,0) -> 10501.51 | G23: =IF(C23>0,E23/C23,0) -> 24668.642
B24: Wed | C24: =COUNTIFS(tblClean[Day of Week],$B24,tblClean[Include],1) -> 57 | D24: =SUMIFS(tblClean[Duration Hours],tblClean[Day of Week],$B24,tblClean[Include],1) -> 139 | E24: =SUMIFS(tblClean[Attributed GMV PHP],tblClean[Day of Week],$B24,tblClean[Include],1) -> 1406832 | F24: =IF(D24>0,E24/D24,0) -> 10121.094 | G24: =IF(C24>0,E24/C24,0) -> 24681.263
B25: Thu | C25: =COUNTIFS(tblClean[Day of Week],$B25,tblClean[Include],1) -> 52 | D25: =SUMIFS(tblClean[Duration Hours],tblClean[Day of Week],$B25,tblClean[Include],1) -> 117.5 | E25: =SUMIFS(tblClean[Attributed GMV PHP],tblClean[Day of Week],$B25,tblClean[Include],1) -> 1447913 | F25: =IF(D25>0,E25/D25,0) -> 12322.664 | G25: =IF(C25>0,E25/C25,0) -> 27844.481
B26: Fri | C26: =COUNTIFS(tblClean[Day of Week],$B26,tblClean[Include],1) -> 54 | D26: =SUMIFS(tblClean[Duration Hours],tblClean[Day of Week],$B26,tblClean[Include],1) -> 132 | E26: =SUMIFS(tblClean[Attributed GMV PHP],tblClean[Day of Week],$B26,tblClean[Include],1) -> 1854576 | F26: =IF(D26>0,E26/D26,0) -> 14049.818 | G26: =IF(C26>0,E26/C26,0) -> 34344
B27: Sat | C27: =COUNTIFS(tblClean[Day of Week],$B27,tblClean[Include],1) -> 53 | D27: =SUMIFS(tblClean[Duration Hours],tblClean[Day of Week],$B27,tblClean[Include],1) -> 121.5 | E27: =SUMIFS(tblClean[Attributed GMV PHP],tblClean[Day of Week],$B27,tblClean[Include],1) -> 1814928 | F27: =IF(D27>0,E27/D27,0) -> 14937.679 | G27: =IF(C27>0,E27/C27,0) -> 34243.925
B28: Sun | C28: =COUNTIFS(tblClean[Day of Week],$B28,tblClean[Include],1) -> 55 | D28: =SUMIFS(tblClean[Duration Hours],tblClean[Day of Week],$B28,tblClean[Include],1) -> 135.5 | E28: =SUMIFS(tblClean[Attributed GMV PHP],tblClean[Day of Week],$B28,tblClean[Include],1) -> 2006221 | F28: =IF(D28>0,E28/D28,0) -> 14806.059 | G28: =IF(C28>0,E28/C28,0) -> 36476.745
B29: Weekday | C29: =COUNTIFS(tblClean[Day Type],$B29,tblClean[Include],1) -> 266 | D29: =SUMIFS(tblClean[Duration Hours],tblClean[Day Type],$B29,tblClean[Include],1) -> 628.5 | E29: =SUMIFS(tblClean[Attributed GMV PHP],tblClean[Day Type],$B29,tblClean[Include],1) -> 7331946 | F29: =IF(D29>0,E29/D29,0) -> 11665.785 | G29: =IF(C29>0,E29/C29,0) -> 27563.707
B30: Weekend | C30: =COUNTIFS(tblClean[Day Type],$B30,tblClean[Include],1) -> 108 | D30: =SUMIFS(tblClean[Duration Hours],tblClean[Day Type],$B30,tblClean[Include],1) -> 257 | E30: =SUMIFS(tblClean[Attributed GMV PHP],tblClean[Day Type],$B30,tblClean[Include],1) -> 3821149 | F30: =IF(D30>0,E30/D30,0) -> 14868.284 | G30: =IF(C30>0,E30/C30,0) -> 35381.009
B32: B. Performance by livestream duration band
B33: Duration band | C33: Sessions | D33: Avg Duration (h) | E33: Avg GMV per Session | F33: GMV per Hour
B34: Short (under 2h) | C34: =COUNTIFS(tblClean[Duration Band],$B34,tblClean[Include],1) -> 36 | D34: =IF(C34>0,SUMIFS(tblClean[Duration Hours],tblClean[Duration Band],$B34,tblClean[Include],1)/C34,0) -> 1.5 | E34: =IF(C34>0,SUMIFS(tblClean[Attributed GMV PHP],tblClean[Duration Band],$B34,tblClean[Include],1)/C34,0) -> 23172.056 | F34: =IFERROR(SUMIFS(tblClean[Attributed GMV PHP],tblClean[Duration Band],$B34,tblClean[Include],1)/SUMIFS(tblClean[Duration Hours],tblClean[Duration Band],$B34,tblClean[Include],1),0) -> 15448.037
B35: Standard (2h to under 3h) | C35: =COUNTIFS(tblClean[Duration Band],$B35,tblClean[Include],1) -> 238 | D35: =IF(C35>0,SUMIFS(tblClean[Duration Hours],tblClean[Duration Band],$B35,tblClean[Include],1)/C35,0) -> 2.2331933 | E35: =IF(C35>0,SUMIFS(tblClean[Attributed GMV PHP],tblClean[Duration Band],$B35,tblClean[Include],1)/C35,0) -> 29160.483 | F35: =IFERROR(SUMIFS(tblClean[Attributed GMV PHP],tblClean[Duration Band],$B35,tblClean[Include],1)/SUMIFS(tblClean[Duration Hours],tblClean[Duration Band],$B35,tblClean[Include],1),0) -> 13057.752
B36: Long (3h or more) | C36: =COUNTIFS(tblClean[Duration Band],$B36,tblClean[Include],1) -> 100 | D36: =IF(C36>0,SUMIFS(tblClean[Duration Hours],tblClean[Duration Band],$B36,tblClean[Include],1)/C36,0) -> 3 | E36: =IF(C36>0,SUMIFS(tblClean[Attributed GMV PHP],tblClean[Duration Band],$B36,tblClean[Include],1)/C36,0) -> 33787.06 | F36: =IFERROR(SUMIFS(tblClean[Attributed GMV PHP],tblClean[Duration Band],$B36,tblClean[Include],1)/SUMIFS(tblClean[Duration Hours],tblClean[Duration Band],$B36,tblClean[Include],1),0) -> 11262.353
B37: Correlation r: duration vs session GMV | E37: =CORREL(tblClean[Duration Hours],tblClean[Attributed GMV PHP]) -> 0.18451685
B39: C. Performance by time slot (session start)
B40: Time slot | C40: Sessions | D40: Hours | E40: Total GMV | F40: GMV per Hour
B41: Morning | C41: =COUNTIFS(tblClean[Time Slot],$B41,tblClean[Include],1) -> 62 | D41: =SUMIFS(tblClean[Duration Hours],tblClean[Time Slot],$B41,tblClean[Include],1) -> 150.5 | E41: =SUMIFS(tblClean[Attributed GMV PHP],tblClean[Time Slot],$B41,tblClean[Include],1) -> 1108150 | F41: =IF(D41>0,E41/D41,0) -> 7363.1229
B42: Afternoon | C42: =COUNTIFS(tblClean[Time Slot],$B42,tblClean[Include],1) -> 73 | D42: =SUMIFS(tblClean[Duration Hours],tblClean[Time Slot],$B42,tblClean[Include],1) -> 174.5 | E42: =SUMIFS(tblClean[Attributed GMV PHP],tblClean[Time Slot],$B42,tblClean[Include],1) -> 1875300 | F42: =IF(D42>0,E42/D42,0) -> 10746.705
B43: Early Evening | C43: =COUNTIFS(tblClean[Time Slot],$B43,tblClean[Include],1) -> 84 | D43: =SUMIFS(tblClean[Duration Hours],tblClean[Time Slot],$B43,tblClean[Include],1) -> 204.5 | E43: =SUMIFS(tblClean[Attributed GMV PHP],tblClean[Time Slot],$B43,tblClean[Include],1) -> 2552692 | F43: =IF(D43>0,E43/D43,0) -> 12482.601
B44: Prime Time | C44: =COUNTIFS(tblClean[Time Slot],$B44,tblClean[Include],1) -> 91 | D44: =SUMIFS(tblClean[Duration Hours],tblClean[Time Slot],$B44,tblClean[Include],1) -> 204.5 | E44: =SUMIFS(tblClean[Attributed GMV PHP],tblClean[Time Slot],$B44,tblClean[Include],1) -> 3756933 | F44: =IF(D44>0,E44/D44,0) -> 18371.311
B45: Late Night | C45: =COUNTIFS(tblClean[Time Slot],$B45,tblClean[Include],1) -> 64 | D45: =SUMIFS(tblClean[Duration Hours],tblClean[Time Slot],$B45,tblClean[Include],1) -> 151.5 | E45: =SUMIFS(tblClean[Attributed GMV PHP],tblClean[Time Slot],$B45,tblClean[Include],1) -> 1860020 | F45: =IF(D45>0,E45/D45,0) -> 12277.36
B47: D. Trend and peak-week statistics
B48: Avg weekly GMV, weeks 1–4 | C48: =AVERAGE('Weekly Summary'!D6:D9) -> 723013.75
B49: Avg weekly GMV, weeks 10–13 | C49: =AVERAGE('Weekly Summary'!D15:D18) -> 906546.25
B50: Change, weeks 10–13 vs 1–4 | C50: =IF(C48>0,(C49-C48)/C48,0) -> 0.25384372
B51: Linear trend (PHP per week) | C51: =SLOPE('Weekly Summary'!$D$6:$D$18,'Weekly Summary'!$A$6:$A$18) -> 18110.604
B52: Peak week # | C52: =INDEX('Weekly Summary'!$A$6:$A$18,MATCH(MAX('Weekly Summary'!$D$6:$D$18),'Weekly Summary'!$D$6:$D$18,0)) -> 9
B53: Peak week GMV | C53: =MAX('Weekly Summary'!$D$6:$D$18) -> 1170261
B54: Lowest week # | C54: =INDEX('Weekly Summary'!$A$6:$A$18,MATCH(MIN('Weekly Summary'!$D$6:$D$18),'Weekly Summary'!$D$6:$D$18,0)) -> 3
B55: Lowest week GMV | C55: =MIN('Weekly Summary'!$D$6:$D$18) -> 678714
B56: Average weekly GMV | C56: =AVERAGE('Weekly Summary'!$D$6:$D$18) -> 857930.38
B57: Weeks with WoW GMV decline | C57: =COUNTIF('Weekly Summary'!$I$6:$I$18,"<0") -> 7
B58: Week-over-week comparisons | C58: =COUNT('Weekly Summary'!$D$6:$D$18)-1 -> 12
